Workbook

Sheet Resumo
B1: PAINEL DE CUSTOS — GRUPO DTEL | E1: MES_BLOCO | F1: OFFSET
E2: ABRIL/2026 | F2: 2
B3: Selecione o mês: | C3: 46204 | E3: MAIO/2026 | F3: 61
E4: JUNHO/2026 | F4: 120
B5: Adm atendimento | E5: JULHO/2026 | F5: 179
B6: Comercial corporativo
B7: Compras
B8: Configuração
B9: Contabilidade
B10: Desenvolvimento
B11: DP
B12: Engenharia - Adm Engenharia
B13: Engenharia - Equipe de Josadark
B14: Engenharia - Equipe de Leonardo
B15: Estoque
B16: Financeiro
B17: Fique móvel
... B26: TOTAL SETORES
B28: COMERCIAL — POR EMPRESA | C28: TOTAL
B29: DTEL
B30: DX2
B31: VOICE NET
B32: SOARES E SILVA
B33: SOARES E LINS
B34: SOUZA E SILVA
B35: LITORAL NET
B36: TOTAL COMERCIAL
B38: REEMBOLSO GERAL
B40: TOTAL GERAL DO MÊS

Sheet Base Setores
A1: MÊS | B1: SETOR | C1: DESPESA | D1: QTD | E1: VALOR UN. | F1: VALOR TOTAL | G1: OBS | H1: Nº CLIENTES | I1: BASE DE CLIENTES | J1: CUSTO UNIT. / CLIENTE (R$) | L1: TOTAL (respeita o filtro):
A2: ABRIL/2026 | B2: Adm atendimento | C2: Folha trabalhista | D2: 10 | E2: 33427.48 | F2: =E2 -> 33427.48 | H2: 189453 | I2: Clientes, com H&A | J2: =IFERROR(SUMIFS($F$2:$F$1749,$A$2:$A$1749,A2,$B$2:$B$1749,B2)/H2,"") -> 0.1870984
A3: ABRIL/2026 | B3: Adm atendimento | C3: Seg. Trabalho | D3: 10 | E3: 45.310245 | F3: =D3*E3 -> 453.10245 | H3: 189453 | I3: Clientes, com H&A | J3: =IFERROR(SUMIFS($F$2:$F$1749,$A$2:$A$1749,A3,$B$2:$B$1749,B3)/H3,"") -> 0.1870984
A4: ABRIL/2026 | B4: Adm atendimento | C4: RH | D4: 10 | E4: 24.798868 | F4: =D4*E4 -> 247.98868 | H4: 189453 | I4: Clientes, com H&A | J4: =IFERROR(SUMIFS($F$2:$F$1749,$A$2:$A$1749,A4,$B$2:$B$1749,B4)/H4,"") -> 0.1870984
A5: ABRIL/2026 | B5: Adm atendimento | C5: DP | D5: 10 | E5: 40.668213 | F5: =D5*E5 -> 406.68213 | H5: 189453 | I5: Clientes, com H&A | J5: =IFERROR(SUMIFS($F$2:$F$1749,$A$2:$A$1749,A5,$B$2:$B$1749,B5)/H5,"") -> 0.1870984
A6: ABRIL/2026 | B6: Adm atendimento | C6: EMAIL | D6: 10 | E6: 50 | F6: =D6*E6 -> 500 | H6: 189453 | I6: Clientes, com H&A | J6: =IFERROR(SUMIFS($F$2:$F$1749,$A$2:$A$1749,A6,$B$2:$B$1749,B6)/H6,"") -> 0.1870984
A7: ABRIL/2026 | B7: Adm atendimento | C7: Linhas moveis fique movel | D7: 5 | E7: 30 | F7: =D7*E7 -> 150 | H7: 189453 | I7: Clientes, com H&A | J7: =IFERROR(SUMIFS($F$2:$F$1749,$A$2:$A$1749,A7,$B$2:$B$1749,B7)/H7,"") -> 0.1870984
A8: ABRIL/2026 | B8: Adm atendimento | C8: Gympass | D8: 10 | E8: 10.15 | F8: =D8*E8 -> 101.5 | H8: 189453 | I8: Clientes, com H&A | J8: =IFERROR(SUMIFS($F$2:$F$1749,$A$2:$A$1749,A8,$B$2:$B$1749,B8)/H8,"") -> 0.1870984
A9: ABRIL/2026 | B9: Adm atendimento | C9: Stargrid | D9: 10 | E9: 2.92 | F9: =D9*E9 -> 29.2 | H9: 189453 | I9: Clientes, com H&A | J9: =IFERROR(SUMIFS($F$2:$F$1749,$A$2:$A$1749,A9,$B$2:$B$1749,B9)/H9,"") -> 0.1870984
A10: ABRIL/2026 | B10: Adm atendimento | C10: Rescisões | D10: 0 | E10: 0 | F10: =D10*E10 -> 0 | H10: 189453 | I10: Clientes, com H&A | J10: =IFERROR(SUMIFS($F$2:$F$1749,$A$2:$A$1749,A10,$B$2:$B$1749,B10)/H10,"") -> 0.1870984
A11: ABRIL/2026 | B11: Adm atendimento | C11: Fardamento | D11: 0 | E11: 0 | F11: =D11*E11 -> 0 | H11: 189453 | I11: Clientes, com H&A | J11: =IFERROR(SUMIFS($F$2:$F$1749,$A$2:$A$1749,A11,$B$2:$B$1749,B11)/H11,"") -> 0.1870984
A12: ABRIL/2026 | B12: Adm atendimento | C12: Fardamento substituição | D12: 0 | E12: 0 | F12: =D12*E12 -> 0 | H12: 189453 | I12: Clientes, com H&A | J12: =IFERROR(SUMIFS($F$2:$F$1749,$A$2:$A$1749,A12,$B$2:$B$1749,B12)/H12,"") -> 0.1870984
A13: ABRIL/2026 | B13: Adm atendimento | C13: Exames médicos | D13: 0 | E13: 0 | F13: =D13*E13 -> 0 | H13: 189453 | I13: Clientes, com H&A | J13: =IFERROR(SUMIFS($F$2:$F$1749,$A$2:$A$1749,A13,$B$2:$B$1749,B13)/H13,"") -> 0.1870984
A14: ABRIL/2026 | B14: Adm atendimento | C14: Mat. uso coletivo | D14: 1 | E14: 130.4 | F14: =D14*E14 -> 130.4 | G14: Total dos itens (Materiais dos setores.xlsx) | H14: 189453 | I14: Clientes, com H&A | J14: =IFERROR(SUMIFS($F$2:$F$1749,$A$2:$A$1749,A14,$B$2:$B$1749,B14)/H14,"") -> 0.1870984
A15: ABRIL/2026 | B15: Adm atendimento | C15: Mat. Escritório | D15: 1 | E15: 0 | F15: =D15*E15 -> 0 | G15: Total dos itens (Materiais dos setores.xlsx) | H15: 189453 | I15: Clientes, com H&A | J15: =IFERROR(SUMIFS($F$2:$F$1749,$A$2:$A$1749,A15,$B$2:$B$1749,B15)/H15,"") -> 0.1870984
A16: ABRIL/2026 | B16: Adm atendimento | C16: Alimentação | D16: 0 | E16: 0 | F16: =D16*E16 -> 0 | H16: 189453 | I16: Clientes, com H&A | J16: =IFERROR(SUMIFS($F$2:$F$1749,$A$2:$A$1749,A16,$B$2:$B$1749,B16)/H16,"") -> 0.1870984
A17: ABRIL/2026 | B17: C.O.E | C17: Folha trabalhista | D17: 15 | E17: 73051.42 | F17: =E17 -> 73051.42 | H17: 165302 | I17: Clientes | J17: =IFERROR(SUMIFS($F$2:$F$1749,$A$2:$A$1749,A17,$B$2:$B$1749,B17)/H17,"") -> 0.45770245
A18: ABRIL/2026 | B18: C.O.E | C18: Seg. Trabalho | D18: 15 | E18: 45.310245 | F18: =D18*E18 -> 679.65367 | H18: 165302 | I18: Clientes | J18: =IFERROR(SUMIFS($F$2:$F$1749,$A$2:$A$1749,A18,$B$2:$B$1749,B18)/H18,"") -> 0.45770245
A19: ABRIL/2026 | B19: C.O.E | C19: RH | D19: 15 | E19: 24.798868 | F19: =D19*E19 -> 371.98302 | H19: 165302 | I19: Clientes | J19: =IFERROR(SUMIFS($F$2:$F$1749,$A$2:$A$1749,A19,$B$2:$B$1749,B19)/H19,"") -> 0.45770245
A20: ABRIL/2026 | B20: C.O.E | C20: DP | D20: 15 | E20: 40.668213 | F20: =D20*E20 -> 610.02319 | H20: 165302 | I20: Clientes | J20: =IFERROR(SUMIFS($F$2:$F$1749,$A$2:$A$1749,A20,$B$2:$B$1749,B20)/H20,"") -> 0.45770245
A21: ABRIL/2026 | B21: C.O.E | C21: EMAIL | D21: 6 | E21: 50 | F21: =D21*E21 -> 300 | H21: 165302 | I21: Clientes | J21: =IFERROR(SUMIFS($F$2:$F$1749,$A$2:$A$1749,A21,$B$2:$B$1749,B21)/H21,"") -> 0.45770245
A22: ABRIL/2026 | B22: C.O.E | C22: Exames medicos | D22: 0 | E22: 0 | F22: =D22*E22 -> 0 | H22: 165302 | I22: Clientes | J22: =IFERROR(SUMIFS($F$2:$F$1749,$A$2:$A$1749,A22,$B$2:$B$1749,B22)/H22,"") -> 0.45770245
A23: ABRIL/2026 | B23: C.O.E | C23: Linhas moveis vivo | D23: 0 | E23: 0 | F23: =D23*E23 -> 0 | H23: 165302 | I23: Clientes | J23: =IFERROR(SUMIFS($F$2:$F$1749,$A$2:$A$1749,A23,$B$2:$B$1749,B23)/H23,"") -> 0.45770245
A24: ABRIL/2026 | B24: C.O.E | C24: Linhas moveis fique movel | D24: 15 | E24: 30 | F24: =D24*E24 -> 450 | H24: 165302 | I24: Clientes | J24: =IFERROR(SUMIFS($F$2:$F$1749,$A$2:$A$1749,A24,$B$2:$B$1749,B24)/H24,"") -> 0.45770245
A25: ABRIL/2026 | B25: C.O.E | C25: Impressora | D25: 0 | E25: 0 | F25: =D25*E25 -> 0 | H25: 165302 | I25: Clientes | J25: =IFERROR(SUMIFS($F$2:$F$1749,$A$2:$A$1749,A25,$B$2:$B$1749,B25)/H25,"") -> 0.45770245
A26: ABRIL/2026 | B26: C.O.E | C26: Gympass | D26: 15 | E26: 10.15 | F26: =D26*E26 -> 152.25 | H26: 165302 | I26: Clientes | J26: =IFERROR(SUMIFS($F$2:$F$1749,$A$2:$A$1749,A26,$B$2:$B$1749,B26)/H26,"") -> 0.45770245
A27: ABRIL/2026 | B27: C.O.E | C27: Stargrid | D27: 15 | E27: 2.92 | F27: =D27*E27 -> 43.8 | H27: 165302 | I27: Clientes | J27: =IFERROR(SUMIFS($F$2:$F$1749,$A$2:$A$1749,A27,$B$2:$B$1749,B27)/H27,"") -> 0.45770245
A28: ABRIL/2026 | B28: C.O.E | C28: Rescisões Trabalhistas | D28: 0 | E28: 0 | F28: =D28*E28 -> 0 | H28: 165302 | I28: Clientes | J28: =IFERROR(SUMIFS($F$2:$F$1749,$A$2:$A$1749,A28,$B$2:$B$1749,B28)/H28,"") -> 0.45770245
A29: ABRIL/2026 | B29: C.O.E | C29: Fardamento novo | D29: 0 | E29: 0 | F29: =D29*E29 -> 0 | H29: 165302 | I29: Clientes | J29: =IFERROR(SUMIFS($F$2:$F$1749,$A$2:$A$1749,A29,$B$2:$B$1749,B29)/H29,"") -> 0.45770245
... A32: ABRIL/2026 | B32: C.O.E | C32: Mat. uso coletivo | D32: 0 | E32: 0 | F32: =D32*E32 -> 0 | H32: 165302 | I32: Clientes | J32: =IFERROR(SUMIFS($F$2:$F$1749,$A$2:$A$1749,A32,$B$2:$B$1749,B32)/H32,"") -> 0.45770245
A33: ABRIL/2026 | B33: Comercial corporativo | C33: Folha trabalhista | D33: 9 | E33: 88730.25 | F33: =E33 -> 88730.25 | H33: 189453 | I33: Clientes, com H&A | J33: =IFERROR(SUMIFS($F$2:$F$1749,$A$2:$A$1749,A33,$B$2:$B$1749,B33)/H33,"") -> 0.52393985
A34: ABRIL/2026 | B34: Comercial corporativo | C34: Seg. Trabalho | D34: 9 | E34: 45.310245 | F34: =D34*E34 -> 407.7922 | H34: 189453 | I34: Clientes, com H&A | J34: =IFERROR(SUMIFS($F$2:$F$1749,$A$2:$A$1749,A34,$B$2:$B$1749,B34)/H34,"") -> 0.52393985
A35: ABRIL/2026 | B35: Comercial corporativo | C35: RH | D35: 9 | E35: 24.798868 | F35: =D35*E35 -> 223.18981 | H35: 189453 | I35: Clientes, com H&A | J35: =IFERROR(SUMIFS($F$2:$F$1749,$A$2:$A$1749,A35,$B$2:$B$1749,B35)/H35,"") -> 0.52393985
A36: ABRIL/2026 | B36: Comercial corporativo | C36: DP | D36: 9 | E36: 40.668213 | F36: =D36*E36 -> 366.01391 | H36: 189453 | I36: Clientes, com H&A | J36: =IFERROR(SUMIFS($F$2:$F$1749,$A$2:$A$1749,A36,$B$2:$B$1749,B36)/H36,"") -> 0.52393985
A37: ABRIL/2026 | B37: Comercial corporativo | C37: EMAIL | D37: 9 | E37: 50 | F37: =D37*E37 -> 450 | H37: 189453 | I37: Clientes, com H&A | J37: =IFERROR(SUMIFS($F$2:$F$1749,$A$2:$A$1749,A37,$B$2:$B$1749,B37)/H37,"") -> 0.52393985
A38: ABRIL/2026 | B38: Comercial corporativo | C38: Linhas moveis claro | D38: 0 | E38: 0 | F38: =D38*E38 -> 0 | H38: 189453 | I38: Clientes, com H&A | J38: =IFERROR(SUMIFS($F$2:$F$1749,$A$2:$A$1749,A38,$B$2:$B$1749,B38)/H38,"") -> 0.52393985
A39: ABRIL/2026 | B39: Comercial corporativo | C39: Linhas moveis fique movel | D39: 7 | E39: 30 | F39: =D39*E39 -> 210 | H39: 189453 | I39: Clientes, com H&A | J39: =IFERROR(SUMIFS($F$2:$F$1749,$A$2:$A$1749,A39,$B$2:$B$1749,B39)/H39,"") -> 0.52393985
A40: ABRIL/2026 | B40: Comercial corporativo | C40: Gympass | D40: 9 | E40: 10.15 | F40: =D40*E40 -> 91.35 | H40: 189453 | I40: Clientes, com H&A | J40: =IFERROR(SUMIFS($F$2:$F$1749,$A$2:$A$1749,A40,$B$2:$B$1749,B40)/H40,"") -> 0.52393985
A41: ABRIL/2026 | B41: Comercial corporativo | C41: Stargrid | D41: 9 | E41: 2.92 | F41: =D41*E41 -> 26.28 | H41: 189453 | I41: Clientes, com H&A | J41: =IFERROR(SUMIFS($F$2:$F$1749,$A$2:$A$1749,A41,$B$2:$B$1749,B41)/H41,"") -> 0.52393985
A42: ABRIL/2026 | B42: Comercial corporativo | C42: Rescisões | D42: 0 | E42: 0 | F42: =D42*E42 -> 0 | H42: 189453 | I42: Clientes, com H&A | J42: =IFERROR(SUMIFS($F$2:$F$1749,$A$2:$A$1749,A42,$B$2:$B$1749,B42)/H42,"") -> 0.52393985
A43: ABRIL/2026 | B43: Comercial corporativo | C43: Fardamento | D43: 2 | E43: 68 | F43: =D43*E43 -> 136 | H43: 189453 | I43: Clientes, com H&A | J43: =IFERROR(SUMIFS($F$2:$F$1749,$A$2:$A$1749,A43,$B$2:$B$1749,B43)/H43,"") -> 0.52393985
A44: ABRIL/2026 | B44: Comercial corporativo | C44: Fardamento substituição | D44: 4 | E44: 68 | F44: =D44*E44 -> 272 | H44: 189453 | I44: Clientes, com H&A | J44: =IFERROR(SUMIFS($F$2:$F$1749,$A$2:$A$1749,A44,$B$2:$B$1749,B44)/H44,"") -> 0.52393985
A45: ABRIL/2026 | B45: Comercial corporativo | C45: Exames médicos | D45: 0 | E45: 0 | F45: =D45*E45 -> 0 | H45: 189453 | I45: Clientes, com H&A | J45: =IFERROR(SUMIFS($F$2:$F$1749,$A$2:$A$1749,A45,$B$2:$B$1749,B45)/H45,"") -> 0.52393985
... A53: ABRIL/2026 | B53: Comercial corporativo | C53: Salesforce | D53: 0 | E53: 0 | F53: =D53*E53 -> 0 | H53: 189453 | I53: Clientes, com H&A | J53: =IFERROR(SUMIFS($F$2:$F$1749,$A$2:$A$1749,A53,$B$2:$B$1749,B53)/H53,"") -> 0.52393985
A54: ABRIL/2026 | B54: Compras | C54: Folha trabalhista | D54: 4 | E54: 16347.84 | F54: =E54 -> 16347.84 | H54: 176152 | I54: Clientes, menos H&A | J54: =IFERROR(SUMIFS($F$2:$F$1749,$A$2:$A$1749,A54,$B$2:$B$1749,B54)/H54,"") -> 0.097017231
A55: ABRIL/2026 | B55: Compras | C55: Seg. Trabalho | D55: 4 | E55: 45.310245 | F55: =D55*E55 -> 181.24098 | H55: 176152 | I55: Clientes, menos H&A | J55: =IFERROR(SUMIFS($F$2:$F$1749,$A$2:$A$1749,A55,$B$2:$B$1749,B55)/H55,"") -> 0.097017231
A56: ABRIL/2026 | B56: Compras | C56: RH | D56: 4 | E56: 24.798868 | F56: =D56*E56 -> 99.195472 | H56: 176152 | I56: Clientes, menos H&A | J56: =IFERROR(SUMIFS($F$2:$F$1749,$A$2:$A$1749,A56,$B$2:$B$1749,B56)/H56,"") -> 0.097017231
A57: ABRIL/2026 | B57: Compras | C57: DP | D57: 4 | E57: 40.668213 | F57: =D57*E57 -> 162.67285 | H57: 176152 | I57: Clientes, menos H&A | J57: =IFERROR(SUMIFS($F$2:$F$1749,$A$2:$A$1749,A57,$B$2:$B$1749,B57)/H57,"") -> 0.097017231
A58: ABRIL/2026 | B58: Compras | C58: EMAIL | D58: 4 | E58: 28 | F58: =D58*E58 -> 112 | H58: 176152 | I58: Clientes, menos H&A | J58: =IFERROR(SUMIFS($F$2:$F$1749,$A$2:$A$1749,A58,$B$2:$B$1749,B58)/H58,"") -> 0.097017231
A59: ABRIL/2026 | B59: Compras | C59: Exames medicos | D59: 0 | E59: 0 | F59: =D59*E59 -> 0 | H59: 176152 | I59: Clientes, menos H&A | J59: =IFERROR(SUMIFS($F$2:$F$1749,$A$2:$A$1749,A59,$B$2:$B$1749,B59)/H59,"") -> 0.097017231
A60: ABRIL/2026 | B60: Compras | C60: Linhas moveis fique movel | D60: 0 | E60: 0 | F60: =D60*E60 -> 0 | H60: 176152 | I60: Clientes, menos H&A | J60: =IFERROR(SUMIFS($F$2:$F$1749,$A$2:$A$1749,A60,$B$2:$B$1749,B60)/H60,"") -> 0.097017231
A61: ABRIL/2026 | B61: Compras | C61: Linhas moveis vivo | D61: 1 | E61: 40.52 | F61: =D61*E61 -> 40.52 | H61: 176152 | I61: Clientes, menos H&A | J61: =IFERROR(SUMIFS($F$2:$F$1749,$A$2:$A$1749,A61,$B$2:$B$1749,B61)/H61,"") -> 0.097017231
A62: ABRIL/2026 | B62: Compras | C62: Impressora | D62: 1 | E62: 25.6 | F62: =D62*E62 -> 25.6 | H62: 176152 | I62: Clientes, menos H&A | J62: =IFERROR(SUMIFS($F$2:$F$1749,$A$2:$A$1749,A62,$B$2:$B$1749,B62)/H62,"") -> 0.097017231
A63: ABRIL/2026 | B63: Compras | C63: Gympass | D63: 4 | E63: 10.15 | F63: =D63*E63 -> 40.6 | H63: 176152 | I63: Clientes, menos H&A | J63: =IFERROR(SUMIFS($F$2:$F$1749,$A$2:$A$1749,A63,$B$2:$B$1749,B63)/H63,"") -> 0.097017231
A64: ABRIL/2026 | B64: Compras | C64: Stargrid | D64: 4 | E64: 2.92 | F64: =D64*E64 -> 11.68 | H64: 176152 | I64: Clientes, menos H&A | J64: =IFERROR(SUMIFS($F$2:$F$1749,$A$2:$A$1749,A64,$B$2:$B$1749,B64)/H64,"") -> 0.097017231
A65: ABRIL/2026 | B65: Compras | C65: Fardamento novo | D65: 0 | E65: 0 | F65: =D65*E65 -> 0 | H65: 176152 | I65: Clientes, menos H&A | J65: =IFERROR(SUMIFS($F$2:$F$1749,$A$2:$A$1749,A65,$B$2:$B$1749,B65)/H65,"") -> 0.097017231
A66: ABRIL/2026 | B66: Compras | C66: Fardamento substituição | D66: 0 | E66: 0 | F66: =D66*E66 -> 0 | H66: 176152 | I66: Clientes, menos H&A | J66: =IFERROR(SUMIFS($F$2:$F$1749,$A$2:$A$1749,A66,$B$2:$B$1749,B66)/H66,"") -> 0.097017231
... A73: ABRIL/2026 | B73: Compras | C73: Mat. uso coletivo | D73: 1 | E73: 68.43 | F73: =D73*E73 -> 68.43 | H73: 176152 | I73: Clientes, menos H&A | J73: =IFERROR(SUMIFS($F$2:$F$1749,$A$2:$A$1749,A73,$B$2:$B$1749,B73)/H73,"") -> 0.097017231
A74: ABRIL/2026 | B74: Configuração | C74: Folha trabalhista | D74: 9 | E74: 31499.62 | F74: =E74 -> 31499.62 | H74: 189453 | I74: Clientes, com H&A | J74: =IFERROR(SUMIFS($F$2:$F$1749,$A$2:$A$1749,A74,$B$2:$B$1749,B74)/H74,"") -> 0.17862455
A75: ABRIL/2026 | B75: Configuração | C75: Seg. Trabalho | D75: 9 | E75: 45.310245 | F75: =D75*E75 -> 407.7922 | H75: 189453 | I75: Clientes, com H&A | J75: =IFERROR(SUMIFS($F$2:$F$1749,$A$2:$A$1749,A75,$B$2:$B$1749,B75)/H75,"") -> 0.17862455
A76: ABRIL/2026 | B76: Configuração | C76: RH | D76: 9 | E76: 24.798868 | F76: =D76*E76 -> 223.18981 | H76: 189453 | I76: Clientes, com H&A | J76: =IFERROR(SUMIFS($F$2:$F$1749,$A$2:$A$1749,A76,$B$2:$B$1749,B76)/H76,"") -> 0.17862455
A77: ABRIL/2026 | B77: Configuração | C77: DP | D77: 9 | E77: 40.668213 | F77: =D77*E77 -> 366.01391 | H77: 189453 | I77: Clientes, com H&A | J77: =IFERROR(SUMIFS($F$2:$F$1749,$A$2:$A$1749,A77,$B$2:$B$1749,B77)/H77,"") -> 0.17862455
A78: ABRIL/2026 | B78: Configuração | C78: Email | D78: 9 | E78: 50 | F78: =D78*E78 -> 450 | H78: 189453 | I78: Clientes, com H&A | J78: =IFERROR(SUMIFS($F$2:$F$1749,$A$2:$A$1749,A78,$B$2:$B$1749,B78)/H78,"") -> 0.17862455
A79: ABRIL/2026 | B79: Configuração | C79: Linhas moveis fique movel | D79: 9 | E79: 30 | F79: =D79*E79 -> 270 | H79: 189453 | I79: Clientes, com H&A | J79: =IFERROR(SUMIFS($F$2:$F$1749,$A$2:$A$1749,A79,$B$2:$B$1749,B79)/H79,"") -> 0.17862455
A80: ABRIL/2026 | B80: Configuração | C80: Linhas moveis vivo | D80: 0 | E80: 0 | F80: =D80*E80 -> 0 | H80: 189453 | I80: Clientes, com H&A | J80: =IFERROR(SUMIFS($F$2:$F$1749,$A$2:$A$1749,A80,$B$2:$B$1749,B80)/H80,"") -> 0.17862455
A81: ABRIL/2026 | B81: Configuração | C81: Impressora | D81: 1 | E81: 30.71 | F81: =D81*E81 -> 30.71 | H81: 189453 | I81: Clientes, com H&A | J81: =IFERROR(SUMIFS($F$2:$F$1749,$A$2:$A$1749,A81,$B$2:$B$1749,B81)/H81,"") -> 0.17862455
A82: ABRIL/2026 | B82: Configuração | C82: Gympass | D82: 9 | E82: 10.15 | F82: =D82*E82 -> 91.35 | H82: 189453 | I82: Clientes, com H&A | J82: =IFERROR(SUMIFS($F$2:$F$1749,$A$2:$A$1749,A82,$B$2:$B$1749,B82)/H82,"") -> 0.17862455
A83: ABRIL/2026 | B83: Configuração | C83: Stargrid | D83: 9 | E83: 2.92 | F83: =D83*E83 -> 26.28 | H83: 189453 | I83: Clientes, com H&A | J83: =IFERROR(SUMIFS($F$2:$F$1749,$A$2:$A$1749,A83,$B$2:$B$1749,B83)/H83,"") -> 0.17862455
A84: ABRIL/2026 | B84: Configuração | C84: Fardamento novo | D84: 0 | E84: 0 | F84: =D84*E84 -> 0 | H84: 189453 | I84: Clientes, com H&A | J84: =IFERROR(SUMIFS($F$2:$F$1749,$A$2:$A$1749,A84,$B$2:$B$1749,B84)/H84,"") -> 0.17862455
A85: ABRIL/2026 | B85: Configuração | C85: Fardamento substituição | D85: 7 | E85: 68 | F85: =D85*E85 -> 476 | H85: 189453 | I85: Clientes, com H&A | J85: =IFERROR(SUMIFS($F$2:$F$1749,$A$2:$A$1749,A85,$B$2:$B$1749,B85)/H85,"") -> 0.17862455
A86: ABRIL/2026 | B86: Configuração | C86: Rescisões | D86: 0 | E86: 0 | F86: =D86*E86 -> 0 | H86: 189453 | I86: Clientes, com H&A | J86: =IFERROR(SUMIFS($F$2:$F$1749,$A$2:$A$1749,A86,$B$2:$B$1749,B86)/H86,"") -> 0.17862455
... A89: ABRIL/2026 | B89: Configuração | C89: Mat. Escritório | D89: 0 | E89: 0 | F89: =D89*E89 -> 0 | H89: 189453 | I89: Clientes, com H&A | J89: =IFERROR(SUMIFS($F$2:$F$1749,$A$2:$A$1749,A89,$B$2:$B$1749,B89)/H89,"") -> 0.17862455
A90: ABRIL/2026 | B90: Contabilidade | C90: Folha trabalhista | D90: 4 | E90: 11566 | F90: =E90 -> 11566 | H90: 176152 | I90: Clientes, menos H&A | J90: =IFERROR(SUMIFS($F$2:$F$1749,$A$2:$A$1749,A90,$B$2:$B$1749,B90)/H90,"") -> 0.12024569
A91: ABRIL/2026 | B91: Contabilidade | C91: Seg. Trabalho | D91: 4 | E91: 45.310245 | F91: =D91*E91 -> 181.24098 | H91: 176152 | I91: Clientes, menos H&A | J91: =IFERROR(SUMIFS($F$2:$F$1749,$A$2:$A$1749,A91,$B$2:$B$1749,B91)/H91,"") -> 0.12024569
A92: ABRIL/2026 | B92: Contabilidade | C92: RH | D92: 4 | E92: 24.798868 | F92: =D92*E92 -> 99.195472 | H92: 176152 | I92: Clientes, menos H&A | J92: =IFERROR(SUMIFS($F$2:$F$1749,$A$2:$A$1749,A92,$B$2:$B$1749,B92)/H92,"") -> 0.12024569
A93: ABRIL/2026 | B93: Contabilidade | C93: DP | D93: 4 | E93: 40.668213 | F93: =D93*E93 -> 162.67285 | H93: 176152 | I93: Clientes, menos H&A | J93: =IFERROR(SUMIFS($F$2:$F$1749,$A$2:$A$1749,A93,$B$2:$B$1749,B93)/H93,"") -> 0.12024569
A94: ABRIL/2026 | B94: Contabilidade | C94: Email | D94: 6 | E94: 50 | F94: =D94*E94 -> 300 | H94: 176152 | I94: Clientes, menos H&A | J94: =IFERROR(SUMIFS($F$2:$F$1749,$A$2:$A$1749,A94,$B$2:$B$1749,B94)/H94,"") -> 0.12024569
A95: ABRIL/2026 | B95: Contabilidade | C95: Linhas moveis fique movel | D95: 2 | E95: 30 | F95: =D95*E95 -> 60 | H95: 176152 | I95: Clientes, menos H&A | J95: =IFERROR(SUMIFS($F$2:$F$1749,$A$2:$A$1749,A95,$B$2:$B$1749,B95)/H95,"") -> 0.12024569
A96: ABRIL/2026 | B96: Contabilidade | C96: Linhas moveis vivo | D96: 0 | E96: 0 | F96: =D96*E96 -> 0 | H96: 176152 | I96: Clientes, menos H&A | J96: =IFERROR(SUMIFS($F$2:$F$1749,$A$2:$A$1749,A96,$B$2:$B$1749,B96)/H96,"") -> 0.12024569
A97: ABRIL/2026 | B97: Contabilidade | C97: Gympass | D97: 5 | E97: 10.15 | F97: =D97*E97 -> 50.75 | H97: 176152 | I97: Clientes, menos H&A | J97: =IFERROR(SUMIFS($F$2:$F$1749,$A$2:$A$1749,A97,$B$2:$B$1749,B97)/H97,"") -> 0.12024569
A98: ABRIL/2026 | B98: Contabilidade | C98: Stargrid | D98: 5 | E98: 2.92 | F98: =D98*E98 -> 14.6 | H98: 176152 | I98: Clientes, menos H&A | J98: =IFERROR(SUMIFS($F$2:$F$1749,$A$2:$A$1749,A98,$B$2:$B$1749,B98)/H98,"") -> 0.12024569
A99: ABRIL/2026 | B99: Contabilidade | C99: exames medicos | D99: 1 | E99: 68 | F99: =D99*E99 -> 68 | H99: 176152 | I99: Clientes, menos H&A | J99: =IFERROR(SUMIFS($F$2:$F$1749,$A$2:$A$1749,A99,$B$2:$B$1749,B99)/H99,"") -> 0.12024569
A100: ABRIL/2026 | B100: Contabilidade | C100: Fardamento novo | D100: 0 | E100: 0 | F100: =D100*E100 -> 0 | H100: 176152 | I100: Clientes, menos H&A | J100: =IFERROR(SUMIFS($F$2:$F$1749,$A$2:$A$1749,A100,$B$2:$B$1749,B100)/H100,"") -> 0.12024569
A101: ABRIL/2026 | B101: Contabilidade | C101: Fardamento substituição | D101: 0 | E101: 0 | F101: =D101*E101 -> 0 | H101: 176152 | I101: Clientes, menos H&A | J101: =IFERROR(SUMIFS($F$2:$F$1749,$A$2:$A$1749,A101,$B$2:$B$1749,B101)/H101,"") -> 0.12024569
A102: ABRIL/2026 | B102: Contabilidade | C102: Vexpenses | D102: 0 | E102: 0 | F102: =D102*E102 -> 0 | H102: 176152 | I102: Clientes, menos H&A | J102: =IFERROR(SUMIFS($F$2:$F$1749,$A$2:$A$1749,A102,$B$2:$B$1749,B102)/H102,"") -> 0.12024569
... A110: ABRIL/2026 | B110: Contabilidade | C110: Software exclusivo gci net dividido com dp | D110: 1 | E110: 2559.45 | F110: =D110*E110 -> 2559.45 | H110: 176152 | I110: Clientes, menos H&A | J110: =IFERROR(SUMIFS($F$2:$F$1749,$A$2:$A$1749,A110,$B$2:$B$1749,B110)/H110,"") -> 0.12024569
A111: ABRIL/2026 | B111: DP | C111: Folha trabalhista | D111: 7 | E111: 32333.15 | F111: =E111 -> 32333.15 | H111: 1007 | I111: Funcionários do mês | J111: =IFERROR(SUMIFS($F$2:$F$1749,$A$2:$A$1749,A111,$B$2:$B$1749,B111)/H111,"") -> 40.668213
A112: ABRIL/2026 | B112: DP | C112: Email | D112: 8 | E112: 50 | F112: =D112*E112 -> 400 | H112: 1007 | I112: Funcionários do mês | J112: =IFERROR(SUMIFS($F$2:$F$1749,$A$2:$A$1749,A112,$B$2:$B$1749,B112)/H112,"") -> 40.668213
A113: ABRIL/2026 | B113: DP | C113: Fardamento novo | D113: 0 | E113: 0 | F113: =D113*E113 -> 0 | H113: 1007 | I113: Funcionários do mês | J113: =IFERROR(SUMIFS($F$2:$F$1749,$A$2:$A$1749,A113,$B$2:$B$1749,B113)/H113,"") -> 40.668213
A114: ABRIL/2026 | B114: DP | C114: Fardamento substituição | D114: 0 | E114: 0 | F114: =D114*E114 -> 0 | H114: 1007 | I114: Funcionários do mês | J114: =IFERROR(SUMIFS($F$2:$F$1749,$A$2:$A$1749,A114,$B$2:$B$1749,B114)/H114,"") -> 40.668213
A115: ABRIL/2026 | B115: DP | C115: Gympass | D115: 7 | E115: 10.15 | F115: =D115*E115 -> 71.05 | H115: 1007 | I115: Funcionários do mês | J115: =IFERROR(SUMIFS($F$2:$F$1749,$A$2:$A$1749,A115,$B$2:$B$1749,B115)/H115,"") -> 40.668213
A116: ABRIL/2026 | B116: DP | C116: Stargrid | D116: 7 | E116: 2.92 | F116: =D116*E116 -> 20.44 | H116: 1007 | I116: Funcionários do mês | J116: =IFERROR(SUMIFS($F$2:$F$1749,$A$2:$A$1749,A116,$B$2:$B$1749,B116)/H116,"") -> 40.668213
A117: ABRIL/2026 | B117: DP | C117: Exames medicos | D117: 0 | E117: 0 | F117: =D117*E117 -> 0 | H117: 1007 | I117: Funcionários do mês | J117: =IFERROR(SUMIFS($F$2:$F$1749,$A$2:$A$1749,A117,$B$2:$B$1749,B117)/H117,"") -> 40.668213
A118: ABRIL/2026 | B118: DP | C118: Impressora | D118: 1 | E118: 153.58 | F118: =D118*E118 -> 153.58 | H118: 1007 | I118: Funcionários do mês | J118: =IFERROR(SUMIFS($F$2:$F$1749,$A$2:$A$1749,A118,$B$2:$B$1749,B118)/H118,"") -> 40.668213
A119: ABRIL/2026 | B119: DP | C119: Linhas moveis Fique movel | D119: 2 | E119: 30 | F119: =D119*E119 -> 60 | H119: 1007 | I119: Funcionários do mês | J119: =IFERROR(SUMIFS($F$2:$F$1749,$A$2:$A$1749,A119,$B$2:$B$1749,B119)/H119,"") -> 40.668213
A120: ABRIL/2026 | B120: DP | C120: Linhas moveis claro | D120: 0 | E120: 0 | F120: =D120*E120 -> 0 | H120: 1007 | I120: Funcionários do mês | J120: =IFERROR(SUMIFS($F$2:$F$1749,$A$2:$A$1749,A120,$B$2:$B$1749,B120)/H120,"") -> 40.668213
A121: ABRIL/2026 | B121: DP | C121: Mat. escritorio | D121: 1 | E121: 28.5 | F121: =D121*E121 -> 28.5 | G121: Total dos itens (Materiais dos setores.xlsx) | H121: 1007 | I121: Funcionários do mês | J121: =IFERROR(SUMIFS($F$2:$F$1749,$A$2:$A$1749,A121,$B$2:$B$1749,B121)/H121,"") -> 40.668213
A122: ABRIL/2026 | B122: DP | C122: Mat. uso coletivo | D122: 1 | E122: 0 | F122: =D122*E122 -> 0 | G122: Total dos itens (Materiais dos setores.xlsx) | H122: 1007 | I122: Funcionários do mês | J122: =IFERROR(SUMIFS($F$2:$F$1749,$A$2:$A$1749,A122,$B$2:$B$1749,B122)/H122,"") -> 40.668213
A123: ABRIL/2026 | B123: DP | C123: Rescisões Trabalhistas | D123: 0 | E123: 0 | F123: =D123*E123 -> 0 | H123: 1007 | I123: Funcionários do mês | J123: =IFERROR(SUMIFS($F$2:$F$1749,$A$2:$A$1749,A123,$B$2:$B$1749,B123)/H123,"") -> 40.668213
A124: ABRIL/2026 | B124: DP | C124: Vexpenses | D124: 0 | E124: 0 | F124: =D124*E124 -> 0 | H124: 1007 | I124: Funcionários do mês | J124: =IFERROR(SUMIFS($F$2:$F$1749,$A$2:$A$1749,A124,$B$2:$B$1749,B124)/H124,"") -> 40.668213
...

Sheet Comercial
A1: COMERCIAL — ABRIL 2026
A3: DTEL | D3: DX2 | G3: VOICE NET | J3: SOARES E SILVA | M3: Soares e lins | P3: Souza e Silva | S3: LITORAL NET
A4: Custos comerciais | B4: Valores | D4: Custos comerciais | E4: Valores | G4: Custos comerciais | H4: Valores | J4: Custos comerciais | K4: Valores | M4: Custos comerciais | N4: Valores | P4: Custos comerciais | Q4: Valores | S4: Custos comerciais | T4: Valores
A5: Valores de alimentação fora o mês | B5: 0 | D5: Valores de alimentação fora o mês | E5: 0 | G5: Valores de alimentação fora o mês | H5: 0 | J5: Valores de alimentação fora o mês | K5: 0 | M5: Valores de alimentação fora o mês | N5: 0 | P5: Valores de alimentação fora o mês | Q5: 0 | S5: Valores de alimentação fora o mês | T5: 0
A6: Despesas Trabalhistas extra folha | B6: 4905.36 | D6: Despesas Trabalhistas extra folha | E6: 0 | G6: Despesas Trabalhistas extra folha | H6: 11274.36 | J6: Despesas Trabalhistas extra folha | K6: 1785.97 | M6: Despesas Trabalhistas extra folha | N6: 0 | P6: Despesas Trabalhistas extra folha | Q6: 2365.44 | S6: Despesas Trabalhistas extra folha | T6: 3219.12
A7: Endomarketing | B7: 0 | D7: Marketing direto | E7: 0 | G7: Marketing direto | H7: 0 | J7: Endomarketing | K7: 0 | M7: Endomarketing | N7: 0 | P7: Endomarketing | Q7: 0 | S7: Endomarketing | T7: 0
A8: Marketing direto | B8: 0 | D8: E-mail do departamento (1 email) | E8: 50 | G8: E-mail do departamento (4 email) | H8: 120 | J8: E-mail do departamento (2 email) | K8: 50 | M8: Marketing direto | N8: 0 | P8: Marketing direto | Q8: 0 | S8: Marketing direto | T8: 0
A9: E-mail do departamento (11 emails) | B9: 350 | D9: Folha Trabalhista com impostos do mês | E9: 22072.83 | G9: Folha Trabalhista com impostos do mês | H9: 6378.71 | J9: Folha Trabalhista com impostos do mês | K9: 37856.07 | M9: E-mail do departamento | N9: 0 | P9: E-mail do departamento | Q9: 0 | S9: E-mail do departamento (1 email) | T9: 10
A10: Folha Trabalhista com impostos do mês | B10: 231241.42 | D10: Vexpenses | E10: 0 | G10: Vale Transporte | H10: 1026 | J10: Vale Transporte | K10: 2615 | M10: Folha Trabalhista com impostos do mês | N10: 3360.44 | P10: Folha Trabalhista com impostos do mês | Q10: 12661.55 | S10: Folha Trabalhista com impostos do mês | T10: 0
A11: Vale Transporte | B11: 3960 | D11: Linhas moveis (FIQUE MÓVEL) | E11: 300 | G11: Linhas moveis (FIQUE MÓVEL) | H11: 210 | J11: KM Rodado R$ Vexpenses | K11: 0 | M11: Vale Transporte | N11: 0 | P11: Vale Transporte | Q11: 0 | S11: Vale Transporte | T11: 216
A12: Linhas moveis (FIQUE MÓVEL) | B12: 2520 | D12: Despesas com RH | E12: =E36*B47 -> 224.32 | G12: Despesas com RH | H12: =H36*B47 -> 196.28 | J12: Linhas moveis (FIQUE MÓVEL) | K12: 360 | M12: Linhas moveis (FIQUE MÓVEL) | N12: 120 | P12: Linhas moveis (FIQUE MÓVEL) | Q12: 60 | S12: Linhas moveis (FIQUE MÓVEL) | T12: 90
A13: Despesas com RH | B13: =B36*B47 -> 1542.2 | D13: Despesas com DP | E13: =E36*B48 -> 292.56 | G13: Despesas com DP | H13: =H36*B48 -> 255.99 | J13: Despesas com RH | K13: =K36*B47 -> 392.56 | M13: Despesas com RH | N13: =N36*B47 -> 28.04 | P13: Despesas com RH | Q13: =Q36*B47 -> 140.2 | S13: Despesas com RH | T13: =T36*B47 -> 28.04
A14: Despesas com DP | B14: =B36*B48 -> 2011.35 | D14: Despesas com SST | E14: =E36*B49 -> 356 | G14: Despesas com SST | H14: =H36*B49 -> 311.5 | J14: Despesas com DP | K14: =K36*B48 -> 511.98 | M14: Despesas com DP | N14: =N36*B48 -> 36.57 | P14: Despesas com DP | Q14: =Q36*B48 -> 182.85 | S14: Despesas com DP | T14: =T36*B48 -> 36.57
A15: Despesas com SST | B15: =B36*B49 -> 2447.5 | D15: Despesas SST exames | E15: 180 | G15: Despesas SST exames | H15: 121 | J15: Despesas com SST | K15: =K36*B49 -> 623 | M15: Despesas com SST | N15: =N36*B49 -> 44.5 | P15: Despesas com SST | Q15: =Q36*B49 -> 222.5 | S15: Despesas com SST | T15: =T36*B49 -> 44.5
A16: Despesas SST exames | B16: 194.6 | D16: Novo Fardamento | E16: 0 | G16: Devolução fardamento | H16: -271.8 | J16: Despesas SST exames | K16: 770 | M16: Devolução de fardamento | N16: 0 | P16: Despesas SST exames | Q16: 360 | S16: Despesas SST exames | T16: 0
A17: Novo Fardamento | B17: 94.42 | D17: Devolução de fardamento | E17: 0 | G17: Novo Fardamento | H17: 0 | J17: Devolução fardamento | K17: -1076.34 | M17: Novo Fardamento | N17: 0 | P17: Novo Fardamento | Q17: 984.16 | S17: Novo Fardamento | T17: 0
A18: Devolução de fardamento | B18: -951.3 | D18: Substituição extra de Fardamento | E18: 0 | G18: Substituição extra de Fardamento | H18: 0 | J18: Novo Fardamento | K18: 1556.24 | M18: Substituição extra de Fardamento | N18: 0 | P18: Devolução de fardamento | Q18: -358.78 | S18: Substituição extra de Fardamento | T18: 0
A19: Substituição extra de Fardamento | B19: 130.14 | D19: Combustivel de TIAGO | E19: 821.42 | G19: Combustivel RENAN RAFAEL | H19: 315.97 | J19: Substituição extra de Fardamento | K19: 0 | M19: Gympass | N19: =N36*B50 -> 11.37 | P19: Substituição extra de Fardamento | Q19: 0 | S19: Devoulução de fardamento | T19: -358.78
A20: Consumo de combustivel 4 VANs | B20: 9096.55 | D20: Gympass | E20: =E36*B50 -> 90.96 | G20: Combustivel CARLOS ROBERTO | H20: 1639.8 | J20: Consumo de combustível jefferson | K20: 1346.19 | M20: Stargrid | N20: =N36*B51 -> 2.24 | P20: Gympass | Q20: =Q36*B50 -> 56.85 | S20: Combustivel Jose gabriel | T20: 223.46
A21: Combustível Alvaro (kombi) | B21: 1719.94 | D21: Stargrid | E21: =E36*B51 -> 17.92 | G21: Discador | H21: 447.13 | J21: Consumo de combustível Camila Cordeiro | K21: 37.08 | M21: Total | P21: Stargrid | Q21: =Q36*B51 -> 11.2 | S21: Gympass | T21: =T36*B50 -> 11.37
A22: Combustivel Tarcizio | B22: 1124.73 | D22: Total | G22: Gympass | H22: =H36*B50 -> 79.59 | J22: Consumo de combustível KATHERINE | K22: 724.64 | P22: Total | S22: Stargrid | T22: =T36*B51 -> 2.24
A23: Combustivel de Nedson(executivo) | B23: 782.36 | G23: Stargrid | H23: =H36*B51 -> 15.68 | J23: Gympass | K23: =K36*B50 -> 159.18 | S23: Total
A24: Combustivel jean pereira(executivo) | B24: 139.54 | G24: Total | J24: Stargrid | K24: =K36*B51 -> 31.36
A25: Combustivel Elthon | B25: 988.16 | J25: Combustivel Manoel lopes(executivo) | K25: 782.2
A26: Combustivel rayanne meneses(executivo) | B26: 156.23 | J26: Total
A27: Combustivel myllena kelly (executiva) | B27: 1014.69
A28: Combustivel Denise kelline | B28: 1068.57
A29: Combustivel joyce rayanna | B29: 350
A30: Combustivel Djalma (executivo) | B30: 330.41
A31: Gympass | B31: =B36*B50 -> 625.35
A32: Stargrid | B32: =B36*B51 -> 123.2
A33: Total
A36: Nº Colaboradores | B36: 55 | D36: Nº Colaboradores | E36: 8 | G36: Nº Colaboradores | H36: 7 | J36: Nº Colaboradores | K36: 14 | M36: Nº Colaboradores | N36: 1 | P36: Nº Colaboradores | Q36: 5 | S36: Nº Colaboradores | T36: 1
A37: Qtd. analise | B37: 0 | D37: Qtd. analise | E37: 0 | G37: Qtd. analise | H37: 0 | J37: Qtd. analise | K37: 0 | M37: Qtd. analise | N37: 0 | P37: Qtd. analise | Q37: 0 | S37: Qtd. analise | T37: 0
A38: Vendas instaladas | B38: 1781 | D38: Vendas instaladas | E38: 136 | G38: Vendas instaladas | H38: 63 | J38: Vendas instaladas | K38: 149 | M38: Vendas instaladas | N38: 34 | P38: Vendas instaladas | Q38: 21 | S38: Vendas instaladas | T38: 9
A39: Upgrade | B39: 16 | D39: Upgrade | E39: 3 | G39: Upgrade | H39: 1 | J39: Upgrade | K39: 0 | M39: Upgrade | N39: 1 | P39: Upgrade | Q39: 1 | S39: Upgrade | T39: 0
A41: Receita vendas instaladas | B41: 147589.25 | D41: Receita vendas instaladas | E41: 10986.18 | G41: Receita vendas instaladas | H41: 5519.56 | J41: Receita vendas instaladas | K41: 14226.45 | M41: Receita vendas instaladas | N41: 3391.87 | P41: Receita vendas instaladas | Q41: 1453.39 | S41: Receita vendas instaladas | T41: 719.1
A42: Receita upgrade | B42: 375.32 | D42: Receita upgrade | E42: 24.98 | G42: Receita upgrade | H42: 4.99 | J42: Receita upgrade | K42: 0 | M42: Receita upgrade | N42: 39.99 | P42: Receita upgrade | Q42: 15 | S42: Receita upgrade | T42: 0
A43: Soma de Receita
A45: Valor da venda despesas/qtd instalada | D45: Valor da venda despesas/qtd instalada | G45: Valor da venda despesas/qtd instalada | J45: Valor da venda despesas/qtd instalada | M45: Valor da venda despesas/qtd instalada | P45: Valor da venda despesas/qtd instalada | S45: Valor da venda despesas/qtd instalada
A47: RH | B47: 28.04
A48: DP | B48: 36.57
A49: SST | B49: 44.5
A50: GYMPASS | B50: 11.37
A51: STARGRID | B51: 2.24
A53: no valor de folha não entra os vendedores registrados no mês, pois não fizeram vendas no mês anterior
A55: vendas inst. do pap e executivo, selecionar na planilha do analitico pela empresa do vendedor
A60: COMERCIAL — MAIO 2026 (preencher)
A62: DTEL | D62: DX2 | G62: VOICE NET | J62: SOARES E SILVA | M62: Soares e lins | P62: Souza e Silva | S62: LITORAL NET
A63: Custos comerciais | B63: Valores | D63: Custos comerciais | E63: Valores | G63: Custos comerciais | H63: Valores | J63: Custos comerciais | K63: Valores | M63: Custos comerciais | N63: Valores | P63: Custos comerciais | Q63: Valores | S63: Custos comerciais | T63: Valores
A64: Valores de alimentação fora o mês | D64: Valores de alimentação fora o mês | G64: Valores de alimentação fora o mês | J64: Valores de alimentação fora o mês | M64: Valores de alimentação fora o mês | P64: Valores de alimentação fora o mês | S64: Valores de alimentação fora o mês
A65: Rescisões | B65: 10409.19 | D65: Rescisões | G65: Rescisões | H65: 24565.95 | J65: Rescisões | K65: 1234.31 | M65: Rescisões | P65: Rescisões | S65: Rescisões
A66: Endomarketing | D66: Marketing direto | G66: Marketing direto | J66: Endomarketing | M66: Endomarketing | P66: Endomarketing | S66: Endomarketing
A67: Marketing direto | D67: E-mail do departamento (1 email) | E67: 50 | G67: E-mail do departamento (1) | H67: 50 | J67: E-mail do departamento (4 email) | K67: 200 | M67: Marketing direto | P67: Marketing direto | S67: Marketing direto
A68: E-mail do departamento (11 emails) | B68: 550 | D68: Folha Trabalhista com impostos do mês | E68: 38302.98 | G68: Folha Trabalhista com impostos do mês | H68: 3939.82 | J68: Folha Trabalhista com impostos do mês | K68: 45703.62 | M68: E-mail do departamento | P68: E-mail do departamento | S68: E-mail do departamento (1 email)
A69: Folha Trabalhista com impostos do mês | B69: 330070.25 | D69: Vexpenses | G69: Vale Transporte | J69: Vale Transporte | K69: 2775 | M69: Folha Trabalhista com impostos do mês | N69: 3592.34 | P69: Folha Trabalhista com impostos do mês | Q69: 14607.01 | S69: Folha Trabalhista com impostos do mês | T69: 4116.49
A70: Vale Transporte | B70: 5868 | D70: Linhas moveis (FIQUE MÓVEL) | E70: =E95*B110 -> 330 | G70: Linhas moveis (FIQUE MÓVEL) | H70: =H95*B110 -> 30 | J70: KM Rodado R$ Vexpenses | M70: Vale Transporte | P70: Vale Transporte | S70: Vale Transporte
A71: Linhas moveis (FIQUE MÓVEL) | B71: =B95*B110 -> 2160 | D71: Despesas com RH | E71: =E95*B105 -> 273.02 | G71: Despesas com RH | H71: =H95*B105 -> 24.82 | J71: Linhas moveis (FIQUE MÓVEL) | K71: =K95*B110 -> 390 | M71: Linhas moveis (FIQUE MÓVEL) | N71: =N95*B110 -> 30 | P71: Linhas moveis (FIQUE MÓVEL) | Q71: =Q95*B110 -> 150 | S71: Linhas moveis (FIQUE MÓVEL) | T71: =T95*B110 -> 30
A72: Despesas com RH | B72: =B95*B105 -> 1787.04 | D72: Despesas com DP | E72: =E95*B106 -> 448.25 | G72: Despesas com DP | H72: =H95*B106 -> 40.75 | J72: Despesas com RH | K72: =K95*B105 -> 322.66 | M72: Despesas com RH | N72: =N95*B105 -> 24.82 | P72: Despesas com RH | Q72: =Q95*B105 -> 124.1 | S72: Despesas com RH | T72: =T95*B105 -> 24.82
A73: Despesas com DP | B73: =B95*B106 -> 2934 | D73: Despesas com SST | E73: =E95*B107 -> 498.41 | G73: Despesas com SST | H73: =H95*B107 -> 45.31 | J73: Despesas com DP | K73: =K95*B106 -> 529.75 | M73: Despesas com DP | N73: =N95*B106 -> 40.75 | P73: Despesas com DP | Q73: =Q95*B106 -> 203.75 | S73: Despesas com DP | T73: =T95*B106 -> 40.75
A74: Despesas com SST | B74: =B95*B107 -> 3262.32 | D74: Despesas SST exames | G74: Despesas SST exames | J74: Despesas com SST | K74: =K95*B107 -> 589.03 | M74: Despesas com SST | N74: =N95*B107 -> 45.31 | P74: Despesas com SST | Q74: =Q95*B107 -> 226.55 | S74: Despesas com SST | T74: =T95*B107 -> 45.31
A75: Despesas SST exames | B75: 804 | D75: Novo Fardamento | E75: 699.62 | G75: Devolução fardamento | H75: -494.68 | J75: Despesas SST exames | M75: Devolução de fardamento | P75: Despesas SST exames | S75: Despesas SST exames
A76: Novo Fardamento | B76: 154.6 | D76: Devolução de fardamento | G76: Novo Fardamento | J76: Devolução fardamento | K76: -247.34 | M76: Novo Fardamento | P76: Novo Fardamento | S76: Novo Fardamento
A77: Devolução de fardamento | B77: -227.34 | D77: Substituição extra de Fardamento | E77: 566.12 | G77: Substituição extra de Fardamento | J77: Novo Fardamento | M77: Substituição extra de Fardamento | P77: Devolução de fardamento | S77: Substituição extra de Fardamento
A78: Substituição extra de Fardamento | B78: 240.9 | D78: Combustivel de TIAGO | E78: 1242.63 | G78: Combustivel RENAN RAFAEL | H78: 357.29 | J78: Substituição extra de Fardamento | M78: Gympass | N78: =N95*B108 -> 10.15 | P78: Substituição extra de Fardamento | S78: Devoulução de fardamento
A79: Consumo de combustivel 4 VANs | B79: 13300.75 | D79: Combustivel de van | E79: 570.9 | G79: Combustivel CARLOS ROBERTO | H79: 1441.58 | J79: Consumo de combustível jefferson | K79: 1716.95 | M79: Stargrid | N79: =N95*B109 -> 2.92 | P79: Gympass | Q79: =Q95*B108 -> 50.75 | S79: Combustivel Jose gabriel | T79: 434.51
A80: Combustível Alvaro (kombi) | B80: 2292.48 | D80: Gympass | E80: =E95*B108 -> 111.65 | G80: Discador | J80: Consumo de combustível Camila Cordeiro | K80: 1168.17 | M80: Total | P80: Stargrid | Q80: =Q95*B109 -> 14.6 | S80: Gympass | T80: =T95*B108 -> 10.15
A81: Combustivel Tarcizio | B81: 1872.58 | D81: Stargrid | E81: =E95*B109 -> 32.12 | G81: Gympass | H81: =H95*B108 -> 10.15 | J81: Consumo de combustível KATHERINE | K81: 1178.16 | P81: Total | S81: Stargrid | T81: =T95*B109 -> 2.92
A82: Combustivel de Nedson(executivo) | B82: 744.76 | D82: Total | G82: Stargrid | H82: =H95*B109 -> 2.92 | J82: Gympass | K82: =K95*B108 -> 131.95 | S82: Total
A83: Combustivel jean pereira(executivo) | B83: 280.85 | G83: Total | J83: Stargrid | K83: =K95*B109 -> 37.96
A84: Combustivel Elthon | B84: 1825.34 | J84: Combustivel Manoel lopes(executivo) | K84: 1656.05
A85: Combustivel rayanne meneses(executivo) | B85: 201.23 | J85: Total
A86: Combustivel myllena kelly (executiva) | B86: 1113.47
A87: Combustivel Denise kelline | B87: 1479.27
A88: Combustivel joyce rayanna
A89: Combustivel Djalma (executivo) | B89: 234.76
A90: Gympass | B90: =B95*B108 -> 730.8
A91: Stargrid | B91: =B95*B109 -> 210.24
A92: Total
A95: Nº Colaboradores | B95: 72 | D95: Nº Colaboradores | E95: 11 | G95: Nº Colaboradores | H95: 1 | J95: Nº Colaboradores | K95: 13 | M95: Nº Colaboradores | N95: 1 | P95: Nº Colaboradores | Q95: 5 | S95: Nº Colaboradores | T95: 1
A96: Vendas instaladas | B96: 1512 | D96: Vendas instaladas | E96: 89 | G96: Vendas instaladas | H96: 26 | J96: Vendas instaladas | K96: 92 | M96: Vendas instaladas | N96: 24 | P96: Vendas instaladas | Q96: 59 | S96: Vendas instaladas | T96: 18
A97: Upgrade | B97: 21 | D97: Upgrade | E97: 8 | G97: Upgrade | H97: 0 | J97: Upgrade | K97: 1 | M97: Upgrade | P97: Upgrade | Q97: 2 | S97: Upgrade
A99: Receita vendas instaladas | B99: 131855.21 | D99: Receita vendas instaladas | E99: 7236.53 | G99: Receita vendas instaladas | H99: 2587.68 | J99: Receita vendas instaladas | K99: 8984.96 | M99: Receita vendas instaladas | N99: 2068.08 | P99: Receita vendas instaladas | Q99: 3804.88 | S99: Receita vendas instaladas | T99: 1593.3
A100: Receita upgrade | B100: 2082.84 | D100: Receita upgrade | E100: 799.2 | G100: Receita upgrade | H100: 0 | J100: Receita upgrade | K100: 89.89 | M100: Receita upgrade | P100: Receita upgrade | Q100: 199.8 | S100: Receita upgrade
A101: Soma de Receita
A103: Valor da venda despesas/qtd instalada | D103: Valor da venda despesas/qtd instalada | G103: Valor da venda despesas/qtd instalada | J103: Valor da venda despesas/qtd instalada | M103: Valor da venda despesas/qtd instalada | P103: Valor da venda despesas/qtd instalada | S103: Valor da venda despesas/qtd instalada
A105: RH | B105: 24.82
A106: DP | B106: 40.75
A107: SST | B107: 45.31
A108: GYMPASS | B108: 10.15
A109: STARGRID | B109: 2.92
A110: FIQUE MOVEL | B110: 30
A112: no valor de folha não entra os vendedores registrados no mês, pois não fizeram vendas no mês anterior
A114: vendas inst. do pap e executivo, selecionar na planilha do analitico pela empresa do vendedor
A119: COMERCIAL — JUNHO 2026 (preencher)
A121: DTEL | D121: DX2 | G121: VOICE NET | J121: SOARES E SILVA | M121: Soares e lins | P121: Souza e Silva | S121: LITORAL NET
A122: Custos comerciais | B122: Valores | D122: Custos comerciais | E122: Valores | G122: Custos comerciais | H122: Valores | J122: Custos comerciais | K122: Valores | M122: Custos comerciais | N122: Valores | P122: Custos comerciais | Q122: Valores | S122: Custos comerciais | T122: Valores
A123: Valores de alimentação fora o mês | D123: Valores de alimentação fora o mês | G123: Valores de alimentação fora o mês | J123: Valores de alimentação fora o mês | M123: Valores de alimentação fora o mês | P123: Valores de alimentação fora o mês | S123: Valores de alimentação fora o mês
A124: Despesas Trabalhistas extra folha | D124: Despesas Trabalhistas extra folha | G124: Despesas Trabalhistas extra folha | J124: Despesas Trabalhistas extra folha | M124: Despesas Trabalhistas extra folha | P124: Despesas Trabalhistas extra folha | S124: Despesas Trabalhistas extra folha
A125: Endomarketing | D125: Marketing direto | G125: Marketing direto | J125: Endomarketing | M125: Endomarketing | P125: Endomarketing | S125: Endomarketing
...

Sheet Reembolso Geral
A1: MÊS | B1: Descrição | C1: Setor/ Departamento | D1: Competência | E1: Empresa | F1: QTD referência | G1: Valor uni. | H1: Valor total | I1: FORMA DE CÁLCULO
A2: ABRIL/2026 | B2: Despesa do consultor PEDRO GREGO | C2: Comercial | D2: 46113 | E2: DX2 | F2: 3 | G2: 300.37 | H2: =IF(OR(F2="",G2=""),"",F2*G2) -> 901.11 | I2: despesa trabalhista e combustível do consultor dividido pelo total de vendas (cliente 12195,12634,12408)
A3: ABRIL/2026 | B3: Transporte de produtos | C3: Frota | D3: 46113 | E3: DX2 | F3: 0 | G3: 0 | H3: =IF(OR(F3="",G3=""),"",F3*G3) -> 0 | I3: transportes entre CD01 e empresas no rateio da rota
A4: ABRIL/2026 | B4: Adm atendimento presencial | C4: Adm Atendimento | D4: 46113 | E4: H&A | F4: 13402 | G4: 0.1870984 | H4: =IF(OR(F4="",G4=""),"",F4*G4) -> 2507.4928 | I4: Cálculo por número de clientes ativos
A5: ABRIL/2026 | B5: E-mail Dtel | C5: TIC | D5: 46113 | E5: H&A | F5: 2 | G5: 50 | H5: =IF(OR(F5="",G5=""),"",F5*G5) -> 100 | I5: Utilização de email corporativo
A6: ABRIL/2026 | B6: Vendas da equipe voicenet P/ SOARES E LINS | C6: Comercial | D6: 46113 | E6: Soares & Lins | F6: 0 | G6: 0 | H6: =IF(OR(F6="",G6=""),"",F6*G6) -> 0 | I6: Vendas instaladas
A7: ABRIL/2026 | B7: KM rodado para serviços técnicos da S&L para DTEL | C7: Instalação | D7: 46113 | E7: Soares & Lins | F7: 0 | G7: 0 | H7: =IF(OR(F7="",G7=""),"",F7*G7) -> 0 | I7: Deslocamento de equipes
A8: ABRIL/2026 | B8: Conselho Regional De Enfermagem De Alagoas | C8: Licitação | D8: 46113 | E8: Soares e Silva | F8: -1 | G8: 238.88 | H8: =IF(OR(F8="",G8=""),"",F8*G8) -> -238.88 | I8: mensalidade recebida pela H&A (parcela abril)
A9: ABRIL/2026 | B9: Fardamentos | C9: RH | D9: 46113 | E9: Souza & Silva | F9: 0 | G9: 0 | H9: =IF(OR(F9="",G9=""),"",F9*G9) -> 0 | I9: Solicitações de fardamentos administrativos
A10: ABRIL/2026 | B10: Despesa do consultor PAULO MELO | C10: Comercial | D10: 46113 | E10: Voicenet | F10: 2 | G10: 338.53 | H10: =IF(OR(F10="",G10=""),"",F10*G10) -> 677.06 | I10: despesa trabalhista e combustivel do consultor dividido pelo total de vendas(cliente 15826, 15746)
A11: ABRIL/2026 | B11: Vendas do site Mundiale | C11: Marketing | D11: 46113 | E11: Dtel Telecom | F11: 1 | G11: 404.4 | H11: =IF(OR(F11="",G11=""),"",F11*G11) -> 404.4 | I11: Vendas instaladas do impulsionamento site mundiale (VENDAS MUNDIALE - MAIO 2026.xlsx)
A12: ABRIL/2026 | B12: Vendas da equipe Dtel porta a porta | C12: Comercial | D12: 46114 | E12: DX2 | F12: 0 | G12: 0 | H12: =IF(OR(F12="",G12=""),"",F12*G12) -> 0 | I12: Vendas instaladas
A13: ABRIL/2026 | B13: Abastecimento | C13: Frota | D13: 46114 | E13: DX2 | F13: 0 | G13: 0 | H13: =IF(OR(F13="",G13=""),"",F13*G13) -> 0 | I13: Abastecimento da van da dx2 com cartao Dtel
... A35: ABRIL/2026 | B35: E-mail Dtel | C35: TIC | D35: 46116 | E35: Soares e Silva | F35: 5 | G35: 50 | H35: =IF(OR(F35="",G35=""),"",F35*G35) -> 250 | I35: Utilização de email corporativo
A36: ABRIL/2026 | B36: Vendas da equipe Dtel porta a porta | C36: Comercial | D36: 46116 | E36: Voicenet | F36: 4 | H36: =IF(OR(F36="",G36=""),"",F36*G36) | I36: Vendas instaladas
A37: ABRIL/2026 | B37: Conselho regional de farmacia dos estado de pernambuco | C37: Licitação | D37: 46116 | E37: Voicenet | F37: -1 | G37: 510 | H37: =IF(OR(F37="",G37=""),"",F37*G37) -> -510 | I37: mensalidade recebida pela H&A (parcela abril)
A38: ABRIL/2026 | B38: Vendas da equipe H&A porta a porta P/ DX2 | C38: Comercial | D38: 46117 | E38: DX2 | F38: 0 | G38: 0 | H38: =IF(OR(F38="",G38=""),"",F38*G38) -> 0 | I38: Vendas instaladas
A39: ABRIL/2026 | B39: Manutenção predial | C39: Manutenção | D39: 46117 | E39: DX2 | F39: 1 | G39: 7780.43 | H39: =IF(OR(F39="",G39=""),"",F39*G39) -> 7780.43 | I39: Serviços executados para verificação de tacaimbó, e manut. de alarme e sensor loja pesqueira, despesa com comb. e colab.
A40: ABRIL/2026 | B40: Equipamentos de Segurança | C40: SST | D40: 46117 | E40: DX2 | F40: 1 | G40: 13006.38 | H40: =IF(OR(F40="",G40=""),"",F40*G40) -> 13006.38 | I40: EPI, EPC, Fardamento
A41: ABRIL/2026 | B41: Rastreamento veicular | C41: Frota | D41: 46117 | E41: Soares & Lins | F41: 3 | G41: 20 | H41: =IF(OR(F41="",G41=""),"",F41*G41) -> 60 | I41: rastreamento dos veículos
A42: ABRIL/2026 | B42: Serviços técnicos da S&L para DTEL | C42: Instalação | D42: 46117 | E42: Soares & Lins | F42: -1 | G42: 4279.74 | H42: =IF(OR(F42="",G42=""),"",F42*G42) -> -4279.74 | I42: Serviços da equipe técnica
A43: ABRIL/2026 | B43: Reembolso por receita recebida | C43: Administrativo | D43: 46117 | E43: Soares e Silva | F43: 1 | G43: 36742.58 | H43: =IF(OR(F43="",G43=""),"",F43*G43) -> 36742.58 | I43: Taxa de administração de 6% e 1% de utilização da marca
A44: ABRIL/2026 | B44: Despesa do consultor PAULO MELO | C44: Comercial | D44: 46117 | E44: Soares e Silva | F44: 4 | G44: 338.53 | H44: =IF(OR(F44="",G44=""),"",F44*G44) -> 1354.12 | I44: despesa trabalhista e combustÍvel dividida pela quantidade de vendas(cliente 12023,11614)
A45: ABRIL/2026 | B45: E-mail Dtel | C45: TIC | D45: 46117 | E45: Solon araújo | F45: 2 | G45: 50 | H45: =IF(OR(F45="",G45=""),"",F45*G45) -> 100 | I45: Utilização de email corporativo
A46: ABRIL/2026 | B46: Vendas da equipe H&A p/ voice | C46: Comercial | D46: 46117 | E46: Voicenet | F46: 0 | G46: 0 | H46: =IF(OR(F46="",G46=""),"",F46*G46) -> 0 | I46: Vendas instaladas
A47: ABRIL/2026 | B47: Vendas da equipe VOICENET porta a porta P/ DX2 | C47: Comercial | D47: 46118 | E47: DX2 | F47: 0 | G47: 0 | H47: =IF(OR(F47="",G47=""),"",F47*G47) -> 0 | I47: Vendas instaladas
A48: ABRIL/2026 | B48: Manutenção predial | C48: Manutenção | D48: 46118 | E48: H&A | F48: 1 | G48: 2777.71 | H48: =IF(OR(F48="",G48=""),"",F48*G48) -> 2777.71 | I48: Despesa com combust. e colaborador para manutenção de ar condicionado do estoque
... A61: ABRIL/2026 | B61: Reembolso por receita recebida | C61: Administrativo | D61: 46119 | E61: Souza & Silva | F61: 1 | G61: 24090.35 | H61: =IF(OR(F61="",G61=""),"",F61*G61) -> 24090.35 | I61: Taxa de administração de 6% e 1% de utilização da marca
A62: ABRIL/2026 | B62: Vendas da equipe Voicenet para Dtel | C62: Comercial | D62: 46119 | E62: Voicenet | F62: -15 | H62: =IF(OR(F62="",G62=""),"",F62*G62) | I62: Vendas instaladas
A63: ABRIL/2026 | B63: E-mail Dtel | C63: TIC | D63: 46119 | E63: Voicenet | F63: 1 | G63: 90 | H63: =IF(OR(F63="",G63=""),"",F63*G63) -> 90 | I63: Utilização de email corporativo
A64: ABRIL/2026 | B64: Despesa do coordenador TIAGO, pela gestão da equipe | C64: Comercial | D64: 46120 | E64: DX2 | F64: -1 | G64: 812.42 | H64: =IF(OR(F64="",G64=""),"",F64*G64) -> -812.42 | I64: crédito por despesa com combustível e utilização de veÍculo dx2
A65: ABRIL/2026 | B65: Serviços de configuração e suporte ao Técnico | C65: Configuração | D65: 46120 | E65: DX2 | F65: 6280 | G65: 0.17862455 | H65: =IF(OR(F65="",G65=""),"",F65*G65) -> 1121.7621 | I65: Cálculo por número de clientes ativos
A66: ABRIL/2026 | B66: Saude e segurança no trabalho | C66: SST | D66: 46120 | E66: H&A | F66: 0 | G66: 0 | H66: =IF(OR(F66="",G66=""),"",F66*G66) -> 0 | I66: Rateio do departamento (despesa por colaborador, mês de jan fev e março)
A67: ABRIL/2026 | B67: Despesa do coordenador TIAGO, pela gestão da equipe | C67: Comercial | D67: 46120 | E67: Soares e Silva | F67: 149 | G67: 20.06 | H67: =IF(OR(F67="",G67=""),"",F67*G67) -> 2988.94 | I67: despesa trabalhista e pela quantidade de vendas
A68: ABRIL/2026 | B68: Abastecimento | C68: Frota | D68: 46120 | E68: Soares e silva | F68: 0 | G68: 0 | H68: =IF(OR(F68="",G68=""),"",F68*G68) -> 0 | I68: Abastecimento de 2 veiculos
A69: ABRIL/2026 | B69: Serviços técnicos da Dx2 p/ soares e silva | C69: Instalação | D69: 46120 | E69: Soares e Silva | F69: 0 | G69: 0 | H69: =IF(OR(F69="",G69=""),"",F69*G69) -> 0 | I69: Serviços das equipes técnicas
A70: ABRIL/2026 | B70: Manutenção predial | C70: Manutenção | D70: 46120 | E70: Soares e Silva | F70: 1 | G70: 4438.18 | H70: =IF(OR(F70="",G70=""),"",F70*G70) -> 4438.18 | I70: Serviços executados, despesa com combustÍvel e colaborador para reforma pop b, e passagem de tubulação de condensadora
A71: ABRIL/2026 | B71: Reembolso por receita recebida | C71: Administrativo | D71: 46120 | E71: Voicenet | F71: 1 | G71: 29402.21 | H71: =IF(OR(F71="",G71=""),"",F71*G71) -> 29402.21 | I71: Taxa de administração de 6% e 1% de utilização da marca
A72: ABRIL/2026 | B72: E-mail Dtel | C72: TIC | D72: 46120 | E72: Voicenet | F72: 2 | G72: 10 | H72: =IF(OR(F72="",G72=""),"",F72*G72) -> 20 | I72: Utilização de email corporativo
A73: ABRIL/2026 | B73: Material de escritório | C73: Atendimento | D73: 46121 | E73: DX2 | F73: 0 | G73: 0 | H73: =IF(OR(F73="",G73=""),"",F73*G73) -> 0 | I73: Capa de carnê
A74: ABRIL/2026 | B74: Despesa do coordenador TIAGO, pela gestão da equipe | C74: Comercial | D74: 46121 | E74: DX2 | F74: -1 | G74: 4015.98 | H74: =IF(OR(F74="",G74=""),"",F74*G74) -> -4015.98 | I74: Crédito por participação do coordenador na base h&a e soares e silva
... A76: ABRIL/2026 | B76: Serviços prestados pela equipe Segurança do trabalho dtel p/ h&a | C76: SST | D76: 46121 | E76: H&A | F76: 0 | G76: 0 | H76: =IF(OR(F76="",G76=""),"",F76*G76) -> 0 | I76: Serviços da equipe para Horas cursos de normas e reciclagem ou visitas
A77: ABRIL/2026 | B77: Vendas da equipe Dtel porta a porta p/ Soares e silva | C77: Comercial | D77: 46121 | E77: Soares e Silva | F77: 2 | H77: =IF(OR(F77="",G77=""),"",F77*G77) | I77: Vendas instaladas
A78: ABRIL/2026 | B78: Locação de veículos | C78: Frota | D78: 46121 | E78: Soares e Silva | F78: 0 | G78: 0 | H78: =IF(OR(F78="",G78=""),"",F78*G78) -> 0 | I78: Veiculos Dtel emprestado para serviços 2 carros
A79: ABRIL/2026 | B79: KM rodado para serviços técnicos dx2 p/ Solon | C79: Instalação | D79: 46121 | E79: Solon araújo | F79: 0 | G79: 0 | H79: =IF(OR(F79="",G79=""),"",F79*G79) -> 0 | I79: Serviços das equipes dx2 p/ solon
A80: ABRIL/2026 | B80: Manutenção predial | C80: Manutenção | D80: 46121 | E80: Solon araújo | F80: 1 | G80: 5054.07 | H80: =IF(OR(F80="",G80=""),"",F80*G80) -> 5054.07 | I80: Despesa com material, combust, e colaborador para manut. de ar, e manut. de telhado
A81: ABRIL/2026 | B81: E-mail Dtel | C81: TIC | D81: 46121 | E81: Voicenet | F81: 3 | G81: 50 | H81: =IF(OR(F81="",G81=""),"",F81*G81) -> 150 | I81: Utilização de email corporativo
A82: ABRIL/2026 | B82: Material de uso coletivo | C82: Atendimento | D82: 46122 | E82: DX2 | F82: 16 | G82: 2.85 | H82: =IF(OR(F82="",G82=""),"",F82*G82) -> 45.6 | I82: Água mineral
A83: ABRIL/2026 | B83: Comissão de manutenção da Totum | C83: Comercial | D83: 46122 | E83: H&A | F83: 1 | G83: 33.5 | H83: =IF(OR(F83="",G83=""),"",F83*G83) -> 33.5 | I83: Conselho regional de enfermagem de PE
A84: ABRIL/2026 | B84: Saldo restante de reembolso | C84: Contabilidade | D84: 46122 | E84: H&A | F84: 1 | G84: 80 | H84: =IF(OR(F84="",G84=""),"",F84*G84) -> 80 | I84: Parcela de reembolso gerado menor que o valor enviado no email de reembolso de março
A85: ABRIL/2026 | B85: Serviços de configuração e suporte ao Técnico | C85: Configuração | D85: 46122 | E85: Soares & Lins | F85: 3650 | G85: 0.17862455 | H85: =IF(OR(F85="",G85=""),"",F85*G85) -> 651.97959 | I85: Cálculo por número de clientes ativos
A86: ABRIL/2026 | B86: Equipamentos de Segurança | C86: SST | D86: 46122 | E86: Soares & Lins | F86: 0 | G86: 0 | H86: =IF(OR(F86="",G86=""),"",F86*G86) -> 0 | I86: Devolução de Crédito
A87: ABRIL/2026 | B87: Vendas da equipe H&A para Soares e Silva | C87: Comercial | D87: 46122 | E87: Soares e Silva | F87: 0 | G87: 0 | H87: =IF(OR(F87="",G87=""),"",F87*G87) -> 0 | I87: Vendas instaladas
A88: ABRIL/2026 | B88: Manutenção de veiculo | C88: Frota | D88: 46122 | E88: Soares e silva | F88: 0 | G88: 0 | H88: =IF(OR(F88="",G88=""),"",F88*G88) -> 0 | I88: manutenção veicular
A89: ABRIL/2026 | B89: Serviços técnicos da Dx2 p/ Solon | C89: Instalação | D89: 46122 | E89: Solon araújo | F89: 0 | G89: 0 | H89: =IF(OR(F89="",G89=""),"",F89*G89) -> 0 | I89: Serviços das equipes técnicas Dx2 p/ solon
... A147: ABRIL/2026 | B147: Gestão Regional MICHELANGELO | C147: Instalação | D147: 46129 | E147: Voicenet | F147: 4782 | G147: 0.31 | H147: =IF(OR(F147="",G147=""),"",F147*G147) -> 1482.42 | I147: Cálculo por número de clientes ativos
A148: ABRIL/2026 | B148: Vendas da equipe Dtel porta a porta | C148: Comercial | D148: 46130 | E148: H&A | F148: 1 | H148: =IF(OR(F148="",G148=""),"",F148*G148) | I148: Vendas instaladas
A149: ABRIL/2026 | B149: Serviços prestados pela equipe Segurança do trabalho soares e silva p/ dtel | C149: SST | D149: 46130 | E149: Soares e Silva | F149: 0 | G149: 0 | H149: =IF(OR(F149="",G149=""),"",F149*G149) -> 0 | I149: Serviços da equipe para Horas cursos de normas e reciclagem ou visitas
A150: ABRIL/2026 | B150: Material de uso coletivo | C150: Atendimento | D150: 46130 | E150: Solon araújo | F150: 20 | G150: 2.85 | H150: =IF(OR(F150="",G150=""),"",F150*G150) -> 57 | I150: Água mineral
A151: ABRIL/2026 | B151: Vendas da equipe da soares e lins para Solon | C151: Comercial | D151: 46130 | E151: Solon araújo | F151: 0 | G151: 0 | H151: =IF(OR(F151="",G151=""),"",F151*G151) -> 0 | I151: Vendas instaladas
A152: ABRIL/2026 | B152: Uso mútuo de Postes | C152: Engenharia | D152: 46130 | E152: Souza & Silva | F152: 1 | G152: 15695.77 | H152: =IF(OR(F152="",G152=""),"",F152*G152) -> 15695.77 | I152: Contrato das empresas que está em nome da Dtel
A153: ABRIL/2026 | B153: Rastreamento veicular | C153: Frota | D153: 46130 | E153: Souza & Silva | F153: 4 | G153: 20 | H153: =IF(OR(F153="",G153=""),"",F153*G153) -> 80 | I153: rastreamento dos veículos
A154: ABRIL/2026 | B154: Vendas do site Mundiale | C154: Marketing | D154: 46130 | E154: Souza & Silva | F154: 1 | G154: 143.82 | H154: =IF(OR(F154="",G154=""),"",F154*G154) -> 143.82 | I154: Vendas instaladas do impulsionamento site mundiale
A155: ABRIL/2026 | B155: KM rodado para serviços técnicos Dtel para Voicenet | C155: Instalação | D155: 46130 | E155: Voicenet | F155: 1 | G155: 2480.38 | H155: =IF(OR(F155="",G155=""),"",F155*G155) -> 2480.38 | I155: Deslocamento de equipes
A156: ABRIL/2026 | B156: Vendas da equipe H&A P/ VOICENET | C156: Comercial | D156: 46131 | E156: H&A | F156: 0 | G156: 0 | H156: =IF(OR(F156="",G156=""),"",F156*G156) -> 0 | I156: Vendas instaladas
A157: ABRIL/2026 | B157: Serviços prestados pela equipe Segurança do trabalho soares e silva p/ LITORAL | C157: SST | D157: 46131 | E157: Soares e Silva | F157: 0 | G157: 0 | H157: =IF(OR(F157="",G157=""),"",F157*G157) -> 0 | I157: Serviços da equipe para Horas cursos de normas e reciclagem ou visitas
A158: ABRIL/2026 | B158: Vendas da equipe Dtel porta a porta | C158: Comercial | D158: 46131 | E158: Solon araújo | F158: 15 | H158: =IF(OR(F158="",G158=""),"",F158*G158) | I158: Vendas instaladas
A159: ABRIL/2026 | B159: Material de escritório | C159: Atendimento | D159: 46131 | E159: Souza & Silva | F159: 0 | G159: 0 | H159: =IF(OR(F159="",G159=""),"",F159*G159) -> 0 | I159: Porta panfleto
A160: ABRIL/2026 | B160: Transporte de produtos | C160: Frota | D160: 46131 | E160: Souza & Silva | F160: 0 | G160: 0 | H160: =IF(OR(F160="",G160=""),"",F160*G160) -> 0 | I160: transportes entre CD01 e empresas no rateio da rota
A161: ABRIL/2026 | B161: Despesas da equipe de Engenharia | C161: Engenharia | D161: 46131 | E161: Voicenet | F161: 0 | G161: 0 | H161: =IF(OR(F161="",G161=""),"",F161*G161) -> 0 | I161: Combustível, alimentação
A162: ABRIL/2026 | B162: KM rodado para serviços técnicos Voicenet p/ Dtel | C162: Instalação | D162: 46131 | E162: Voicenet | F162: 0 | G162: 0 | H162: =IF(OR(F162="",G162=""),"",F162*G162) -> 0 | I162: Deslocamento de equipes
A163: ABRIL/2026 | B163: Vendas do site Mundiale | C163: Marketing | D163: 46131 | E163: Voicenet | F163: 9 | G163: 123.18 | H163: =IF(OR(F163="",G163=""),"",F163*G163) -> 1108.62 | I163: Vendas instaladas do impulsionamento site mundiale
A164: ABRIL/2026 | B164: Serviços realizados pelo estoque | C164: Estoque | D164: 46132 | E164: DX2 | F164: 1 | G164: 1128 | H164: =IF(OR(F164="",G164=""),"",F164*G164) -> 1128 | I164: Serviços de marcação de equipamentos
A165: ABRIL/2026 | B165: Vendas da equipe H&A para Dtel | C165: Comercial | D165: 46132 | E165: H&A | F165: 1 | G165: 0 | H165: =IF(OR(F165="",G165=""),"",F165*G165) -> 0 | I165: Vendas instaladas
A166: ABRIL/2026 | B166: Relacionamento Dtel | C166: Relacionamento | D166: 46132 | E166: H&A | F166: 13402 | G166: 2.2145965 | H166: =IF(OR(F166="",G166=""),"",F166*G166) -> 29680.022 | I166: Cálculo por número de clientes ativos
A167: ABRIL/2026 | B167: Vendas da equipe Litoral p/ Dtel | C167: Comercial | D167: 46132 | E167: Solon araújo | F167: 0 | G167: 0 | H167: =IF(OR(F167="",G167=""),"",F167*G167) -> 0 | I167: Vendas instaladas
A168: ABRIL/2026 | B168: Equipamentos de Segurança | C168: SST | D168: 46132 | E168: Solon araújo | F168: -1 | G168: 1333.53 | H168: =IF(OR(F168="",G168=""),"",F168*G168) -> -1333.53 | I168: Devolução de Crédito
A169: ABRIL/2026 | B169: Material de escritório | C169: Atendimento | D169: 46132 | E169: Souza & Silva | F169: 0 | G169: 0 | H169: =IF(OR(F169="",G169=""),"",F169*G169) -> 0 | I169: Panfletos
A170: ABRIL/2026 | B170: Troca de Óleo e Filtro | C170: Frota | D170: 46132 | E170: Souza & Silva | F170: 1 | G170: 366.53 | H170: =IF(OR(F170="",G170=""),"",F170*G170) -> 366.53 | I170: manutenção veicular
... A230: ABRIL/2026 | B230: Municipio De Primavera | C230: Licitação | D230: 46140 | E230: H&A | F230: 1 | G230: 7615.46 | H230: =IF(OR(F230="",G230=""),"",F230*G230) -> 7615.46 | I230: mensalidade recebida pela H&A (parcela abril)
A231: ABRIL/2026 | B231: Vendas da equipe Dtel porta a porta | C231: Comercial | D231: 46140 | E231: Soares & Lins | F231: 1 | H231: =IF(OR(F231="",G231=""),"",F231*G231) | I231: Vendas instaladas
A232: ABRIL/2026 | B232: Fardamentos | C232: RH | D232: 46140 | E232: Soares & Lins | F232: 0 | G232: 0 | H232: =IF(OR(F232="",G232=""),"",F232*G232) -> 0 | I232: Solicitações de fardamentos administrativos
A233: ABRIL/2026 | B233: Vendas da equipe Souza e silva p/ DTEL | C233: Comercial | D233: 46140 | E233: Souza & Silva | F233: 0 | G233: 0 | H233: =IF(OR(F233="",G233=""),"",F233*G233) -> 0 | I233: Vendas instaladas
A234: ABRIL/2026 | B234: Serviços realizados pelo estoque | C234: Estoque | D234: 46140 | E234: Voicenet | F234: 1 | G234: 569.64 | H234: =IF(OR(F234="",G234=""),"",F234*G234) -> 569.64 | I234: Serviços de marcação de equipamentos
A235: ABRIL/2026 | B235: Km rodado Segurança e Saúde do Trabalho dtel p/ voice net | C235: SST | D235: 46140 | E235: Voicenet | F235: 0 | G235: 0 | H235: =IF(OR(F235="",G235=""),"",F235*G235) -> 0 | I235: Deslocamento da equipe para Horas cursos de normas e reciclagem ou visitas
A236: ABRIL/2026 | B236: Despesa do consultor BARTOLOMEU | C236: Comercial | D236: 46141 | E236: DX2 | F236: 2 | G236: 383.56 | H236: =IF(OR(F236="",G236=""),"",F236*G236) -> 767.12 | I236: despesa trabalhista e combustivel do consultor dividido pelo total de vendas
A237: ABRIL/2026 | B237: Locação de veículos | C237: Frota | D237: 46141 | E237: DX2 | F237: 0 | G237: 0 | H237: =IF(OR(F237="",G237=""),"",F237*G237) -> 0 | I237: Veiculos Dtel emprestado para serviços na DX2 (2 carros)
A238: ABRIL/2026 | B238: km rodado da equipe DX2 para H&A | C238: Instalação | D238: 46141 | E238: H&A | F238: 0 | G238: 0 | H238: =IF(OR(F238="",G238=""),"",F238*G238) -> 0 | I238: Serviços das equipes técnicas Dtel
A239: ABRIL/2026 | B239: Vendas da equipe Soares e lins p/ Dtel | C239: Comercial | D239: 46141 | E239: Soares & Lins | F239: 1 | G239: 0 | H239: =IF(OR(F239="",G239=""),"",F239*G239) -> 0 | I239: Vendas instaladas
A240: ABRIL/2026 | B240: Treinamentos/integração | C240: RH | D240: 46141 | E240: Soares & Lins | F240: 0 | G240: 0 | H240: =IF(OR(F240="",G240=""),"",F240*G240) -> 0 | I240: Despesa com integração/alimentação
A241: ABRIL/2026 | B241: AGÊNCIA REGULADORA DOS SERVIÇOS PÚBLICOS DO ESTADO DE ALAGOAS - ARSAL | C241: Licitação | D241: 46141 | E241: Soares e Silva | F241: -1 | G241: 837.25 | H241: =IF(OR(F241="",G241=""),"",F241*G241) -> -837.25 | I241: mensalidade recebida pela Dtel (parcela abril)
A242: ABRIL/2026 | B242: Consultas e análises de crédito | C242: Comercial | D242: 46141 | E242: Voicenet | F242: 378 | G242: 1.86 | H242: =IF(OR(F242="",G242=""),"",F242*G242) -> 703.08 | I242: vendas cadastradas e consultadas pelo argos
A243: ABRIL/2026 | B243: Serviços prestados pela equipe Segurança do trabalho | C243: SST | D243: 46141 | E243: Voicenet | F243: 0 | G243: 0 | H243: =IF(OR(F243="",G243=""),"",F243*G243) -> 0 | I243: Serviços da equipe para Horas cursos de normas e reciclagem ou visitas
... A299: MAIO/2026 | B299: Despesa do coordenador TIAGO, pela gestão da equipe | C299: Comercial | D299: 46143 | E299: H&A | F299: 64 | G299: 23.15 | H299: =IF(OR(F299="",G299=""),"",F299*G299) -> 1481.6 | I299: despesa trabalhista dividida pela quantidade de vendas
A300: MAIO/2026 | B300: Vendas da equipe Dtel porta a porta | C300: Comercial | D300: 46143 | E300: H&A | F300: 1 | H300: =IF(OR(F300="",G300=""),"",F300*G300) | I300: Vendas instaladas
A301: MAIO/2026 | B301: Vendas da equipe DX2 para H&A | C301: Comercial | D301: 46143 | E301: H&A | F301: 3 | G301: 0 | H301: =IF(OR(F301="",G301=""),"",F301*G301) -> 0 | I301: Vendas instaladas
A302: MAIO/2026 | B302: Vendas da equipe H&A P/ VOICENET | C302: Comercial | D302: 46143 | E302: H&A | F302: 0 | G302: 0 | H302: =IF(OR(F302="",G302=""),"",F302*G302) -> 0 | I302: Vendas instaladas
A303: MAIO/2026 | B303: Vendas da equipe H&A para Dtel | C303: Comercial | D303: 46143 | E303: H&A | F303: 2 | G303: 0 | H303: =IF(OR(F303="",G303=""),"",F303*G303) -> 0 | I303: Vendas instaladas
A304: MAIO/2026 | B304: Vendas da equipe H&A para Dx2 | C304: Comercial | D304: 46143 | E304: H&A | F304: 5 | G304: 0 | H304: =IF(OR(F304="",G304=""),"",F304*G304) -> 0 | I304: Vendas instaladas
A305: MAIO/2026 | B305: Vendas da equipe H&A para soares e silva | C305: Comercial | D305: 46143 | E305: H&A | F305: 0 | G305: 0 | H305: =IF(OR(F305="",G305=""),"",F305*G305) -> 0 | I305: Vendas instaladas
...

Sheet Parâmetros
A1: INFORMAÇÕES ADICIONAIS POR SETOR (clientes, custo por cliente/funcionário, observações — nada foi descartado)
A3: Adm atendimento
A4: [A17] Total
A5: [D17] fórmula original: =SUBTOTAL(109,D2:D16)
A6: [C18] Total clientes grupo dtel, com h&a
A7: [D18] 189453
A8: [D19] 0.19
A10: C.O.E
A11: [A18] Total
A12: [C18] fórmula original: =SUBTOTAL(109,C2:C17)
A13: [D18] fórmula original: =SUBTOTAL(109,D2:D17)
A14: [A19] nº de clientes menos h&a e dx2, e souza e silva pois estão fazendo a distribuição dos serviços
... A247: [B26] fórmula original: =Tabela56457[[#Totals],[Total]]/D25
