Workbook

Sheet PARÂMETROS
A1: PARÂMETROS DE RATEIO — EMPRESAS PARCEIRAS/LICENCIADAS
A3: Mês de referência:
A5: Preencha o Nº de Clientes atendidos e o Nº de Funcionários da Dtel alocados a cada empresa. Estes números definem o % de rateio de cada setor (conforme critério definido na aba SETORES). O % Royalty é opcional — deixe 0% enquanto o rateio for só a custo (ver nota jurídico-fiscal abaixo).
A7: Empresa | B7: Nº de Clientes Atendidos | C7: Nº de Funcionários Dtel Alocados | D7: % de Clientes | E7: % de Funcionários | F7: % Royalty | G7: Mês
A8: Empresa Licenciada DX2 | B8: 6445 | C8: 34 | D8: =IFERROR(B8/SUMIFS($B$8:$B$907,$G$8:$G$907,G8),0) -> 0.033077914 | E8: =IFERROR(C8/SUMIFS($C$8:$C$907,$G$8:$G$907,G8),0) -> 0.032411821 | F8: 0 | G8: Junho/2026
A9: Empresa Licenciada H&A | B9: 13418 | C9: 32 | D9: =IFERROR(B9/SUMIFS($B$8:$B$907,$G$8:$G$907,G9),0) -> 0.068865702 | E9: =IFERROR(C9/SUMIFS($C$8:$C$907,$G$8:$G$907,G9),0) -> 0.030505243 | F9: 0 | G9: Junho/2026
A10: Empresa Licenciada SOLON ARAUJO | B10: 14441 | C10: 42 | D10: =IFERROR(B10/SUMIFS($B$8:$B$907,$G$8:$G$907,G10),0) -> 0.074116083 | E10: =IFERROR(C10/SUMIFS($C$8:$C$907,$G$8:$G$907,G10),0) -> 0.040038132 | F10: 0 | G10: Junho/2026
A11: Empresa Licenciada SOARES E LINS | B11: 3704 | C11: 11 | D11: =IFERROR(B11/SUMIFS($B$8:$B$907,$G$8:$G$907,G11),0) -> 0.019010177 | E11: =IFERROR(C11/SUMIFS($C$8:$C$907,$G$8:$G$907,G11),0) -> 0.010486177 | F11: 0 | G11: Junho/2026
A12: Empresa Licenciada SOARES E SILVA | B12: 6434 | C12: 42 | D12: =IFERROR(B12/SUMIFS($B$8:$B$907,$G$8:$G$907,G12),0) -> 0.033021458 | E12: =IFERROR(C12/SUMIFS($C$8:$C$907,$G$8:$G$907,G12),0) -> 0.040038132 | F12: 0 | G12: Junho/2026
A13: Empresa Licenciada SOUZA E SILVA | B13: 4749 | C13: 18 | D13: =IFERROR(B13/SUMIFS($B$8:$B$907,$G$8:$G$907,G13),0) -> 0.02437347 | E13: =IFERROR(C13/SUMIFS($C$8:$C$907,$G$8:$G$907,G13),0) -> 0.017159199 | F13: 0 | G13: Junho/2026
A14: Empresa Licenciada VOICENET | B14: 4795 | C14: 17 | D14: =IFERROR(B14/SUMIFS($B$8:$B$907,$G$8:$G$907,G14),0) -> 0.024609557 | E14: =IFERROR(C14/SUMIFS($C$8:$C$907,$G$8:$G$907,G14),0) -> 0.01620591 | F14: 0 | G14: Junho/2026
A15: DTEL (uso próprio) | B15: 140857 | C15: 853 | D15: =IFERROR(B15/SUMIFS($B$8:$B$907,$G$8:$G$907,G15),0) -> 0.72292564 | E15: =IFERROR(C15/SUMIFS($C$8:$C$907,$G$8:$G$907,G15),0) -> 0.81315539 | F15: 0 | G15: Junho/2026
A16: TOTAL | B16: =SUM(B8:B15) -> 194843 | C16: =SUM(C8:C15) -> 1049
A17: Empresa Licenciada DX2 | B17: 6280 | C17: 35 | D17: =IFERROR(B17/SUMIFS($B$8:$B$907,$G$8:$G$907,G17),0) -> 0.032823386 | E17: =IFERROR(C17/SUMIFS($C$8:$C$907,$G$8:$G$907,G17),0) -> 0.033238367 | F17: 0 | G17: Maio/2026
A18: Empresa Licenciada H&A | B18: 13402 | C18: 35 | D18: =IFERROR(B18/SUMIFS($B$8:$B$907,$G$8:$G$907,G18),0) -> 0.070047615 | E18: =IFERROR(C18/SUMIFS($C$8:$C$907,$G$8:$G$907,G18),0) -> 0.033238367 | F18: 0 | G18: Maio/2026
A19: Empresa Licenciada SOLON ARAUJO | B19: 14331 | C19: 42 | D19: =IFERROR(B19/SUMIFS($B$8:$B$907,$G$8:$G$907,G19),0) -> 0.074903176 | E19: =IFERROR(C19/SUMIFS($C$8:$C$907,$G$8:$G$907,G19),0) -> 0.03988604 | F19: 0 | G19: Maio/2026
A20: Empresa Licenciada SOARES E LINS | B20: 3650 | C20: 11 | D20: =IFERROR(B20/SUMIFS($B$8:$B$907,$G$8:$G$907,G20),0) -> 0.019077287 | E20: =IFERROR(C20/SUMIFS($C$8:$C$907,$G$8:$G$907,G20),0) -> 0.010446344 | F20: 0 | G20: Maio/2026
A21: Empresa Licenciada SOARES E SILVA | B21: 6396 | C21: 42 | D21: =IFERROR(B21/SUMIFS($B$8:$B$907,$G$8:$G$907,G21),0) -> 0.033429678 | E21: =IFERROR(C21/SUMIFS($C$8:$C$907,$G$8:$G$907,G21),0) -> 0.03988604 | F21: 0 | G21: Maio/2026
A22: Empresa Licenciada SOUZA E SILVA | B22: 4730 | C22: 18 | D22: =IFERROR(B22/SUMIFS($B$8:$B$907,$G$8:$G$907,G22),0) -> 0.024722073 | E22: =IFERROR(C22/SUMIFS($C$8:$C$907,$G$8:$G$907,G22),0) -> 0.017094017 | F22: 0 | G22: Maio/2026
A23: Empresa Licenciada VOICENET | B23: 4782 | C23: 20 | D23: =IFERROR(B23/SUMIFS($B$8:$B$907,$G$8:$G$907,G23),0) -> 0.024993859 | E23: =IFERROR(C23/SUMIFS($C$8:$C$907,$G$8:$G$907,G23),0) -> 0.018993352 | F23: 0 | G23: Maio/2026
A24: DTEL (uso próprio) | B24: 137756 | C24: 850 | D24: =IFERROR(B24/SUMIFS($B$8:$B$907,$G$8:$G$907,G24),0) -> 0.72000293 | E24: =IFERROR(C24/SUMIFS($C$8:$C$907,$G$8:$G$907,G24),0) -> 0.80721747 | F24: 0 | G24: Maio/2026
A25: TOTAL | B25: =SUM(B17:B24) -> 191327 | C25: =SUM(C17:C24) -> 1053
A26: Empresa Licenciada DX2 | B26: 6588 | C26: 34 | D26: =IFERROR(B26/SUMIFS($B$8:$B$907,$G$8:$G$907,G26),0) -> 0.032696249 | E26: =IFERROR(C26/SUMIFS($C$8:$C$907,$G$8:$G$907,G26),0) -> 0.031192661 | F26: 0 | G26: Julho/2026
A27: Empresa Licenciada H&A | B27: 13530 | C27: 0 | D27: =IFERROR(B27/SUMIFS($B$8:$B$907,$G$8:$G$907,G27),0) -> 0.067149401 | E27: =IFERROR(C27/SUMIFS($C$8:$C$907,$G$8:$G$907,G27),0) -> 0 | F27: 0 | G27: Julho/2026
A28: Empresa Licenciada SOLON ARAUJO | B28: 14689 | C28: 47 | D28: =IFERROR(B28/SUMIFS($B$8:$B$907,$G$8:$G$907,G28),0) -> 0.072901519 | E28: =IFERROR(C28/SUMIFS($C$8:$C$907,$G$8:$G$907,G28),0) -> 0.043119266 | F28: 0 | G28: Julho/2026
A29: Empresa Licenciada SOARES E LINS | B29: 3765 | C29: 11 | D29: =IFERROR(B29/SUMIFS($B$8:$B$907,$G$8:$G$907,G29),0) -> 0.018685698 | E29: =IFERROR(C29/SUMIFS($C$8:$C$907,$G$8:$G$907,G29),0) -> 0.010091743 | F29: 0 | G29: Julho/2026
A30: Empresa Licenciada SOARES E SILVA | B30: 6568 | C30: 50 | D30: =IFERROR(B30/SUMIFS($B$8:$B$907,$G$8:$G$907,G30),0) -> 0.032596989 | E30: =IFERROR(C30/SUMIFS($C$8:$C$907,$G$8:$G$907,G30),0) -> 0.04587156 | F30: 0 | G30: Julho/2026
A31: Empresa Licenciada SOUZA E SILVA | B31: 4805 | C31: 18 | D31: =IFERROR(B31/SUMIFS($B$8:$B$907,$G$8:$G$907,G31),0) -> 0.023847219 | E31: =IFERROR(C31/SUMIFS($C$8:$C$907,$G$8:$G$907,G31),0) -> 0.016513761 | F31: 0 | G31: Julho/2026
A32: Empresa Licenciada VOICENET | B32: 4806 | C32: 24 | D32: =IFERROR(B32/SUMIFS($B$8:$B$907,$G$8:$G$907,G32),0) -> 0.023852182 | E32: =IFERROR(C32/SUMIFS($C$8:$C$907,$G$8:$G$907,G32),0) -> 0.022018349 | F32: 0 | G32: Julho/2026
A33: DTEL (uso próprio) | B33: 146740 | C33: 906 | D33: =IFERROR(B33/SUMIFS($B$8:$B$907,$G$8:$G$907,G33),0) -> 0.72827074 | E33: =IFERROR(C33/SUMIFS($C$8:$C$907,$G$8:$G$907,G33),0) -> 0.83119266 | F33: 0 | G33: Julho/2026
A34: TOTAL | B34: =SUM(B26:B33) -> 201491 | C34: =SUM(C26:C33) -> 1090
A35: RATEIO POR EMPRESA
A36: Para cada setor, o % aplicado a cada empresa vem de PARÂMETROS: % de Clientes (se critério = Clientes) ou % de Funcionários (se critério = Funcionários). O Valor de Royalty só existe se a empresa tiver % Royalty > 0% em PARÂMETROS (padrão é 0%).
A38: Setor | B38: Critério | C38: Empresa | D38: % Aplicado | E38: Custo Total do Setor | F38: Valor de Custo Rateado | G38: % Royalty | H38: Valor de Royalty | I38: Valor Total a Cobrar | J38: Mês
A39: NOC | B39: =INDEX(SETORES!$B:$B,MATCH(A39,SETORES!$A:$A,0)) -> Clientes | C39: Empresa Licenciada DX2 | D39: =IF(B39="Clientes",SUMIFS(PARÂMETROS!$D$8:$D$907,PARÂMETROS!$A$8:$A$907,C39,PARÂMETROS!$G$8:$G$907,J39),SUMIFS(PARÂMETROS!$E$8:$E$907,PARÂMETROS!$A$8:$A$907,C39,PARÂMETROS!$G$8:$G$907,J39)) -> 0.033077914 | E39: =SUMIFS(SETORES!$D:$D,SETORES!$A:$A,A39,SETORES!$F:$F,J39) -> 69943.851 | F39: =IFERROR(D39*E39,0) -> 2313.5967 | G39: =SUMIFS(PARÂMETROS!$F$8:$F$907,PARÂMETROS!$A$8:$A$907,C39,PARÂMETROS!$G$8:$G$907,J39) -> 0 | H39: =IFERROR(F39*G39,0) -> 0 | I39: =F39+H39 -> 2313.5967 | J39: Junho/2026
A40: NOC | B40: =INDEX(SETORES!$B:$B,MATCH(A40,SETORES!$A:$A,0)) -> Clientes | C40: Empresa Licenciada H&A | D40: =IF(B40="Clientes",SUMIFS(PARÂMETROS!$D$8:$D$907,PARÂMETROS!$A$8:$A$907,C40,PARÂMETROS!$G$8:$G$907,J40),SUMIFS(PARÂMETROS!$E$8:$E$907,PARÂMETROS!$A$8:$A$907,C40,PARÂMETROS!$G$8:$G$907,J40)) -> 0.068865702 | E40: =SUMIFS(SETORES!$D:$D,SETORES!$A:$A,A40,SETORES!$F:$F,J40) -> 69943.851 | F40: =IFERROR(D40*E40,0) -> 4816.7324 | G40: =SUMIFS(PARÂMETROS!$F$8:$F$907,PARÂMETROS!$A$8:$A$907,C40,PARÂMETROS!$G$8:$G$907,J40) -> 0 | H40: =IFERROR(F40*G40,0) -> 0 | I40: =F40+H40 -> 4816.7324 | J40: Junho/2026
A41: NOC | B41: =INDEX(SETORES!$B:$B,MATCH(A41,SETORES!$A:$A,0)) -> Clientes | C41: Empresa Licenciada SOLON ARAUJO | D41: =IF(B41="Clientes",SUMIFS(PARÂMETROS!$D$8:$D$907,PARÂMETROS!$A$8:$A$907,C41,PARÂMETROS!$G$8:$G$907,J41),SUMIFS(PARÂMETROS!$E$8:$E$907,PARÂMETROS!$A$8:$A$907,C41,PARÂMETROS!$G$8:$G$907,J41)) -> 0.074116083 | E41: =SUMIFS(SETORES!$D:$D,SETORES!$A:$A,A41,SETORES!$F:$F,J41) -> 69943.851 | F41: =IFERROR(D41*E41,0) -> 5183.9643 | G41: =SUMIFS(PARÂMETROS!$F$8:$F$907,PARÂMETROS!$A$8:$A$907,C41,PARÂMETROS!$G$8:$G$907,J41) -> 0 | H41: =IFERROR(F41*G41,0) -> 0 | I41: =F41+H41 -> 5183.9643 | J41: Junho/2026
A42: NOC | B42: =INDEX(SETORES!$B:$B,MATCH(A42,SETORES!$A:$A,0)) -> Clientes | C42: Empresa Licenciada SOARES E LINS | D42: =IF(B42="Clientes",SUMIFS(PARÂMETROS!$D$8:$D$907,PARÂMETROS!$A$8:$A$907,C42,PARÂMETROS!$G$8:$G$907,J42),SUMIFS(PARÂMETROS!$E$8:$E$907,PARÂMETROS!$A$8:$A$907,C42,PARÂMETROS!$G$8:$G$907,J42)) -> 0.019010177 | E42: =SUMIFS(SETORES!$D:$D,SETORES!$A:$A,A42,SETORES!$F:$F,J42) -> 69943.851 | F42: =IFERROR(D42*E42,0) -> 1329.645 | G42: =SUMIFS(PARÂMETROS!$F$8:$F$907,PARÂMETROS!$A$8:$A$907,C42,PARÂMETROS!$G$8:$G$907,J42) -> 0 | H42: =IFERROR(F42*G42,0) -> 0 | I42: =F42+H42 -> 1329.645 | J42: Junho/2026
A43: NOC | B43: =INDEX(SETORES!$B:$B,MATCH(A43,SETORES!$A:$A,0)) -> Clientes | C43: Empresa Licenciada SOARES E SILVA | D43: =IF(B43="Clientes",SUMIFS(PARÂMETROS!$D$8:$D$907,PARÂMETROS!$A$8:$A$907,C43,PARÂMETROS!$G$8:$G$907,J43),SUMIFS(PARÂMETROS!$E$8:$E$907,PARÂMETROS!$A$8:$A$907,C43,PARÂMETROS!$G$8:$G$907,J43)) -> 0.033021458 | E43: =SUMIFS(SETORES!$D:$D,SETORES!$A:$A,A43,SETORES!$F:$F,J43) -> 69943.851 | F43: =IFERROR(D43*E43,0) -> 2309.648 | G43: =SUMIFS(PARÂMETROS!$F$8:$F$907,PARÂMETROS!$A$8:$A$907,C43,PARÂMETROS!$G$8:$G$907,J43) -> 0 | H43: =IFERROR(F43*G43,0) -> 0 | I43: =F43+H43 -> 2309.648 | J43: Junho/2026
A44: NOC | B44: =INDEX(SETORES!$B:$B,MATCH(A44,SETORES!$A:$A,0)) -> Clientes | C44: Empresa Licenciada SOUZA E SILVA | D44: =IF(B44="Clientes",SUMIFS(PARÂMETROS!$D$8:$D$907,PARÂMETROS!$A$8:$A$907,C44,PARÂMETROS!$G$8:$G$907,J44),SUMIFS(PARÂMETROS!$E$8:$E$907,PARÂMETROS!$A$8:$A$907,C44,PARÂMETROS!$G$8:$G$907,J44)) -> 0.02437347 | E44: =SUMIFS(SETORES!$D:$D,SETORES!$A:$A,A44,SETORES!$F:$F,J44) -> 69943.851 | F44: =IFERROR(D44*E44,0) -> 1704.7744 | G44: =SUMIFS(PARÂMETROS!$F$8:$F$907,PARÂMETROS!$A$8:$A$907,C44,PARÂMETROS!$G$8:$G$907,J44) -> 0 | H44: =IFERROR(F44*G44,0) -> 0 | I44: =F44+H44 -> 1704.7744 | J44: Junho/2026
A45: NOC | B45: =INDEX(SETORES!$B:$B,MATCH(A45,SETORES!$A:$A,0)) -> Clientes | C45: Empresa Licenciada VOICENET | D45: =IF(B45="Clientes",SUMIFS(PARÂMETROS!$D$8:$D$907,PARÂMETROS!$A$8:$A$907,C45,PARÂMETROS!$G$8:$G$907,J45),SUMIFS(PARÂMETROS!$E$8:$E$907,PARÂMETROS!$A$8:$A$907,C45,PARÂMETROS!$G$8:$G$907,J45)) -> 0.024609557 | E45: =SUMIFS(SETORES!$D:$D,SETORES!$A:$A,A45,SETORES!$F:$F,J45) -> 69943.851 | F45: =IFERROR(D45*E45,0) -> 1721.2872 | G45: =SUMIFS(PARÂMETROS!$F$8:$F$907,PARÂMETROS!$A$8:$A$907,C45,PARÂMETROS!$G$8:$G$907,J45) -> 0 | H45: =IFERROR(F45*G45,0) -> 0 | I45: =F45+H45 -> 1721.2872 | J45: Junho/2026
A46: NOC | B46: =INDEX(SETORES!$B:$B,MATCH(A46,SETORES!$A:$A,0)) -> Clientes | C46: DTEL (uso próprio) | D46: =IF(B46="Clientes",SUMIFS(PARÂMETROS!$D$8:$D$907,PARÂMETROS!$A$8:$A$907,C46,PARÂMETROS!$G$8:$G$907,J46),SUMIFS(PARÂMETROS!$E$8:$E$907,PARÂMETROS!$A$8:$A$907,C46,PARÂMETROS!$G$8:$G$907,J46)) -> 0.72292564 | E46: =SUMIFS(SETORES!$D:$D,SETORES!$A:$A,A46,SETORES!$F:$F,J46) -> 69943.851 | F46: =IFERROR(D46*E46,0) -> 50564.203 | G46: =SUMIFS(PARÂMETROS!$F$8:$F$907,PARÂMETROS!$A$8:$A$907,C46,PARÂMETROS!$G$8:$G$907,J46) -> 0 | H46: =IFERROR(F46*G46,0) -> 0 | I46: =F46+H46 -> 50564.203 | J46: Junho/2026
A47: RH | B47: =INDEX(SETORES!$B:$B,MATCH(A47,SETORES!$A:$A,0)) -> Funcionários | C47: Empresa Licenciada DX2 | D47: =IF(B47="Clientes",SUMIFS(PARÂMETROS!$D$8:$D$907,PARÂMETROS!$A$8:$A$907,C47,PARÂMETROS!$G$8:$G$907,J47),SUMIFS(PARÂMETROS!$E$8:$E$907,PARÂMETROS!$A$8:$A$907,C47,PARÂMETROS!$G$8:$G$907,J47)) -> 0.032411821 | E47: =SUMIFS(SETORES!$D:$D,SETORES!$A:$A,A47,SETORES!$F:$F,J47) -> 36047.874 | F47: =IFERROR(D47*E47,0) -> 1168.3772 | G47: =SUMIFS(PARÂMETROS!$F$8:$F$907,PARÂMETROS!$A$8:$A$907,C47,PARÂMETROS!$G$8:$G$907,J47) -> 0 | H47: =IFERROR(F47*G47,0) -> 0 | I47: =F47+H47 -> 1168.3772 | J47: Junho/2026
A48: RH | B48: =INDEX(SETORES!$B:$B,MATCH(A48,SETORES!$A:$A,0)) -> Funcionários | C48: Empresa Licenciada H&A | D48: =IF(B48="Clientes",SUMIFS(PARÂMETROS!$D$8:$D$907,PARÂMETROS!$A$8:$A$907,C48,PARÂMETROS!$G$8:$G$907,J48),SUMIFS(PARÂMETROS!$E$8:$E$907,PARÂMETROS!$A$8:$A$907,C48,PARÂMETROS!$G$8:$G$907,J48)) -> 0.030505243 | E48: =SUMIFS(SETORES!$D:$D,SETORES!$A:$A,A48,SETORES!$F:$F,J48) -> 36047.874 | F48: =IFERROR(D48*E48,0) -> 1099.6492 | G48: =SUMIFS(PARÂMETROS!$F$8:$F$907,PARÂMETROS!$A$8:$A$907,C48,PARÂMETROS!$G$8:$G$907,J48) -> 0 | H48: =IFERROR(F48*G48,0) -> 0 | I48: =F48+H48 -> 1099.6492 | J48: Junho/2026
A49: RH | B49: =INDEX(SETORES!$B:$B,MATCH(A49,SETORES!$A:$A,0)) -> Funcionários | C49: Empresa Licenciada SOLON ARAUJO | D49: =IF(B49="Clientes",SUMIFS(PARÂMETROS!$D$8:$D$907,PARÂMETROS!$A$8:$A$907,C49,PARÂMETROS!$G$8:$G$907,J49),SUMIFS(PARÂMETROS!$E$8:$E$907,PARÂMETROS!$A$8:$A$907,C49,PARÂMETROS!$G$8:$G$907,J49)) -> 0.040038132 | E49: =SUMIFS(SETORES!$D:$D,SETORES!$A:$A,A49,SETORES!$F:$F,J49) -> 36047.874 | F49: =IFERROR(D49*E49,0) -> 1443.2895 | G49: =SUMIFS(PARÂMETROS!$F$8:$F$907,PARÂMETROS!$A$8:$A$907,C49,PARÂMETROS!$G$8:$G$907,J49) -> 0 | H49: =IFERROR(F49*G49,0) -> 0 | I49: =F49+H49 -> 1443.2895 | J49: Junho/2026
A50: RH | B50: =INDEX(SETORES!$B:$B,MATCH(A50,SETORES!$A:$A,0)) -> Funcionários | C50: Empresa Licenciada SOARES E LINS | D50: =IF(B50="Clientes",SUMIFS(PARÂMETROS!$D$8:$D$907,PARÂMETROS!$A$8:$A$907,C50,PARÂMETROS!$G$8:$G$907,J50),SUMIFS(PARÂMETROS!$E$8:$E$907,PARÂMETROS!$A$8:$A$907,C50,PARÂMETROS!$G$8:$G$907,J50)) -> 0.010486177 | E50: =SUMIFS(SETORES!$D:$D,SETORES!$A:$A,A50,SETORES!$F:$F,J50) -> 36047.874 | F50: =IFERROR(D50*E50,0) -> 378.0044 | G50: =SUMIFS(PARÂMETROS!$F$8:$F$907,PARÂMETROS!$A$8:$A$907,C50,PARÂMETROS!$G$8:$G$907,J50) -> 0 | H50: =IFERROR(F50*G50,0) -> 0 | I50: =F50+H50 -> 378.0044 | J50: Junho/2026
... A638: Administrativo | B638: =INDEX(SETORES!$B:$B,MATCH(A638,SETORES!$A:$A,0)) -> Funcionários | C638: DTEL (uso próprio) | D638: =IF(B638="Clientes",SUMIFS(PARÂMETROS!$D$8:$D$907,PARÂMETROS!$A$8:$A$907,C638,PARÂMETROS!$G$8:$G$907,J638),SUMIFS(PARÂMETROS!$E$8:$E$907,PARÂMETROS!$A$8:$A$907,C638,PARÂMETROS!$G$8:$G$907,J638)) -> 0.83119266 | E638: =SUMIFS(SETORES!$D:$D,SETORES!$A:$A,A638,SETORES!$F:$F,J638) -> 23776.09 | F638: =IFERROR(D638*E638,0) -> 19762.512 | G638: =SUMIFS(PARÂMETROS!$F$8:$F$907,PARÂMETROS!$A$8:$A$907,C638,PARÂMETROS!$G$8:$G$907,J638) -> 0 | H638: =IFERROR(F638*G638,0) -> 0 | I638: =F638+H638 -> 19762.512 | J638: Julho/2026
A641: Legenda de cores:
A642: Azul | B642: Célula de entrada manual (preencher)
A643: Amarelo | B643: Linha de exemplo — ajuste os números reais
A644: Azul claro (aba SETORES) | B644: Setor rateado por % de CLIENTES
A645: Verde claro (aba SETORES) | B645: Setor rateado por % de FUNCIONÁRIOS
A647: Atenção — recomendação jurídico-fiscal:
A648: 1. Formalize um contrato/convênio de rateio de custos compartilhados com as empresas licenciadas
A649: definindo os critérios objetivos de rateio (nº de clientes e nº de funcionários) — exigência para dedutibilidade
A650: fiscal (IRPJ/CSLL) e para descaracterizar o reembolso como prestação de serviço com margem.
A651: 2. O reembolso deve ser feito a custo (sem markup/lucro), proporcional a métricas verificáveis — enquanto o
A652: % Royalty (coluna F) estiver em 0%, o cálculo continua sendo puro rateio de custo compartilhado.
A653: 3. Se um % Royalty for definido (>0%), isso deixa de ser rateio de custo puro e passa a ter natureza de
A654: royalty/licenciamento — tratamento fiscal diferente (ex.: incidência de IRRF sobre royalties) e exige um
A655: contrato de licenciamento/franquia, não apenas um convênio de rateio. Confirme com a contabilidade/jurídico
A656: antes de definir esse percentual.
A657: 4. Com a Reforma Tributária (LC 214/2025), rateios entre empresas de um mesmo grupo podem passar a sofrer
A658: incidência de IBS/CBS mesmo sem margem — vale confirmar o tratamento tributário com a contabilidade/jurídico.
A659: RATEIO POR EMPRESA — setores adicionados em 20/08/2026 (mesma fórmula/critério dos demais setores)
A660: COE | B660: =INDEX(SETORES!$B:$B,MATCH(A660,SETORES!$A:$A,0)) -> Clientes | C660: Empresa Licenciada DX2 | D660: =IF(B660="Clientes",SUMIFS(PARÂMETROS!$D$8:$D$907,PARÂMETROS!$A$8:$A$907,C660,PARÂMETROS!$G$8:$G$907,J660),SUMIFS(PARÂMETROS!$E$8:$E$907,PARÂMETROS!$A$8:$A$907,C660,PARÂMETROS!$G$8:$G$907,J660)) -> 0.032823386 | E660: =SUMIFS(SETORES!$D:$D,SETORES!$A:$A,A660,SETORES!$F:$F,J660) -> 83174.848 | F660: 0 | G660: =SUMIFS(PARÂMETROS!$F$8:$F$907,PARÂMETROS!$A$8:$A$907,C660,PARÂMETROS!$G$8:$G$907,J660) -> 0 | H660: =IFERROR(F660*G660,0) -> 0 | I660: =F660+H660 -> 0 | J660: Maio/2026
A661: COE | B661: =INDEX(SETORES!$B:$B,MATCH(A661,SETORES!$A:$A,0)) -> Clientes | C661: Empresa Licenciada H&A | D661: =IF(B661="Clientes",SUMIFS(PARÂMETROS!$D$8:$D$907,PARÂMETROS!$A$8:$A$907,C661,PARÂMETROS!$G$8:$G$907,J661),SUMIFS(PARÂMETROS!$E$8:$E$907,PARÂMETROS!$A$8:$A$907,C661,PARÂMETROS!$G$8:$G$907,J661)) -> 0.070047615 | E661: =SUMIFS(SETORES!$D:$D,SETORES!$A:$A,A661,SETORES!$F:$F,J661) -> 83174.848 | F661: 0 | G661: =SUMIFS(PARÂMETROS!$F$8:$F$907,PARÂMETROS!$A$8:$A$907,C661,PARÂMETROS!$G$8:$G$907,J661) -> 0 | H661: =IFERROR(F661*G661,0) -> 0 | I661: =F661+H661 -> 0 | J661: Maio/2026
A662: COE | B662: =INDEX(SETORES!$B:$B,MATCH(A662,SETORES!$A:$A,0)) -> Clientes | C662: Empresa Licenciada SOLON ARAUJO | D662: =IF(B662="Clientes",SUMIFS(PARÂMETROS!$D$8:$D$907,PARÂMETROS!$A$8:$A$907,C662,PARÂMETROS!$G$8:$G$907,J662),SUMIFS(PARÂMETROS!$E$8:$E$907,PARÂMETROS!$A$8:$A$907,C662,PARÂMETROS!$G$8:$G$907,J662)) -> 0.074903176 | E662: =SUMIFS(SETORES!$D:$D,SETORES!$A:$A,A662,SETORES!$F:$F,J662) -> 83174.848 | F662: 7542.682 | G662: =SUMIFS(PARÂMETROS!$F$8:$F$907,PARÂMETROS!$A$8:$A$907,C662,PARÂMETROS!$G$8:$G$907,J662) -> 0 | H662: =IFERROR(F662*G662,0) -> 0 | I662: =F662+H662 -> 7542.682 | J662: Maio/2026
A663: COE | B663: =INDEX(SETORES!$B:$B,MATCH(A663,SETORES!$A:$A,0)) -> Clientes | C663: Empresa Licenciada SOARES E LINS | D663: =IF(B663="Clientes",SUMIFS(PARÂMETROS!$D$8:$D$907,PARÂMETROS!$A$8:$A$907,C663,PARÂMETROS!$G$8:$G$907,J663),SUMIFS(PARÂMETROS!$E$8:$E$907,PARÂMETROS!$A$8:$A$907,C663,PARÂMETROS!$G$8:$G$907,J663)) -> 0.019077287 | E663: =SUMIFS(SETORES!$D:$D,SETORES!$A:$A,A663,SETORES!$F:$F,J663) -> 83174.848 | F663: 1921.0655 | G663: =SUMIFS(PARÂMETROS!$F$8:$F$907,PARÂMETROS!$A$8:$A$907,C663,PARÂMETROS!$G$8:$G$907,J663) -> 0 | H663: =IFERROR(F663*G663,0) -> 0 | I663: =F663+H663 -> 1921.0655 | J663: Maio/2026
A664: COE | B664: =INDEX(SETORES!$B:$B,MATCH(A664,SETORES!$A:$A,0)) -> Clientes | C664: Empresa Licenciada SOARES E SILVA | D664: =IF(B664="Clientes",SUMIFS(PARÂMETROS!$D$8:$D$907,PARÂMETROS!$A$8:$A$907,C664,PARÂMETROS!$G$8:$G$907,J664),SUMIFS(PARÂMETROS!$E$8:$E$907,PARÂMETROS!$A$8:$A$907,C664,PARÂMETROS!$G$8:$G$907,J664)) -> 0.033429678 | E664: =SUMIFS(SETORES!$D:$D,SETORES!$A:$A,A664,SETORES!$F:$F,J664) -> 83174.848 | F664: 3366.3383 | G664: =SUMIFS(PARÂMETROS!$F$8:$F$907,PARÂMETROS!$A$8:$A$907,C664,PARÂMETROS!$G$8:$G$907,J664) -> 0 | H664: =IFERROR(F664*G664,0) -> 0 | I664: =F664+H664 -> 3366.3383 | J664: Maio/2026
A665: COE | B665: =INDEX(SETORES!$B:$B,MATCH(A665,SETORES!$A:$A,0)) -> Clientes | C665: Empresa Licenciada SOUZA E SILVA | D665: =IF(B665="Clientes",SUMIFS(PARÂMETROS!$D$8:$D$907,PARÂMETROS!$A$8:$A$907,C665,PARÂMETROS!$G$8:$G$907,J665),SUMIFS(PARÂMETROS!$E$8:$E$907,PARÂMETROS!$A$8:$A$907,C665,PARÂMETROS!$G$8:$G$907,J665)) -> 0.024722073 | E665: =SUMIFS(SETORES!$D:$D,SETORES!$A:$A,A665,SETORES!$F:$F,J665) -> 83174.848 | F665: 0 | G665: =SUMIFS(PARÂMETROS!$F$8:$F$907,PARÂMETROS!$A$8:$A$907,C665,PARÂMETROS!$G$8:$G$907,J665) -> 0 | H665: =IFERROR(F665*G665,0) -> 0 | I665: =F665+H665 -> 0 | J665: Maio/2026
A666: COE | B666: =INDEX(SETORES!$B:$B,MATCH(A666,SETORES!$A:$A,0)) -> Clientes | C666: Empresa Licenciada VOICENET | D666: =IF(B666="Clientes",SUMIFS(PARÂMETROS!$D$8:$D$907,PARÂMETROS!$A$8:$A$907,C666,PARÂMETROS!$G$8:$G$907,J666),SUMIFS(PARÂMETROS!$E$8:$E$907,PARÂMETROS!$A$8:$A$907,C666,PARÂMETROS!$G$8:$G$907,J666)) -> 0.024993859 | E666: =SUMIFS(SETORES!$D:$D,SETORES!$A:$A,A666,SETORES!$F:$F,J666) -> 83174.848 | F666: 2516.8589 | G666: =SUMIFS(PARÂMETROS!$F$8:$F$907,PARÂMETROS!$A$8:$A$907,C666,PARÂMETROS!$G$8:$G$907,J666) -> 0 | H666: =IFERROR(F666*G666,0) -> 0 | I666: =F666+H666 -> 2516.8589 | J666: Maio/2026
A667: COE | B667: =INDEX(SETORES!$B:$B,MATCH(A667,SETORES!$A:$A,0)) -> Clientes | C667: DTEL (uso próprio) | D667: =IF(B667="Clientes",SUMIFS(PARÂMETROS!$D$8:$D$907,PARÂMETROS!$A$8:$A$907,C667,PARÂMETROS!$G$8:$G$907,J667),SUMIFS(PARÂMETROS!$E$8:$E$907,PARÂMETROS!$A$8:$A$907,C667,PARÂMETROS!$G$8:$G$907,J667)) -> 0.72000293 | E667: =SUMIFS(SETORES!$D:$D,SETORES!$A:$A,A667,SETORES!$F:$F,J667) -> 83174.848 | F667: =IFERROR(D667*E667,0) -> 59886.134 | G667: =SUMIFS(PARÂMETROS!$F$8:$F$907,PARÂMETROS!$A$8:$A$907,C667,PARÂMETROS!$G$8:$G$907,J667) -> 0 | H667: =IFERROR(F667*G667,0) -> 0 | I667: =F667+H667 -> 59886.134 | J667: Maio/2026
A668: COE | B668: =INDEX(SETORES!$B:$B,MATCH(A668,SETORES!$A:$A,0)) -> Clientes | C668: Empresa Licenciada DX2 | D668: =IF(B668="Clientes",SUMIFS(PARÂMETROS!$D$8:$D$907,PARÂMETROS!$A$8:$A$907,C668,PARÂMETROS!$G$8:$G$907,J668),SUMIFS(PARÂMETROS!$E$8:$E$907,PARÂMETROS!$A$8:$A$907,C668,PARÂMETROS!$G$8:$G$907,J668)) -> 0.033077914 | E668: =SUMIFS(SETORES!$D:$D,SETORES!$A:$A,A668,SETORES!$F:$F,J668) -> 94839.632 | F668: 0 | G668: =SUMIFS(PARÂMETROS!$F$8:$F$907,PARÂMETROS!$A$8:$A$907,C668,PARÂMETROS!$G$8:$G$907,J668) -> 0 | H668: =IFERROR(F668*G668,0) -> 0 | I668: =F668+H668 -> 0 | J668: Junho/2026
A669: COE | B669: =INDEX(SETORES!$B:$B,MATCH(A669,SETORES!$A:$A,0)) -> Clientes | C669: Empresa Licenciada H&A | D669: =IF(B669="Clientes",SUMIFS(PARÂMETROS!$D$8:$D$907,PARÂMETROS!$A$8:$A$907,C669,PARÂMETROS!$G$8:$G$907,J669),SUMIFS(PARÂMETROS!$E$8:$E$907,PARÂMETROS!$A$8:$A$907,C669,PARÂMETROS!$G$8:$G$907,J669)) -> 0.068865702 | E669: =SUMIFS(SETORES!$D:$D,SETORES!$A:$A,A669,SETORES!$F:$F,J669) -> 94839.632 | F669: 0 | G669: =SUMIFS(PARÂMETROS!$F$8:$F$907,PARÂMETROS!$A$8:$A$907,C669,PARÂMETROS!$G$8:$G$907,J669) -> 0 | H669: =IFERROR(F669*G669,0) -> 0 | I669: =F669+H669 -> 0 | J669: Junho/2026
A670: COE | B670: =INDEX(SETORES!$B:$B,MATCH(A670,SETORES!$A:$A,0)) -> Clientes | C670: Empresa Licenciada SOLON ARAUJO | D670: =IF(B670="Clientes",SUMIFS(PARÂMETROS!$D$8:$D$907,PARÂMETROS!$A$8:$A$907,C670,PARÂMETROS!$G$8:$G$907,J670),SUMIFS(PARÂMETROS!$E$8:$E$907,PARÂMETROS!$A$8:$A$907,C670,PARÂMETROS!$G$8:$G$907,J670)) -> 0.074116083 | E670: =SUMIFS(SETORES!$D:$D,SETORES!$A:$A,A670,SETORES!$F:$F,J670) -> 94839.632 | F670: 8141.6567 | G670: =SUMIFS(PARÂMETROS!$F$8:$F$907,PARÂMETROS!$A$8:$A$907,C670,PARÂMETROS!$G$8:$G$907,J670) -> 0 | H670: =IFERROR(F670*G670,0) -> 0 | I670: =F670+H670 -> 8141.6567 | J670: Junho/2026
A671: COE | B671: =INDEX(SETORES!$B:$B,MATCH(A671,SETORES!$A:$A,0)) -> Clientes | C671: Empresa Licenciada SOARES E LINS | D671: =IF(B671="Clientes",SUMIFS(PARÂMETROS!$D$8:$D$907,PARÂMETROS!$A$8:$A$907,C671,PARÂMETROS!$G$8:$G$907,J671),SUMIFS(PARÂMETROS!$E$8:$E$907,PARÂMETROS!$A$8:$A$907,C671,PARÂMETROS!$G$8:$G$907,J671)) -> 0.019010177 | E671: =SUMIFS(SETORES!$D:$D,SETORES!$A:$A,A671,SETORES!$F:$F,J671) -> 94839.632 | F671: 2088.2693 | G671: =SUMIFS(PARÂMETROS!$F$8:$F$907,PARÂMETROS!$A$8:$A$907,C671,PARÂMETROS!$G$8:$G$907,J671) -> 0 | H671: =IFERROR(F671*G671,0) -> 0 | I671: =F671+H671 -> 2088.2693 | J671: Junho/2026
A672: COE | B672: =INDEX(SETORES!$B:$B,MATCH(A672,SETORES!$A:$A,0)) -> Clientes | C672: Empresa Licenciada SOARES E SILVA | D672: =IF(B672="Clientes",SUMIFS(PARÂMETROS!$D$8:$D$907,PARÂMETROS!$A$8:$A$907,C672,PARÂMETROS!$G$8:$G$907,J672),SUMIFS(PARÂMETROS!$E$8:$E$907,PARÂMETROS!$A$8:$A$907,C672,PARÂMETROS!$G$8:$G$907,J672)) -> 0.033021458 | E672: =SUMIFS(SETORES!$D:$D,SETORES!$A:$A,A672,SETORES!$F:$F,J672) -> 94839.632 | F672: 3627.4094 | G672: =SUMIFS(PARÂMETROS!$F$8:$F$907,PARÂMETROS!$A$8:$A$907,C672,PARÂMETROS!$G$8:$G$907,J672) -> 0 | H672: =IFERROR(F672*G672,0) -> 0 | I672: =F672+H672 -> 3627.4094 | J672: Junho/2026
A673: COE | B673: =INDEX(SETORES!$B:$B,MATCH(A673,SETORES!$A:$A,0)) -> Clientes | C673: Empresa Licenciada SOUZA E SILVA | D673: =IF(B673="Clientes",SUMIFS(PARÂMETROS!$D$8:$D$907,PARÂMETROS!$A$8:$A$907,C673,PARÂMETROS!$G$8:$G$907,J673),SUMIFS(PARÂMETROS!$E$8:$E$907,PARÂMETROS!$A$8:$A$907,C673,PARÂMETROS!$G$8:$G$907,J673)) -> 0.02437347 | E673: =SUMIFS(SETORES!$D:$D,SETORES!$A:$A,A673,SETORES!$F:$F,J673) -> 94839.632 | F673: 0 | G673: =SUMIFS(PARÂMETROS!$F$8:$F$907,PARÂMETROS!$A$8:$A$907,C673,PARÂMETROS!$G$8:$G$907,J673) -> 0 | H673: =IFERROR(F673*G673,0) -> 0 | I673: =F673+H673 -> 0 | J673: Junho/2026
A674: COE | B674: =INDEX(SETORES!$B:$B,MATCH(A674,SETORES!$A:$A,0)) -> Clientes | C674: Empresa Licenciada VOICENET | D674: =IF(B674="Clientes",SUMIFS(PARÂMETROS!$D$8:$D$907,PARÂMETROS!$A$8:$A$907,C674,PARÂMETROS!$G$8:$G$907,J674),SUMIFS(PARÂMETROS!$E$8:$E$907,PARÂMETROS!$A$8:$A$907,C674,PARÂMETROS!$G$8:$G$907,J674)) -> 0.024609557 | E674: =SUMIFS(SETORES!$D:$D,SETORES!$A:$A,A674,SETORES!$F:$F,J674) -> 94839.632 | F674: 2703.3615 | G674: =SUMIFS(PARÂMETROS!$F$8:$F$907,PARÂMETROS!$A$8:$A$907,C674,PARÂMETROS!$G$8:$G$907,J674) -> 0 | H674: =IFERROR(F674*G674,0) -> 0 | I674: =F674+H674 -> 2703.3615 | J674: Junho/2026
A675: COE | B675: =INDEX(SETORES!$B:$B,MATCH(A675,SETORES!$A:$A,0)) -> Clientes | C675: DTEL (uso próprio) | D675: =IF(B675="Clientes",SUMIFS(PARÂMETROS!$D$8:$D$907,PARÂMETROS!$A$8:$A$907,C675,PARÂMETROS!$G$8:$G$907,J675),SUMIFS(PARÂMETROS!$E$8:$E$907,PARÂMETROS!$A$8:$A$907,C675,PARÂMETROS!$G$8:$G$907,J675)) -> 0.72292564 | E675: =SUMIFS(SETORES!$D:$D,SETORES!$A:$A,A675,SETORES!$F:$F,J675) -> 94839.632 | F675: =IFERROR(D675*E675,0) -> 68562.001 | G675: =SUMIFS(PARÂMETROS!$F$8:$F$907,PARÂMETROS!$A$8:$A$907,C675,PARÂMETROS!$G$8:$G$907,J675) -> 0 | H675: =IFERROR(F675*G675,0) -> 0 | I675: =F675+H675 -> 68562.001 | J675: Junho/2026
A676: COE | B676: =INDEX(SETORES!$B:$B,MATCH(A676,SETORES!$A:$A,0)) -> Clientes | C676: Empresa Licenciada DX2 | D676: =IF(B676="Clientes",SUMIFS(PARÂMETROS!$D$8:$D$907,PARÂMETROS!$A$8:$A$907,C676,PARÂMETROS!$G$8:$G$907,J676),SUMIFS(PARÂMETROS!$E$8:$E$907,PARÂMETROS!$A$8:$A$907,C676,PARÂMETROS!$G$8:$G$907,J676)) -> 0.032696249 | E676: =SUMIFS(SETORES!$D:$D,SETORES!$A:$A,A676,SETORES!$F:$F,J676) -> 78661.701 | F676: 0 | G676: =SUMIFS(PARÂMETROS!$F$8:$F$907,PARÂMETROS!$A$8:$A$907,C676,PARÂMETROS!$G$8:$G$907,J676) -> 0 | H676: =IFERROR(F676*G676,0) -> 0 | I676: =F676+H676 -> 0 | J676: Julho/2026
A677: COE | B677: =INDEX(SETORES!$B:$B,MATCH(A677,SETORES!$A:$A,0)) -> Clientes | C677: Empresa Licenciada H&A | D677: =IF(B677="Clientes",SUMIFS(PARÂMETROS!$D$8:$D$907,PARÂMETROS!$A$8:$A$907,C677,PARÂMETROS!$G$8:$G$907,J677),SUMIFS(PARÂMETROS!$E$8:$E$907,PARÂMETROS!$A$8:$A$907,C677,PARÂMETROS!$G$8:$G$907,J677)) -> 0.067149401 | E677: =SUMIFS(SETORES!$D:$D,SETORES!$A:$A,A677,SETORES!$F:$F,J677) -> 78661.701 | F677: 0 | G677: =SUMIFS(PARÂMETROS!$F$8:$F$907,PARÂMETROS!$A$8:$A$907,C677,PARÂMETROS!$G$8:$G$907,J677) -> 0 | H677: =IFERROR(F677*G677,0) -> 0 | I677: =F677+H677 -> 0 | J677: Julho/2026
A678: COE | B678: =INDEX(SETORES!$B:$B,MATCH(A678,SETORES!$A:$A,0)) -> Clientes | C678: Empresa Licenciada SOLON ARAUJO | D678: =IF(B678="Clientes",SUMIFS(PARÂMETROS!$D$8:$D$907,PARÂMETROS!$A$8:$A$907,C678,PARÂMETROS!$G$8:$G$907,J678),SUMIFS(PARÂMETROS!$E$8:$E$907,PARÂMETROS!$A$8:$A$907,C678,PARÂMETROS!$G$8:$G$907,J678)) -> 0.072901519 | E678: =SUMIFS(SETORES!$D:$D,SETORES!$A:$A,A678,SETORES!$F:$F,J678) -> 78661.701 | F678: 6316.27 | G678: =SUMIFS(PARÂMETROS!$F$8:$F$907,PARÂMETROS!$A$8:$A$907,C678,PARÂMETROS!$G$8:$G$907,J678) -> 0 | H678: =IFERROR(F678*G678,0) -> 0 | I678: =F678+H678 -> 6316.27 | J678: Julho/2026
A679: COE | B679: =INDEX(SETORES!$B:$B,MATCH(A679,SETORES!$A:$A,0)) -> Clientes | C679: Empresa Licenciada SOARES E LINS | D679: =IF(B679="Clientes",SUMIFS(PARÂMETROS!$D$8:$D$907,PARÂMETROS!$A$8:$A$907,C679,PARÂMETROS!$G$8:$G$907,J679),SUMIFS(PARÂMETROS!$E$8:$E$907,PARÂMETROS!$A$8:$A$907,C679,PARÂMETROS!$G$8:$G$907,J679)) -> 0.018685698 | E679: =SUMIFS(SETORES!$D:$D,SETORES!$A:$A,A679,SETORES!$F:$F,J679) -> 78661.701 | F679: 1618.95 | G679: =SUMIFS(PARÂMETROS!$F$8:$F$907,PARÂMETROS!$A$8:$A$907,C679,PARÂMETROS!$G$8:$G$907,J679) -> 0 | H679: =IFERROR(F679*G679,0) -> 0 | I679: =F679+H679 -> 1618.95 | J679: Julho/2026
A680: COE | B680: =INDEX(SETORES!$B:$B,MATCH(A680,SETORES!$A:$A,0)) -> Clientes | C680: Empresa Licenciada SOARES E SILVA | D680: =IF(B680="Clientes",SUMIFS(PARÂMETROS!$D$8:$D$907,PARÂMETROS!$A$8:$A$907,C680,PARÂMETROS!$G$8:$G$907,J680),SUMIFS(PARÂMETROS!$E$8:$E$907,PARÂMETROS!$A$8:$A$907,C680,PARÂMETROS!$G$8:$G$907,J680)) -> 0.032596989 | E680: =SUMIFS(SETORES!$D:$D,SETORES!$A:$A,A680,SETORES!$F:$F,J680) -> 78661.701 | F680: 0 | G680: =SUMIFS(PARÂMETROS!$F$8:$F$907,PARÂMETROS!$A$8:$A$907,C680,PARÂMETROS!$G$8:$G$907,J680) -> 0 | H680: =IFERROR(F680*G680,0) -> 0 | I680: =F680+H680 -> 0 | J680: Julho/2026
A681: COE | B681: =INDEX(SETORES!$B:$B,MATCH(A681,SETORES!$A:$A,0)) -> Clientes | C681: Empresa Licenciada SOUZA E SILVA | D681: =IF(B681="Clientes",SUMIFS(PARÂMETROS!$D$8:$D$907,PARÂMETROS!$A$8:$A$907,C681,PARÂMETROS!$G$8:$G$907,J681),SUMIFS(PARÂMETROS!$E$8:$E$907,PARÂMETROS!$A$8:$A$907,C681,PARÂMETROS!$G$8:$G$907,J681)) -> 0.023847219 | E681: =SUMIFS(SETORES!$D:$D,SETORES!$A:$A,A681,SETORES!$F:$F,J681) -> 78661.701 | F681: 0 | G681: =SUMIFS(PARÂMETROS!$F$8:$F$907,PARÂMETROS!$A$8:$A$907,C681,PARÂMETROS!$G$8:$G$907,J681) -> 0 | H681: =IFERROR(F681*G681,0) -> 0 | I681: =F681+H681 -> 0 | J681: Julho/2026
A682: COE | B682: =INDEX(SETORES!$B:$B,MATCH(A682,SETORES!$A:$A,0)) -> Clientes | C682: Empresa Licenciada VOICENET | D682: =IF(B682="Clientes",SUMIFS(PARÂMETROS!$D$8:$D$907,PARÂMETROS!$A$8:$A$907,C682,PARÂMETROS!$G$8:$G$907,J682),SUMIFS(PARÂMETROS!$E$8:$E$907,PARÂMETROS!$A$8:$A$907,C682,PARÂMETROS!$G$8:$G$907,J682)) -> 0.023852182 | E682: =SUMIFS(SETORES!$D:$D,SETORES!$A:$A,A682,SETORES!$F:$F,J682) -> 78661.701 | F682: 2066.58 | G682: =SUMIFS(PARÂMETROS!$F$8:$F$907,PARÂMETROS!$A$8:$A$907,C682,PARÂMETROS!$G$8:$G$907,J682) -> 0 | H682: =IFERROR(F682*G682,0) -> 0 | I682: =F682+H682 -> 2066.58 | J682: Julho/2026
A683: COE | B683: =INDEX(SETORES!$B:$B,MATCH(A683,SETORES!$A:$A,0)) -> Clientes | C683: DTEL (uso próprio) | D683: =IF(B683="Clientes",SUMIFS(PARÂMETROS!$D$8:$D$907,PARÂMETROS!$A$8:$A$907,C683,PARÂMETROS!$G$8:$G$907,J683),SUMIFS(PARÂMETROS!$E$8:$E$907,PARÂMETROS!$A$8:$A$907,C683,PARÂMETROS!$G$8:$G$907,J683)) -> 0.72827074 | E683: =SUMIFS(SETORES!$D:$D,SETORES!$A:$A,A683,SETORES!$F:$F,J683) -> 78661.701 | F683: =IFERROR(D683*E683,0) -> 57287.015 | G683: =SUMIFS(PARÂMETROS!$F$8:$F$907,PARÂMETROS!$A$8:$A$907,C683,PARÂMETROS!$G$8:$G$907,J683) -> 0 | H683: =IFERROR(F683*G683,0) -> 0 | I683: =F683+H683 -> 57287.015 | J683: Julho/2026
A684: Cozinha | B684: =INDEX(SETORES!$B:$B,MATCH(A684,SETORES!$A:$A,0)) -> Funcionários | C684: Empresa Licenciada DX2 | D684: =IF(B684="Clientes",SUMIFS(PARÂMETROS!$D$8:$D$907,PARÂMETROS!$A$8:$A$907,C684,PARÂMETROS!$G$8:$G$907,J684),SUMIFS(PARÂMETROS!$E$8:$E$907,PARÂMETROS!$A$8:$A$907,C684,PARÂMETROS!$G$8:$G$907,J684)) -> 0.033238367 | E684: =SUMIFS(SETORES!$D:$D,SETORES!$A:$A,A684,SETORES!$F:$F,J684) -> 28357.989 | F684: =IFERROR(D684*E684,0) -> 942.57324 | G684: =SUMIFS(PARÂMETROS!$F$8:$F$907,PARÂMETROS!$A$8:$A$907,C684,PARÂMETROS!$G$8:$G$907,J684) -> 0 | H684: =IFERROR(F684*G684,0) -> 0 | I684: =F684+H684 -> 942.57324 | J684: Maio/2026
A685: Cozinha | B685: =INDEX(SETORES!$B:$B,MATCH(A685,SETORES!$A:$A,0)) -> Funcionários | C685: Empresa Licenciada H&A | D685: =IF(B685="Clientes",SUMIFS(PARÂMETROS!$D$8:$D$907,PARÂMETROS!$A$8:$A$907,C685,PARÂMETROS!$G$8:$G$907,J685),SUMIFS(PARÂMETROS!$E$8:$E$907,PARÂMETROS!$A$8:$A$907,C685,PARÂMETROS!$G$8:$G$907,J685)) -> 0.033238367 | E685: =SUMIFS(SETORES!$D:$D,SETORES!$A:$A,A685,SETORES!$F:$F,J685) -> 28357.989 | F685: =IFERROR(D685*E685,0) -> 942.57324 | G685: =SUMIFS(PARÂMETROS!$F$8:$F$907,PARÂMETROS!$A$8:$A$907,C685,PARÂMETROS!$G$8:$G$907,J685) -> 0 | H685: =IFERROR(F685*G685,0) -> 0 | I685: =F685+H685 -> 942.57324 | J685: Maio/2026
A686: Cozinha | B686: =INDEX(SETORES!$B:$B,MATCH(A686,SETORES!$A:$A,0)) -> Funcionários | C686: Empresa Licenciada SOLON ARAUJO | D686: =IF(B686="Clientes",SUMIFS(PARÂMETROS!$D$8:$D$907,PARÂMETROS!$A$8:$A$907,C686,PARÂMETROS!$G$8:$G$907,J686),SUMIFS(PARÂMETROS!$E$8:$E$907,PARÂMETROS!$A$8:$A$907,C686,PARÂMETROS!$G$8:$G$907,J686)) -> 0.03988604 | E686: =SUMIFS(SETORES!$D:$D,SETORES!$A:$A,A686,SETORES!$F:$F,J686) -> 28357.989 | F686: =IFERROR(D686*E686,0) -> 1131.0879 | G686: =SUMIFS(PARÂMETROS!$F$8:$F$907,PARÂMETROS!$A$8:$A$907,C686,PARÂMETROS!$G$8:$G$907,J686) -> 0 | H686: =IFERROR(F686*G686,0) -> 0 | I686: =F686+H686 -> 1131.0879 | J686: Maio/2026
A687: Cozinha | B687: =INDEX(SETORES!$B:$B,MATCH(A687,SETORES!$A:$A,0)) -> Funcionários | C687: Empresa Licenciada SOARES E LINS | D687: =IF(B687="Clientes",SUMIFS(PARÂMETROS!$D$8:$D$907,PARÂMETROS!$A$8:$A$907,C687,PARÂMETROS!$G$8:$G$907,J687),SUMIFS(PARÂMETROS!$E$8:$E$907,PARÂMETROS!$A$8:$A$907,C687,PARÂMETROS!$G$8:$G$907,J687)) -> 0.010446344 | E687: =SUMIFS(SETORES!$D:$D,SETORES!$A:$A,A687,SETORES!$F:$F,J687) -> 28357.989 | F687: =IFERROR(D687*E687,0) -> 296.2373 | G687: =SUMIFS(PARÂMETROS!$F$8:$F$907,PARÂMETROS!$A$8:$A$907,C687,PARÂMETROS!$G$8:$G$907,J687) -> 0 | H687: =IFERROR(F687*G687,0) -> 0 | I687: =F687+H687 -> 296.2373 | J687: Maio/2026
A688: Cozinha | B688: =INDEX(SETORES!$B:$B,MATCH(A688,SETORES!$A:$A,0)) -> Funcionários | C688: Empresa Licenciada SOARES E SILVA | D688: =IF(B688="Clientes",SUMIFS(PARÂMETROS!$D$8:$D$907,PARÂMETROS!$A$8:$A$907,C688,PARÂMETROS!$G$8:$G$907,J688),SUMIFS(PARÂMETROS!$E$8:$E$907,PARÂMETROS!$A$8:$A$907,C688,PARÂMETROS!$G$8:$G$907,J688)) -> 0.03988604 | E688: =SUMIFS(SETORES!$D:$D,SETORES!$A:$A,A688,SETORES!$F:$F,J688) -> 28357.989 | F688: =IFERROR(D688*E688,0) -> 1131.0879 | G688: =SUMIFS(PARÂMETROS!$F$8:$F$907,PARÂMETROS!$A$8:$A$907,C688,PARÂMETROS!$G$8:$G$907,J688) -> 0 | H688: =IFERROR(F688*G688,0) -> 0 | I688: =F688+H688 -> 1131.0879 | J688: Maio/2026
A689: Cozinha | B689: =INDEX(SETORES!$B:$B,MATCH(A689,SETORES!$A:$A,0)) -> Funcionários | C689: Empresa Licenciada SOUZA E SILVA | D689: =IF(B689="Clientes",SUMIFS(PARÂMETROS!$D$8:$D$907,PARÂMETROS!$A$8:$A$907,C689,PARÂMETROS!$G$8:$G$907,J689),SUMIFS(PARÂMETROS!$E$8:$E$907,PARÂMETROS!$A$8:$A$907,C689,PARÂMETROS!$G$8:$G$907,J689)) -> 0.017094017 | E689: =SUMIFS(SETORES!$D:$D,SETORES!$A:$A,A689,SETORES!$F:$F,J689) -> 28357.989 | F689: =IFERROR(D689*E689,0) -> 484.75195 | G689: =SUMIFS(PARÂMETROS!$F$8:$F$907,PARÂMETROS!$A$8:$A$907,C689,PARÂMETROS!$G$8:$G$907,J689) -> 0 | H689: =IFERROR(F689*G689,0) -> 0 | I689: =F689+H689 -> 484.75195 | J689: Maio/2026
A690: Cozinha | B690: =INDEX(SETORES!$B:$B,MATCH(A690,SETORES!$A:$A,0)) -> Funcionários | C690: Empresa Licenciada VOICENET | D690: =IF(B690="Clientes",SUMIFS(PARÂMETROS!$D$8:$D$907,PARÂMETROS!$A$8:$A$907,C690,PARÂMETROS!$G$8:$G$907,J690),SUMIFS(PARÂMETROS!$E$8:$E$907,PARÂMETROS!$A$8:$A$907,C690,PARÂMETROS!$G$8:$G$907,J690)) -> 0.018993352 | E690: =SUMIFS(SETORES!$D:$D,SETORES!$A:$A,A690,SETORES!$F:$F,J690) -> 28357.989 | F690: =IFERROR(D690*E690,0) -> 538.61328 | G690: =SUMIFS(PARÂMETROS!$F$8:$F$907,PARÂMETROS!$A$8:$A$907,C690,PARÂMETROS!$G$8:$G$907,J690) -> 0 | H690: =IFERROR(F690*G690,0) -> 0 | I690: =F690+H690 -> 538.61328 | J690: Maio/2026
A691: Cozinha | B691: =INDEX(SETORES!$B:$B,MATCH(A691,SETORES!$A:$A,0)) -> Funcionários | C691: DTEL (uso próprio) | D691: =IF(B691="Clientes",SUMIFS(PARÂMETROS!$D$8:$D$907,PARÂMETROS!$A$8:$A$907,C691,PARÂMETROS!$G$8:$G$907,J691),SUMIFS(PARÂMETROS!$E$8:$E$907,PARÂMETROS!$A$8:$A$907,C691,PARÂMETROS!$G$8:$G$907,J691)) -> 0.80721747 | E691: =SUMIFS(SETORES!$D:$D,SETORES!$A:$A,A691,SETORES!$F:$F,J691) -> 28357.989 | F691: =IFERROR(D691*E691,0) -> 22891.064 | G691: =SUMIFS(PARÂMETROS!$F$8:$F$907,PARÂMETROS!$A$8:$A$907,C691,PARÂMETROS!$G$8:$G$907,J691) -> 0 | H691: =IFERROR(F691*G691,0) -> 0 | I691: =F691+H691 -> 22891.064 | J691: Maio/2026
A692: Cozinha | B692: =INDEX(SETORES!$B:$B,MATCH(A692,SETORES!$A:$A,0)) -> Funcionários | C692: Empresa Licenciada DX2 | D692: =IF(B692="Clientes",SUMIFS(PARÂMETROS!$D$8:$D$907,PARÂMETROS!$A$8:$A$907,C692,PARÂMETROS!$G$8:$G$907,J692),SUMIFS(PARÂMETROS!$E$8:$E$907,PARÂMETROS!$A$8:$A$907,C692,PARÂMETROS!$G$8:$G$907,J692)) -> 0.032411821 | E692: =SUMIFS(SETORES!$D:$D,SETORES!$A:$A,A692,SETORES!$F:$F,J692) -> 47063.981 | F692: =IFERROR(D692*E692,0) -> 1525.4293 | G692: =SUMIFS(PARÂMETROS!$F$8:$F$907,PARÂMETROS!$A$8:$A$907,C692,PARÂMETROS!$G$8:$G$907,J692) -> 0 | H692: =IFERROR(F692*G692,0) -> 0 | I692: =F692+H692 -> 1525.4293 | J692: Junho/2026
A693: Cozinha | B693: =INDEX(SETORES!$B:$B,MATCH(A693,SETORES!$A:$A,0)) -> Funcionários | C693: Empresa Licenciada H&A | D693: =IF(B693="Clientes",SUMIFS(PARÂMETROS!$D$8:$D$907,PARÂMETROS!$A$8:$A$907,C693,PARÂMETROS!$G$8:$G$907,J693),SUMIFS(PARÂMETROS!$E$8:$E$907,PARÂMETROS!$A$8:$A$907,C693,PARÂMETROS!$G$8:$G$907,J693)) -> 0.030505243 | E693: =SUMIFS(SETORES!$D:$D,SETORES!$A:$A,A693,SETORES!$F:$F,J693) -> 47063.981 | F693: =IFERROR(D693*E693,0) -> 1435.6982 | G693: =SUMIFS(PARÂMETROS!$F$8:$F$907,PARÂMETROS!$A$8:$A$907,C693,PARÂMETROS!$G$8:$G$907,J693) -> 0 | H693: =IFERROR(F693*G693,0) -> 0 | I693: =F693+H693 -> 1435.6982 | J693: Junho/2026
A694: Cozinha | B694: =INDEX(SETORES!$B:$B,MATCH(A694,SETORES!$A:$A,0)) -> Funcionários | C694: Empresa Licenciada SOLON ARAUJO | D694: =IF(B694="Clientes",SUMIFS(PARÂMETROS!$D$8:$D$907,PARÂMETROS!$A$8:$A$907,C694,PARÂMETROS!$G$8:$G$907,J694),SUMIFS(PARÂMETROS!$E$8:$E$907,PARÂMETROS!$A$8:$A$907,C694,PARÂMETROS!$G$8:$G$907,J694)) -> 0.040038132 | E694: =SUMIFS(SETORES!$D:$D,SETORES!$A:$A,A694,SETORES!$F:$F,J694) -> 47063.981 | F694: =IFERROR(D694*E694,0) -> 1884.3539 | G694: =SUMIFS(PARÂMETROS!$F$8:$F$907,PARÂMETROS!$A$8:$A$907,C694,PARÂMETROS!$G$8:$G$907,J694) -> 0 | H694: =IFERROR(F694*G694,0) -> 0 | I694: =F694+H694 -> 1884.3539 | J694: Junho/2026
...

Sheet SETORES
A1: SETORES — CRITÉRIO DE RATEIO
A2: Critério de Rateio define como o custo do setor será dividido entre as empresas: por % de CLIENTES ou por % de FUNCIONÁRIOS (ver aba PARÂMETROS). Custo Unitário = Custo Total do setor dividido pelo nº total de clientes ou funcionários, conforme o critério. A coluna "Nº de Funcionários/Clientes" mostra esse divisor (a base de rateio) usado para chegar ao Custo Unitário de cada linha.
A4: Setor | B4: Critério de Rateio | C4: Justificativa | D4: Custo Total do Mês | E4: Custo Unitário | F4: Mês | G4: Nº de Funcionários/Clientes
D5: =SUMIFS('CUSTOS MENSAIS'!$F:$F,'CUSTOS MENSAIS'!$A:$A,A5,'CUSTOS MENSAIS'!$H:$H,F5) -> 0 | E5: =IFERROR(D5/IF(B5="Clientes",SUMIFS(PARÂMETROS!$B$8:$B$907,PARÂMETROS!$G$8:$G$907,F5),SUMIFS(PARÂMETROS!$C$8:$C$907,PARÂMETROS!$G$8:$G$907,F5)),0) -> 0 | G5: =IF(B5="Clientes",SUMIFS(PARÂMETROS!$B$8:$B$907,PARÂMETROS!$G$8:$G$907,F5),SUMIFS(PARÂMETROS!$C$8:$C$907,PARÂMETROS!$G$8:$G$907,F5)) -> 0
A6: NOC | B6: Clientes | C6: Infraestrutura de rede/NOC escala com o nº de clientes ativos | D6: =SUMIFS('CUSTOS MENSAIS'!$F:$F,'CUSTOS MENSAIS'!$A:$A,A6,'CUSTOS MENSAIS'!$H:$H,F6) -> 48782.853 | E6: =IFERROR(D6/IF(B6="Clientes",SUMIFS(PARÂMETROS!$B$8:$B$907,PARÂMETROS!$G$8:$G$907,F6),SUMIFS(PARÂMETROS!$C$8:$C$907,PARÂMETROS!$G$8:$G$907,F6)),0) -> 0.25497109 | F6: Maio/2026 | G6: =IF(B6="Clientes",SUMIFS(PARÂMETROS!$B$8:$B$907,PARÂMETROS!$G$8:$G$907,F6),SUMIFS(PARÂMETROS!$C$8:$C$907,PARÂMETROS!$G$8:$G$907,F6)) -> 191327
A7: RH | B7: Funcionários | C7: Recursos Humanos atende diretamente aos colaboradores | D7: =SUMIFS('CUSTOS MENSAIS'!$F:$F,'CUSTOS MENSAIS'!$A:$A,A7,'CUSTOS MENSAIS'!$H:$H,F7) -> 30023.398 | E7: =IFERROR(D7/IF(B7="Clientes",SUMIFS(PARÂMETROS!$B$8:$B$907,PARÂMETROS!$G$8:$G$907,F7),SUMIFS(PARÂMETROS!$C$8:$C$907,PARÂMETROS!$G$8:$G$907,F7)),0) -> 28.512248 | F7: Maio/2026 | G7: =IF(B7="Clientes",SUMIFS(PARÂMETROS!$B$8:$B$907,PARÂMETROS!$G$8:$G$907,F7),SUMIFS(PARÂMETROS!$C$8:$C$907,PARÂMETROS!$G$8:$G$907,F7)) -> 1053
A8: DP | B8: Funcionários | C8: Departamento Pessoal atende à folha de colaboradores | D8: =SUMIFS('CUSTOS MENSAIS'!$F:$F,'CUSTOS MENSAIS'!$A:$A,A8,'CUSTOS MENSAIS'!$H:$H,F8) -> 49826.446 | E8: =IFERROR(D8/IF(B8="Clientes",SUMIFS(PARÂMETROS!$B$8:$B$907,PARÂMETROS!$G$8:$G$907,F8),SUMIFS(PARÂMETROS!$C$8:$C$907,PARÂMETROS!$G$8:$G$907,F8)),0) -> 47.318562 | F8: Maio/2026 | G8: =IF(B8="Clientes",SUMIFS(PARÂMETROS!$B$8:$B$907,PARÂMETROS!$G$8:$G$907,F8),SUMIFS(PARÂMETROS!$C$8:$C$907,PARÂMETROS!$G$8:$G$907,F8)) -> 1053
A9: Gestão de Atendimento | B9: Clientes | C9: Atendimento administrativo e presencial de loja escala com o volume de clientes atendidos | D9: =SUMIFS('CUSTOS MENSAIS'!$F:$F,'CUSTOS MENSAIS'!$A:$A,A9,'CUSTOS MENSAIS'!$H:$H,F9) -> 20198.15 | E9: =IFERROR(D9/IF(B9="Clientes",SUMIFS(PARÂMETROS!$B$8:$B$907,PARÂMETROS!$G$8:$G$907,F9),SUMIFS(PARÂMETROS!$C$8:$C$907,PARÂMETROS!$G$8:$G$907,F9)),0) -> 0.10556874 | F9: Maio/2026 | G9: =IF(B9="Clientes",SUMIFS(PARÂMETROS!$B$8:$B$907,PARÂMETROS!$G$8:$G$907,F9),SUMIFS(PARÂMETROS!$C$8:$C$907,PARÂMETROS!$G$8:$G$907,F9)) -> 191327
A10: CAC | B10: Clientes | C10: Central de Atendimento ao Cliente atende diretamente a base de clientes de cada empresa | D10: =SUMIFS('CUSTOS MENSAIS'!$F:$F,'CUSTOS MENSAIS'!$A:$A,A10,'CUSTOS MENSAIS'!$H:$H,F10) -> 16366.893 | E10: =IFERROR(D10/IF(B10="Clientes",SUMIFS(PARÂMETROS!$B$8:$B$907,PARÂMETROS!$G$8:$G$907,F10),SUMIFS(PARÂMETROS!$C$8:$C$907,PARÂMETROS!$G$8:$G$907,F10)),0) -> 0.085544085 | F10: Maio/2026 | G10: =IF(B10="Clientes",SUMIFS(PARÂMETROS!$B$8:$B$907,PARÂMETROS!$G$8:$G$907,F10),SUMIFS(PARÂMETROS!$C$8:$C$907,PARÂMETROS!$G$8:$G$907,F10)) -> 191327
A11: Financeiro | B11: Clientes | C11: Financeiro cuida da gestão financeira e de faturamento da operação | D11: =SUMIFS('CUSTOS MENSAIS'!$F:$F,'CUSTOS MENSAIS'!$A:$A,A11,'CUSTOS MENSAIS'!$H:$H,F11) -> 71467.006 | E11: =IFERROR(D11/IF(B11="Clientes",SUMIFS(PARÂMETROS!$B$8:$B$907,PARÂMETROS!$G$8:$G$907,F11),SUMIFS(PARÂMETROS!$C$8:$C$907,PARÂMETROS!$G$8:$G$907,F11)),0) -> 0.3735333 | F11: Maio/2026 | G11: =IF(B11="Clientes",SUMIFS(PARÂMETROS!$B$8:$B$907,PARÂMETROS!$G$8:$G$907,F11),SUMIFS(PARÂMETROS!$C$8:$C$907,PARÂMETROS!$G$8:$G$907,F11)) -> 191327
A12: NRC | B12: Clientes | C12: Serviço de Atendimento ao Cliente escala com o volume de clientes atendidos | D12: =SUMIFS('CUSTOS MENSAIS'!$F:$F,'CUSTOS MENSAIS'!$A:$A,A12,'CUSTOS MENSAIS'!$H:$H,F12) -> 153380.8 | E12: =IFERROR(D12/IF(B12="Clientes",SUMIFS(PARÂMETROS!$B$8:$B$907,PARÂMETROS!$G$8:$G$907,F12),SUMIFS(PARÂMETROS!$C$8:$C$907,PARÂMETROS!$G$8:$G$907,F12)),0) -> 0.80166833 | F12: Maio/2026 | G12: =IF(B12="Clientes",SUMIFS(PARÂMETROS!$B$8:$B$907,PARÂMETROS!$G$8:$G$907,F12),SUMIFS(PARÂMETROS!$C$8:$C$907,PARÂMETROS!$G$8:$G$907,F12)) -> 191327
A13: Cobrança | B13: Clientes | C13: Cobrança atua sobre a carteira de clientes inadimplentes de cada empresa | D13: =SUMIFS('CUSTOS MENSAIS'!$F:$F,'CUSTOS MENSAIS'!$A:$A,A13,'CUSTOS MENSAIS'!$H:$H,F13) -> 43385.322 | E13: =IFERROR(D13/IF(B13="Clientes",SUMIFS(PARÂMETROS!$B$8:$B$907,PARÂMETROS!$G$8:$G$907,F13),SUMIFS(PARÂMETROS!$C$8:$C$907,PARÂMETROS!$G$8:$G$907,F13)),0) -> 0.22676006 | F13: Maio/2026 | G13: =IF(B13="Clientes",SUMIFS(PARÂMETROS!$B$8:$B$907,PARÂMETROS!$G$8:$G$907,F13),SUMIFS(PARÂMETROS!$C$8:$C$907,PARÂMETROS!$G$8:$G$907,F13)) -> 191327
A14: Retenção | B14: Clientes | C14: Retenção atua sobre a base de clientes de cada empresa para evitar cancelamento | D14: =SUMIFS('CUSTOS MENSAIS'!$F:$F,'CUSTOS MENSAIS'!$A:$A,A14,'CUSTOS MENSAIS'!$H:$H,F14) -> 37959.883 | E14: =IFERROR(D14/IF(B14="Clientes",SUMIFS(PARÂMETROS!$B$8:$B$907,PARÂMETROS!$G$8:$G$907,F14),SUMIFS(PARÂMETROS!$C$8:$C$907,PARÂMETROS!$G$8:$G$907,F14)),0) -> 0.19840317 | F14: Maio/2026 | G14: =IF(B14="Clientes",SUMIFS(PARÂMETROS!$B$8:$B$907,PARÂMETROS!$G$8:$G$907,F14),SUMIFS(PARÂMETROS!$C$8:$C$907,PARÂMETROS!$G$8:$G$907,F14)) -> 191327
A15: Contabilidade | B15: Clientes | C15: Contabilidade realiza a escrituração fiscal e contábil da operação | D15: =SUMIFS('CUSTOS MENSAIS'!$F:$F,'CUSTOS MENSAIS'!$A:$A,A15,'CUSTOS MENSAIS'!$H:$H,F15) -> 27353.28 | E15: =IFERROR(D15/IF(B15="Clientes",SUMIFS(PARÂMETROS!$B$8:$B$907,PARÂMETROS!$G$8:$G$907,F15),SUMIFS(PARÂMETROS!$C$8:$C$907,PARÂMETROS!$G$8:$G$907,F15)),0) -> 0.14296612 | F15: Maio/2026 | G15: =IF(B15="Clientes",SUMIFS(PARÂMETROS!$B$8:$B$907,PARÂMETROS!$G$8:$G$907,F15),SUMIFS(PARÂMETROS!$C$8:$C$907,PARÂMETROS!$G$8:$G$907,F15)) -> 191327
A16: Controladoria | B16: Clientes | C16: Controladoria acompanha os indicadores financeiros da operação | D16: =SUMIFS('CUSTOS MENSAIS'!$F:$F,'CUSTOS MENSAIS'!$A:$A,A16,'CUSTOS MENSAIS'!$H:$H,F16) -> 18180.292 | E16: =IFERROR(D16/IF(B16="Clientes",SUMIFS(PARÂMETROS!$B$8:$B$907,PARÂMETROS!$G$8:$G$907,F16),SUMIFS(PARÂMETROS!$C$8:$C$907,PARÂMETROS!$G$8:$G$907,F16)),0) -> 0.095022093 | F16: Maio/2026 | G16: =IF(B16="Clientes",SUMIFS(PARÂMETROS!$B$8:$B$907,PARÂMETROS!$G$8:$G$907,F16),SUMIFS(PARÂMETROS!$C$8:$C$907,PARÂMETROS!$G$8:$G$907,F16)) -> 191327
A17: Diretoria Operacional | B17: Clientes | C17: Diretoria Operacional coordena a operação das áreas técnicas e de atendimento | D17: =SUMIFS('CUSTOS MENSAIS'!$F:$F,'CUSTOS MENSAIS'!$A:$A,A17,'CUSTOS MENSAIS'!$H:$H,F17) -> 27798.627 | E17: =IFERROR(D17/IF(B17="Clientes",SUMIFS(PARÂMETROS!$B$8:$B$907,PARÂMETROS!$G$8:$G$907,F17),SUMIFS(PARÂMETROS!$C$8:$C$907,PARÂMETROS!$G$8:$G$907,F17)),0) -> 0.1452938 | F17: Maio/2026 | G17: =IF(B17="Clientes",SUMIFS(PARÂMETROS!$B$8:$B$907,PARÂMETROS!$G$8:$G$907,F17),SUMIFS(PARÂMETROS!$C$8:$C$907,PARÂMETROS!$G$8:$G$907,F17)) -> 191327
... A39: Diretoria Adm | B39: Clientes | C39: Diretoria Administrativa realiza a gestão administrativa executiva da operação | D39: =SUMIFS('CUSTOS MENSAIS'!$F:$F,'CUSTOS MENSAIS'!$A:$A,A39,'CUSTOS MENSAIS'!$H:$H,F39) -> 29568.366 | E39: =IFERROR(D39/IF(B39="Clientes",SUMIFS(PARÂMETROS!$B$8:$B$907,PARÂMETROS!$G$8:$G$907,F39),SUMIFS(PARÂMETROS!$C$8:$C$907,PARÂMETROS!$G$8:$G$907,F39)),0) -> 0.15454361 | F39: Maio/2026 | G39: =IF(B39="Clientes",SUMIFS(PARÂMETROS!$B$8:$B$907,PARÂMETROS!$G$8:$G$907,F39),SUMIFS(PARÂMETROS!$C$8:$C$907,PARÂMETROS!$G$8:$G$907,F39)) -> 191327
A40: Cozinha | B40: Funcionários | C40: Cozinha prepara as refeições dos colaboradores | D40: =SUMIFS('CUSTOS MENSAIS'!$F:$F,'CUSTOS MENSAIS'!$A:$A,A40,'CUSTOS MENSAIS'!$H:$H,F40) -> 28357.989 | E40: =IFERROR(D40/G40,0) -> 33.36234 | F40: Maio/2026 | G40: =SUMIFS(PARÂMETROS!$C$8:$C$907,PARÂMETROS!$G$8:$G$907,F40,PARÂMETROS!$A$8:$A$907,"DTEL (uso próprio)") -> 850
A41: TOTAL GERAL — Maio/2026 | D41: =SUM(D5:D40)+D114+D117+D120+D123 -> 2151966.9
A42: NOC | B42: Clientes | C42: Infraestrutura de rede/NOC escala com o nº de clientes ativos | D42: =SUMIFS('CUSTOS MENSAIS'!$F:$F,'CUSTOS MENSAIS'!$A:$A,A42,'CUSTOS MENSAIS'!$H:$H,F42) -> 69943.851 | E42: =IFERROR(D42/IF(B42="Clientes",SUMIFS(PARÂMETROS!$B$8:$B$907,PARÂMETROS!$G$8:$G$907,F42),SUMIFS(PARÂMETROS!$C$8:$C$907,PARÂMETROS!$G$8:$G$907,F42)),0) -> 0.35897544 | F42: Junho/2026 | G42: =IF(B42="Clientes",SUMIFS(PARÂMETROS!$B$8:$B$907,PARÂMETROS!$G$8:$G$907,F42),SUMIFS(PARÂMETROS!$C$8:$C$907,PARÂMETROS!$G$8:$G$907,F42)) -> 194843
A43: RH | B43: Funcionários | C43: Recursos Humanos atende diretamente aos colaboradores | D43: =SUMIFS('CUSTOS MENSAIS'!$F:$F,'CUSTOS MENSAIS'!$A:$A,A43,'CUSTOS MENSAIS'!$H:$H,F43) -> 36047.874 | E43: =IFERROR(D43/IF(B43="Clientes",SUMIFS(PARÂMETROS!$B$8:$B$907,PARÂMETROS!$G$8:$G$907,F43),SUMIFS(PARÂMETROS!$C$8:$C$907,PARÂMETROS!$G$8:$G$907,F43)),0) -> 34.364037 | F43: Junho/2026 | G43: =IF(B43="Clientes",SUMIFS(PARÂMETROS!$B$8:$B$907,PARÂMETROS!$G$8:$G$907,F43),SUMIFS(PARÂMETROS!$C$8:$C$907,PARÂMETROS!$G$8:$G$907,F43)) -> 1049
A44: DP | B44: Funcionários | C44: Departamento Pessoal atende à folha de colaboradores | D44: =SUMIFS('CUSTOS MENSAIS'!$F:$F,'CUSTOS MENSAIS'!$A:$A,A44,'CUSTOS MENSAIS'!$H:$H,F44) -> 54615.876 | E44: =IFERROR(D44/IF(B44="Clientes",SUMIFS(PARÂMETROS!$B$8:$B$907,PARÂMETROS!$G$8:$G$907,F44),SUMIFS(PARÂMETROS!$C$8:$C$907,PARÂMETROS!$G$8:$G$907,F44)),0) -> 52.064705 | F44: Junho/2026 | G44: =IF(B44="Clientes",SUMIFS(PARÂMETROS!$B$8:$B$907,PARÂMETROS!$G$8:$G$907,F44),SUMIFS(PARÂMETROS!$C$8:$C$907,PARÂMETROS!$G$8:$G$907,F44)) -> 1049
A45: Gestão de Atendimento | B45: Clientes | C45: Atendimento administrativo e presencial de loja escala com o volume de clientes atendidos | D45: =SUMIFS('CUSTOS MENSAIS'!$F:$F,'CUSTOS MENSAIS'!$A:$A,A45,'CUSTOS MENSAIS'!$H:$H,F45) -> 23728.993 | E45: =IFERROR(D45/IF(B45="Clientes",SUMIFS(PARÂMETROS!$B$8:$B$907,PARÂMETROS!$G$8:$G$907,F45),SUMIFS(PARÂMETROS!$C$8:$C$907,PARÂMETROS!$G$8:$G$907,F45)),0) -> 0.1217852 | F45: Junho/2026 | G45: =IF(B45="Clientes",SUMIFS(PARÂMETROS!$B$8:$B$907,PARÂMETROS!$G$8:$G$907,F45),SUMIFS(PARÂMETROS!$C$8:$C$907,PARÂMETROS!$G$8:$G$907,F45)) -> 194843
A46: CAC | B46: Clientes | C46: Central de Atendimento ao Cliente atende diretamente a base de clientes de cada empresa | D46: =SUMIFS('CUSTOS MENSAIS'!$F:$F,'CUSTOS MENSAIS'!$A:$A,A46,'CUSTOS MENSAIS'!$H:$H,F46) -> 17219.469 | E46: =IFERROR(D46/IF(B46="Clientes",SUMIFS(PARÂMETROS!$B$8:$B$907,PARÂMETROS!$G$8:$G$907,F46),SUMIFS(PARÂMETROS!$C$8:$C$907,PARÂMETROS!$G$8:$G$907,F46)),0) -> 0.088376123 | F46: Junho/2026 | G46: =IF(B46="Clientes",SUMIFS(PARÂMETROS!$B$8:$B$907,PARÂMETROS!$G$8:$G$907,F46),SUMIFS(PARÂMETROS!$C$8:$C$907,PARÂMETROS!$G$8:$G$907,F46)) -> 194843
A47: Financeiro | B47: Clientes | C47: Financeiro cuida da gestão financeira e de faturamento da operação | D47: =SUMIFS('CUSTOS MENSAIS'!$F:$F,'CUSTOS MENSAIS'!$A:$A,A47,'CUSTOS MENSAIS'!$H:$H,F47) -> 70630.626 | E47: =IFERROR(D47/IF(B47="Clientes",SUMIFS(PARÂMETROS!$B$8:$B$907,PARÂMETROS!$G$8:$G$907,F47),SUMIFS(PARÂMETROS!$C$8:$C$907,PARÂMETROS!$G$8:$G$907,F47)),0) -> 0.3625002 | F47: Junho/2026 | G47: =IF(B47="Clientes",SUMIFS(PARÂMETROS!$B$8:$B$907,PARÂMETROS!$G$8:$G$907,F47),SUMIFS(PARÂMETROS!$C$8:$C$907,PARÂMETROS!$G$8:$G$907,F47)) -> 194843
A48: NRC | B48: Clientes | C48: Serviço de Atendimento ao Cliente escala com o volume de clientes atendidos | D48: =SUMIFS('CUSTOS MENSAIS'!$F:$F,'CUSTOS MENSAIS'!$A:$A,A48,'CUSTOS MENSAIS'!$H:$H,F48) -> 173281.41 | E48: =IFERROR(D48/IF(B48="Clientes",SUMIFS(PARÂMETROS!$B$8:$B$907,PARÂMETROS!$G$8:$G$907,F48),SUMIFS(PARÂMETROS!$C$8:$C$907,PARÂMETROS!$G$8:$G$907,F48)),0) -> 0.88933867 | F48: Junho/2026 | G48: =IF(B48="Clientes",SUMIFS(PARÂMETROS!$B$8:$B$907,PARÂMETROS!$G$8:$G$907,F48),SUMIFS(PARÂMETROS!$C$8:$C$907,PARÂMETROS!$G$8:$G$907,F48)) -> 194843
A49: Cobrança | B49: Clientes | C49: Cobrança atua sobre a carteira de clientes inadimplentes de cada empresa | D49: =SUMIFS('CUSTOS MENSAIS'!$F:$F,'CUSTOS MENSAIS'!$A:$A,A49,'CUSTOS MENSAIS'!$H:$H,F49) -> 42678.536 | E49: =IFERROR(D49/IF(B49="Clientes",SUMIFS(PARÂMETROS!$B$8:$B$907,PARÂMETROS!$G$8:$G$907,F49),SUMIFS(PARÂMETROS!$C$8:$C$907,PARÂMETROS!$G$8:$G$907,F49)),0) -> 0.21904064 | F49: Junho/2026 | G49: =IF(B49="Clientes",SUMIFS(PARÂMETROS!$B$8:$B$907,PARÂMETROS!$G$8:$G$907,F49),SUMIFS(PARÂMETROS!$C$8:$C$907,PARÂMETROS!$G$8:$G$907,F49)) -> 194843
A50: Retenção | B50: Clientes | C50: Retenção atua sobre a base de clientes de cada empresa para evitar cancelamento | D50: =SUMIFS('CUSTOS MENSAIS'!$F:$F,'CUSTOS MENSAIS'!$A:$A,A50,'CUSTOS MENSAIS'!$H:$H,F50) -> 51023.149 | E50: =IFERROR(D50/IF(B50="Clientes",SUMIFS(PARÂMETROS!$B$8:$B$907,PARÂMETROS!$G$8:$G$907,F50),SUMIFS(PARÂMETROS!$C$8:$C$907,PARÂMETROS!$G$8:$G$907,F50)),0) -> 0.26186801 | F50: Junho/2026 | G50: =IF(B50="Clientes",SUMIFS(PARÂMETROS!$B$8:$B$907,PARÂMETROS!$G$8:$G$907,F50),SUMIFS(PARÂMETROS!$C$8:$C$907,PARÂMETROS!$G$8:$G$907,F50)) -> 194843
A51: Contabilidade | B51: Clientes | C51: Contabilidade realiza a escrituração fiscal e contábil da operação | D51: =SUMIFS('CUSTOS MENSAIS'!$F:$F,'CUSTOS MENSAIS'!$A:$A,A51,'CUSTOS MENSAIS'!$H:$H,F51) -> 38110.164 | E51: =IFERROR(D51/IF(B51="Clientes",SUMIFS(PARÂMETROS!$B$8:$B$907,PARÂMETROS!$G$8:$G$907,F51),SUMIFS(PARÂMETROS!$C$8:$C$907,PARÂMETROS!$G$8:$G$907,F51)),0) -> 0.19559422 | F51: Junho/2026 | G51: =IF(B51="Clientes",SUMIFS(PARÂMETROS!$B$8:$B$907,PARÂMETROS!$G$8:$G$907,F51),SUMIFS(PARÂMETROS!$C$8:$C$907,PARÂMETROS!$G$8:$G$907,F51)) -> 194843
A52: Controladoria | B52: Clientes | C52: Controladoria acompanha os indicadores financeiros da operação | D52: =SUMIFS('CUSTOS MENSAIS'!$F:$F,'CUSTOS MENSAIS'!$A:$A,A52,'CUSTOS MENSAIS'!$H:$H,F52) -> 18198.009 | E52: =IFERROR(D52/IF(B52="Clientes",SUMIFS(PARÂMETROS!$B$8:$B$907,PARÂMETROS!$G$8:$G$907,F52),SUMIFS(PARÂMETROS!$C$8:$C$907,PARÂMETROS!$G$8:$G$907,F52)),0) -> 0.093398318 | F52: Junho/2026 | G52: =IF(B52="Clientes",SUMIFS(PARÂMETROS!$B$8:$B$907,PARÂMETROS!$G$8:$G$907,F52),SUMIFS(PARÂMETROS!$C$8:$C$907,PARÂMETROS!$G$8:$G$907,F52)) -> 194843
A53: Diretoria Operacional | B53: Clientes | C53: Diretoria Operacional coordena a operação das áreas técnicas e de atendimento | D53: =SUMIFS('CUSTOS MENSAIS'!$F:$F,'CUSTOS MENSAIS'!$A:$A,A53,'CUSTOS MENSAIS'!$H:$H,F53) -> 28599.528 | E53: =IFERROR(D53/IF(B53="Clientes",SUMIFS(PARÂMETROS!$B$8:$B$907,PARÂMETROS!$G$8:$G$907,F53),SUMIFS(PARÂMETROS!$C$8:$C$907,PARÂMETROS!$G$8:$G$907,F53)),0) -> 0.14678242 | F53: Junho/2026 | G53: =IF(B53="Clientes",SUMIFS(PARÂMETROS!$B$8:$B$907,PARÂMETROS!$G$8:$G$907,F53),SUMIFS(PARÂMETROS!$C$8:$C$907,PARÂMETROS!$G$8:$G$907,F53)) -> 194843
... A64: Suporte da Central | B64: Clientes | C64: Suporte da Central dá suporte técnico à central de atendimento | D64: =SUMIFS('CUSTOS MENSAIS'!$F:$F,'CUSTOS MENSAIS'!$A:$A,A64,'CUSTOS MENSAIS'!$H:$H,F64) -> 126953.68 | E64: =IFERROR(D64/IF(B64="Clientes",SUMIFS(PARÂMETROS!$B$8:$B$907,PARÂMETROS!$G$8:$G$907,F64),SUMIFS(PARÂMETROS!$C$8:$C$907,PARÂMETROS!$G$8:$G$907,F64)),0) -> 0.65156913 | F64: Junho/2026 | G64: =IF(B64="Clientes",SUMIFS(PARÂMETROS!$B$8:$B$907,PARÂMETROS!$G$8:$G$907,F64),SUMIFS(PARÂMETROS!$C$8:$C$907,PARÂMETROS!$G$8:$G$907,F64)) -> 194843
A65: Comercial Corporativo | B65: Vendas | C65: Comercial Corporativo realiza vendas para clientes corporativos | D65: =SUMIFS('CUSTOS MENSAIS'!$F:$F,'CUSTOS MENSAIS'!$A:$A,A65,'CUSTOS MENSAIS'!$H:$H,F65) -> 143669.77 | E65: =IFERROR(D65/G65,0) -> 997.70672 | F65: Junho/2026 | G65: 144
A66: Administrativo | B66: Funcionários | C66: Administrativo reúne os softwares e sistemas corporativos usados pela operação | D66: =SUMIFS('CUSTOS MENSAIS'!$F:$F,'CUSTOS MENSAIS'!$A:$A,A66,'CUSTOS MENSAIS'!$H:$H,F66) -> 23776.15 | E66: =IFERROR(D66/IF(B66="Clientes",SUMIFS(PARÂMETROS!$B$8:$B$907,PARÂMETROS!$G$8:$G$907,F66),SUMIFS(PARÂMETROS!$C$8:$C$907,PARÂMETROS!$G$8:$G$907,F66)),0) -> 22.665539 | F66: Junho/2026 | G66: =IF(B66="Clientes",SUMIFS(PARÂMETROS!$B$8:$B$907,PARÂMETROS!$G$8:$G$907,F66),SUMIFS(PARÂMETROS!$C$8:$C$907,PARÂMETROS!$G$8:$G$907,F66)) -> 1049
A67: Qualidade | B67: Clientes | C67: Área de Qualidade garante o padrão de atendimento e dos serviços prestados aos clientes | D67: =SUMIFS('CUSTOS MENSAIS'!$F:$F,'CUSTOS MENSAIS'!$A:$A,A67,'CUSTOS MENSAIS'!$H:$H,F67) -> 35036.851 | E67: =IFERROR(D67/IF(B67="Clientes",SUMIFS(PARÂMETROS!$B$8:$B$907,PARÂMETROS!$G$8:$G$907,F67),SUMIFS(PARÂMETROS!$C$8:$C$907,PARÂMETROS!$G$8:$G$907,F67)),0) -> 0.17982094 | F67: Junho/2026 | G67: =IF(B67="Clientes",SUMIFS(PARÂMETROS!$B$8:$B$907,PARÂMETROS!$G$8:$G$907,F67),SUMIFS(PARÂMETROS!$C$8:$C$907,PARÂMETROS!$G$8:$G$907,F67)) -> 194843
A68: Jurídico | B68: Clientes | C68: Jurídico atua nas demandas legais e contratuais da operação | D68: =SUMIFS('CUSTOS MENSAIS'!$F:$F,'CUSTOS MENSAIS'!$A:$A,A68,'CUSTOS MENSAIS'!$H:$H,F68) -> 15557.95 | E68: =IFERROR(D68/IF(B68="Clientes",SUMIFS(PARÂMETROS!$B$8:$B$907,PARÂMETROS!$G$8:$G$907,F68),SUMIFS(PARÂMETROS!$C$8:$C$907,PARÂMETROS!$G$8:$G$907,F68)),0) -> 0.079848647 | F68: Junho/2026 | G68: =IF(B68="Clientes",SUMIFS(PARÂMETROS!$B$8:$B$907,PARÂMETROS!$G$8:$G$907,F68),SUMIFS(PARÂMETROS!$C$8:$C$907,PARÂMETROS!$G$8:$G$907,F68)) -> 194843
A69: Marketing | B69: Clientes | C69: Marketing atua na captação, retenção e comunicação com a base de clientes | D69: =SUMIFS('CUSTOS MENSAIS'!$F:$F,'CUSTOS MENSAIS'!$A:$A,A69,'CUSTOS MENSAIS'!$H:$H,F69) -> 57175.147 | E69: =IFERROR(D69/IF(B69="Clientes",SUMIFS(PARÂMETROS!$B$8:$B$907,PARÂMETROS!$G$8:$G$907,F69),SUMIFS(PARÂMETROS!$C$8:$C$907,PARÂMETROS!$G$8:$G$907,F69)),0) -> 0.29344214 | F69: Junho/2026 | G69: =IF(B69="Clientes",SUMIFS(PARÂMETROS!$B$8:$B$907,PARÂMETROS!$G$8:$G$907,F69),SUMIFS(PARÂMETROS!$C$8:$C$907,PARÂMETROS!$G$8:$G$907,F69)) -> 194843
A70: TIC | B70: Clientes | C70: TIC dá suporte de infraestrutura de tecnologia à operação voltada aos clientes | D70: =SUMIFS('CUSTOS MENSAIS'!$F:$F,'CUSTOS MENSAIS'!$A:$A,A70,'CUSTOS MENSAIS'!$H:$H,F70) -> 32275.313 | E70: =IFERROR(D70/IF(B70="Clientes",SUMIFS(PARÂMETROS!$B$8:$B$907,PARÂMETROS!$G$8:$G$907,F70),SUMIFS(PARÂMETROS!$C$8:$C$907,PARÂMETROS!$G$8:$G$907,F70)),0) -> 0.16564779 | F70: Junho/2026 | G70: =IF(B70="Clientes",SUMIFS(PARÂMETROS!$B$8:$B$907,PARÂMETROS!$G$8:$G$907,F70),SUMIFS(PARÂMETROS!$C$8:$C$907,PARÂMETROS!$G$8:$G$907,F70)) -> 194843
A71: COE | B71: Clientes | C71: Centro de Operações Especiais (COE) trata despacho e demandas operacionais ligadas à base de clientes | D71: =SUMIFS('CUSTOS MENSAIS'!$F:$F,'CUSTOS MENSAIS'!$A:$A,A71,'CUSTOS MENSAIS'!$H:$H,F71) -> 94839.632 | E71: =IFERROR(D71/IF(B71="Clientes",SUMIFS(PARÂMETROS!$B$8:$B$907,PARÂMETROS!$G$8:$G$907,F71),SUMIFS(PARÂMETROS!$C$8:$C$907,PARÂMETROS!$G$8:$G$907,F71)),0) -> 0.48674898 | F71: Junho/2026 | G71: =IF(B71="Clientes",SUMIFS(PARÂMETROS!$B$8:$B$907,PARÂMETROS!$G$8:$G$907,F71),SUMIFS(PARÂMETROS!$C$8:$C$907,PARÂMETROS!$G$8:$G$907,F71)) -> 194843
A72: Fique Móvel | B72: Clientes | C72: Fique Móvel é equipe de vendas que atua diretamente na captação de clientes | D72: =SUMIFS('CUSTOS MENSAIS'!$F:$F,'CUSTOS MENSAIS'!$A:$A,A72,'CUSTOS MENSAIS'!$H:$H,F72) -> 13388.393 | E72: =IFERROR(D72/IF(B72="Clientes",SUMIFS(PARÂMETROS!$B$8:$B$907,PARÂMETROS!$G$8:$G$907,F72),SUMIFS(PARÂMETROS!$C$8:$C$907,PARÂMETROS!$G$8:$G$907,F72)),0) -> 0.068713748 | F72: Junho/2026 | G72: =IF(B72="Clientes",SUMIFS(PARÂMETROS!$B$8:$B$907,PARÂMETROS!$G$8:$G$907,F72),SUMIFS(PARÂMETROS!$C$8:$C$907,PARÂMETROS!$G$8:$G$907,F72)) -> 194843
A73: Lançamento | B73: Clientes | C73: Equipe de Lançamento realiza a instalação/lançamento de rede para atender novos clientes | D73: =SUMIFS('CUSTOS MENSAIS'!$F:$F,'CUSTOS MENSAIS'!$A:$A,A73,'CUSTOS MENSAIS'!$H:$H,F73) -> 162834.54 | E73: =IFERROR(D73/IF(B73="Clientes",SUMIFS(PARÂMETROS!$B$8:$B$907,PARÂMETROS!$G$8:$G$907,F73),SUMIFS(PARÂMETROS!$C$8:$C$907,PARÂMETROS!$G$8:$G$907,F73)),0) -> 0.83572179 | F73: Junho/2026 | G73: =IF(B73="Clientes",SUMIFS(PARÂMETROS!$B$8:$B$907,PARÂMETROS!$G$8:$G$907,F73),SUMIFS(PARÂMETROS!$C$8:$C$907,PARÂMETROS!$G$8:$G$907,F73)) -> 194843
A74: Fusão | B74: Clientes | C74: Equipe de Fusão realiza fusão/manutenção de fibra óptica para atender a base de clientes | D74: =SUMIFS('CUSTOS MENSAIS'!$F:$F,'CUSTOS MENSAIS'!$A:$A,A74,'CUSTOS MENSAIS'!$H:$H,F74) -> 106633.77 | E74: =IFERROR(D74/IF(B74="Clientes",SUMIFS(PARÂMETROS!$B$8:$B$907,PARÂMETROS!$G$8:$G$907,F74),SUMIFS(PARÂMETROS!$C$8:$C$907,PARÂMETROS!$G$8:$G$907,F74)),0) -> 0.54728048 | F74: Junho/2026 | G74: =IF(B74="Clientes",SUMIFS(PARÂMETROS!$B$8:$B$907,PARÂMETROS!$G$8:$G$907,F74),SUMIFS(PARÂMETROS!$C$8:$C$907,PARÂMETROS!$G$8:$G$907,F74)) -> 194843
A75: Diretoria Adm | B75: Clientes | C75: Diretoria Administrativa realiza a gestão administrativa executiva da operação | D75: =SUMIFS('CUSTOS MENSAIS'!$F:$F,'CUSTOS MENSAIS'!$A:$A,A75,'CUSTOS MENSAIS'!$H:$H,F75) -> 29374.966 | E75: =IFERROR(D75/IF(B75="Clientes",SUMIFS(PARÂMETROS!$B$8:$B$907,PARÂMETROS!$G$8:$G$907,F75),SUMIFS(PARÂMETROS!$C$8:$C$907,PARÂMETROS!$G$8:$G$907,F75)),0) -> 0.15076223 | F75: Junho/2026 | G75: =IF(B75="Clientes",SUMIFS(PARÂMETROS!$B$8:$B$907,PARÂMETROS!$G$8:$G$907,F75),SUMIFS(PARÂMETROS!$C$8:$C$907,PARÂMETROS!$G$8:$G$907,F75)) -> 194843
A76: Cozinha | B76: Funcionários | C76: Cozinha prepara as refeições dos colaboradores | D76: =SUMIFS('CUSTOS MENSAIS'!$F:$F,'CUSTOS MENSAIS'!$A:$A,A76,'CUSTOS MENSAIS'!$H:$H,F76) -> 47063.981 | E76: =IFERROR(D76/G76,0) -> 55.174655 | F76: Junho/2026 | G76: =SUMIFS(PARÂMETROS!$C$8:$C$907,PARÂMETROS!$G$8:$G$907,F76,PARÂMETROS!$A$8:$A$907,"DTEL (uso próprio)") -> 853
A77: TOTAL GERAL — Junho/2026 | D77: =SUM(D42:D76)+D115+D118+D121+D124 -> 2500089.9
A78: NOC | B78: Clientes | C78: Infraestrutura de rede/NOC escala com o nº de clientes ativos | D78: =SUMIFS('CUSTOS MENSAIS'!$F:$F,'CUSTOS MENSAIS'!$A:$A,A78,'CUSTOS MENSAIS'!$H:$H,F78) -> 74925.256 | E78: =IFERROR(D78/IF(B78="Clientes",SUMIFS(PARÂMETROS!$B$8:$B$907,PARÂMETROS!$G$8:$G$907,F78),SUMIFS(PARÂMETROS!$C$8:$C$907,PARÂMETROS!$G$8:$G$907,F78)),0) -> 0.37185411 | F78: Julho/2026 | G78: =IF(B78="Clientes",SUMIFS(PARÂMETROS!$B$8:$B$907,PARÂMETROS!$G$8:$G$907,F78),SUMIFS(PARÂMETROS!$C$8:$C$907,PARÂMETROS!$G$8:$G$907,F78)) -> 201491
A79: RH | B79: Funcionários | C79: Recursos Humanos atende diretamente aos colaboradores | D79: =SUMIFS('CUSTOS MENSAIS'!$F:$F,'CUSTOS MENSAIS'!$A:$A,A79,'CUSTOS MENSAIS'!$H:$H,F79) -> 38844.826 | E79: =IFERROR(D79/IF(B79="Clientes",SUMIFS(PARÂMETROS!$B$8:$B$907,PARÂMETROS!$G$8:$G$907,F79),SUMIFS(PARÂMETROS!$C$8:$C$907,PARÂMETROS!$G$8:$G$907,F79)),0) -> 35.637455 | F79: Julho/2026 | G79: =IF(B79="Clientes",SUMIFS(PARÂMETROS!$B$8:$B$907,PARÂMETROS!$G$8:$G$907,F79),SUMIFS(PARÂMETROS!$C$8:$C$907,PARÂMETROS!$G$8:$G$907,F79)) -> 1090
A80: DP | B80: Funcionários | C80: Departamento Pessoal atende à folha de colaboradores | D80: =SUMIFS('CUSTOS MENSAIS'!$F:$F,'CUSTOS MENSAIS'!$A:$A,A80,'CUSTOS MENSAIS'!$H:$H,F80) -> 57153.851 | E80: =IFERROR(D80/IF(B80="Clientes",SUMIFS(PARÂMETROS!$B$8:$B$907,PARÂMETROS!$G$8:$G$907,F80),SUMIFS(PARÂMETROS!$C$8:$C$907,PARÂMETROS!$G$8:$G$907,F80)),0) -> 52.434725 | F80: Julho/2026 | G80: =IF(B80="Clientes",SUMIFS(PARÂMETROS!$B$8:$B$907,PARÂMETROS!$G$8:$G$907,F80),SUMIFS(PARÂMETROS!$C$8:$C$907,PARÂMETROS!$G$8:$G$907,F80)) -> 1090
A81: Gestão de Atendimento | B81: Clientes | C81: Atendimento administrativo e presencial de loja escala com o volume de clientes atendidos | D81: =SUMIFS('CUSTOS MENSAIS'!$F:$F,'CUSTOS MENSAIS'!$A:$A,A81,'CUSTOS MENSAIS'!$H:$H,F81) -> 27303.006 | E81: =IFERROR(D81/IF(B81="Clientes",SUMIFS(PARÂMETROS!$B$8:$B$907,PARÂMETROS!$G$8:$G$907,F81),SUMIFS(PARÂMETROS!$C$8:$C$907,PARÂMETROS!$G$8:$G$907,F81)),0) -> 0.13550484 | F81: Julho/2026 | G81: =IF(B81="Clientes",SUMIFS(PARÂMETROS!$B$8:$B$907,PARÂMETROS!$G$8:$G$907,F81),SUMIFS(PARÂMETROS!$C$8:$C$907,PARÂMETROS!$G$8:$G$907,F81)) -> 201491
A82: CAC | B82: Clientes | C82: Central de Atendimento ao Cliente atende diretamente a base de clientes de cada empresa | D82: =SUMIFS('CUSTOS MENSAIS'!$F:$F,'CUSTOS MENSAIS'!$A:$A,A82,'CUSTOS MENSAIS'!$H:$H,F82) -> 11204.922 | E82: =IFERROR(D82/IF(B82="Clientes",SUMIFS(PARÂMETROS!$B$8:$B$907,PARÂMETROS!$G$8:$G$907,F82),SUMIFS(PARÂMETROS!$C$8:$C$907,PARÂMETROS!$G$8:$G$907,F82)),0) -> 0.055610036 | F82: Julho/2026 | G82: =IF(B82="Clientes",SUMIFS(PARÂMETROS!$B$8:$B$907,PARÂMETROS!$G$8:$G$907,F82),SUMIFS(PARÂMETROS!$C$8:$C$907,PARÂMETROS!$G$8:$G$907,F82)) -> 201491
A83: Financeiro | B83: Clientes | C83: Financeiro cuida da gestão financeira e de faturamento da operação | D83: =SUMIFS('CUSTOS MENSAIS'!$F:$F,'CUSTOS MENSAIS'!$A:$A,A83,'CUSTOS MENSAIS'!$H:$H,F83) -> 75309.688 | E83: =IFERROR(D83/IF(B83="Clientes",SUMIFS(PARÂMETROS!$B$8:$B$907,PARÂMETROS!$G$8:$G$907,F83),SUMIFS(PARÂMETROS!$C$8:$C$907,PARÂMETROS!$G$8:$G$907,F83)),0) -> 0.37376205 | F83: Julho/2026 | G83: =IF(B83="Clientes",SUMIFS(PARÂMETROS!$B$8:$B$907,PARÂMETROS!$G$8:$G$907,F83),SUMIFS(PARÂMETROS!$C$8:$C$907,PARÂMETROS!$G$8:$G$907,F83)) -> 201491
A84: NRC | B84: Clientes | C84: Serviço de Atendimento ao Cliente escala com o volume de clientes atendidos | D84: =SUMIFS('CUSTOS MENSAIS'!$F:$F,'CUSTOS MENSAIS'!$A:$A,A84,'CUSTOS MENSAIS'!$H:$H,F84) -> 162494.88 | E84: =IFERROR(D84/IF(B84="Clientes",SUMIFS(PARÂMETROS!$B$8:$B$907,PARÂMETROS!$G$8:$G$907,F84),SUMIFS(PARÂMETROS!$C$8:$C$907,PARÂMETROS!$G$8:$G$907,F84)),0) -> 0.8064622 | F84: Julho/2026 | G84: =IF(B84="Clientes",SUMIFS(PARÂMETROS!$B$8:$B$907,PARÂMETROS!$G$8:$G$907,F84),SUMIFS(PARÂMETROS!$C$8:$C$907,PARÂMETROS!$G$8:$G$907,F84)) -> 201491
A85: Cobrança | B85: Clientes | C85: Cobrança atua sobre a carteira de clientes inadimplentes de cada empresa | D85: =SUMIFS('CUSTOS MENSAIS'!$F:$F,'CUSTOS MENSAIS'!$A:$A,A85,'CUSTOS MENSAIS'!$H:$H,F85) -> 43123.897 | E85: =IFERROR(D85/IF(B85="Clientes",SUMIFS(PARÂMETROS!$B$8:$B$907,PARÂMETROS!$G$8:$G$907,F85),SUMIFS(PARÂMETROS!$C$8:$C$907,PARÂMETROS!$G$8:$G$907,F85)),0) -> 0.21402394 | F85: Julho/2026 | G85: =IF(B85="Clientes",SUMIFS(PARÂMETROS!$B$8:$B$907,PARÂMETROS!$G$8:$G$907,F85),SUMIFS(PARÂMETROS!$C$8:$C$907,PARÂMETROS!$G$8:$G$907,F85)) -> 201491
A86: Retenção | B86: Clientes | C86: Retenção atua sobre a base de clientes de cada empresa para evitar cancelamento | D86: =SUMIFS('CUSTOS MENSAIS'!$F:$F,'CUSTOS MENSAIS'!$A:$A,A86,'CUSTOS MENSAIS'!$H:$H,F86) -> 52493.491 | E86: =IFERROR(D86/IF(B86="Clientes",SUMIFS(PARÂMETROS!$B$8:$B$907,PARÂMETROS!$G$8:$G$907,F86),SUMIFS(PARÂMETROS!$C$8:$C$907,PARÂMETROS!$G$8:$G$907,F86)),0) -> 0.26052524 | F86: Julho/2026 | G86: =IF(B86="Clientes",SUMIFS(PARÂMETROS!$B$8:$B$907,PARÂMETROS!$G$8:$G$907,F86),SUMIFS(PARÂMETROS!$C$8:$C$907,PARÂMETROS!$G$8:$G$907,F86)) -> 201491
A87: Contabilidade | B87: Clientes | C87: Contabilidade realiza a escrituração fiscal e contábil da operação | D87: =SUMIFS('CUSTOS MENSAIS'!$F:$F,'CUSTOS MENSAIS'!$A:$A,A87,'CUSTOS MENSAIS'!$H:$H,F87) -> 36743.588 | E87: =IFERROR(D87/IF(B87="Clientes",SUMIFS(PARÂMETROS!$B$8:$B$907,PARÂMETROS!$G$8:$G$907,F87),SUMIFS(PARÂMETROS!$C$8:$C$907,PARÂMETROS!$G$8:$G$907,F87)),0) -> 0.18235846 | F87: Julho/2026 | G87: =IF(B87="Clientes",SUMIFS(PARÂMETROS!$B$8:$B$907,PARÂMETROS!$G$8:$G$907,F87),SUMIFS(PARÂMETROS!$C$8:$C$907,PARÂMETROS!$G$8:$G$907,F87)) -> 201491
A88: Controladoria | B88: Clientes | C88: Controladoria acompanha os indicadores financeiros da operação | D88: =SUMIFS('CUSTOS MENSAIS'!$F:$F,'CUSTOS MENSAIS'!$A:$A,A88,'CUSTOS MENSAIS'!$H:$H,F88) -> 20096.858 | E88: =IFERROR(D88/IF(B88="Clientes",SUMIFS(PARÂMETROS!$B$8:$B$907,PARÂMETROS!$G$8:$G$907,F88),SUMIFS(PARÂMETROS!$C$8:$C$907,PARÂMETROS!$G$8:$G$907,F88)),0) -> 0.099740721 | F88: Julho/2026 | G88: =IF(B88="Clientes",SUMIFS(PARÂMETROS!$B$8:$B$907,PARÂMETROS!$G$8:$G$907,F88),SUMIFS(PARÂMETROS!$C$8:$C$907,PARÂMETROS!$G$8:$G$907,F88)) -> 201491
A89: Diretoria Operacional | B89: Clientes | C89: Diretoria Operacional coordena a operação das áreas técnicas e de atendimento | D89: =SUMIFS('CUSTOS MENSAIS'!$F:$F,'CUSTOS MENSAIS'!$A:$A,A89,'CUSTOS MENSAIS'!$H:$H,F89) -> 27599.879 | E89: =IFERROR(D89/IF(B89="Clientes",SUMIFS(PARÂMETROS!$B$8:$B$907,PARÂMETROS!$G$8:$G$907,F89),SUMIFS(PARÂMETROS!$C$8:$C$907,PARÂMETROS!$G$8:$G$907,F89)),0) -> 0.13697822 | F89: Julho/2026 | G89: =IF(B89="Clientes",SUMIFS(PARÂMETROS!$B$8:$B$907,PARÂMETROS!$G$8:$G$907,F89),SUMIFS(PARÂMETROS!$C$8:$C$907,PARÂMETROS!$G$8:$G$907,F89)) -> 201491
... A100: Suporte da Central | B100: Clientes | C100: Suporte da Central dá suporte técnico à central de atendimento | D100: =SUMIFS('CUSTOS MENSAIS'!$F:$F,'CUSTOS MENSAIS'!$A:$A,A100,'CUSTOS MENSAIS'!$H:$H,F100) -> 213378.5 | E100: =IFERROR(D100/IF(B100="Clientes",SUMIFS(PARÂMETROS!$B$8:$B$907,PARÂMETROS!$G$8:$G$907,F100),SUMIFS(PARÂMETROS!$C$8:$C$907,PARÂMETROS!$G$8:$G$907,F100)),0) -> 1.0589977 | F100: Julho/2026 | G100: =IF(B100="Clientes",SUMIFS(PARÂMETROS!$B$8:$B$907,PARÂMETROS!$G$8:$G$907,F100),SUMIFS(PARÂMETROS!$C$8:$C$907,PARÂMETROS!$G$8:$G$907,F100)) -> 201491
A101: Comercial Corporativo | B101: Vendas | C101: Comercial Corporativo realiza vendas para clientes corporativos | D101: =SUMIFS('CUSTOS MENSAIS'!$F:$F,'CUSTOS MENSAIS'!$A:$A,A101,'CUSTOS MENSAIS'!$H:$H,F101) -> 125647.89 | E101: =IFERROR(D101/G101,0) -> 1697.9445 | F101: Julho/2026 | G101: 74
A102: Administrativo | B102: Funcionários | C102: Administrativo reúne os softwares e sistemas corporativos usados pela operação | D102: =SUMIFS('CUSTOS MENSAIS'!$F:$F,'CUSTOS MENSAIS'!$A:$A,A102,'CUSTOS MENSAIS'!$H:$H,F102) -> 23776.09 | E102: =IFERROR(D102/IF(B102="Clientes",SUMIFS(PARÂMETROS!$B$8:$B$907,PARÂMETROS!$G$8:$G$907,F102),SUMIFS(PARÂMETROS!$C$8:$C$907,PARÂMETROS!$G$8:$G$907,F102)),0) -> 21.812927 | F102: Julho/2026 | G102: =IF(B102="Clientes",SUMIFS(PARÂMETROS!$B$8:$B$907,PARÂMETROS!$G$8:$G$907,F102),SUMIFS(PARÂMETROS!$C$8:$C$907,PARÂMETROS!$G$8:$G$907,F102)) -> 1090
A103: Qualidade | B103: Clientes | C103: Área de Qualidade garante o padrão de atendimento e dos serviços prestados aos clientes | D103: =SUMIFS('CUSTOS MENSAIS'!$F:$F,'CUSTOS MENSAIS'!$A:$A,A103,'CUSTOS MENSAIS'!$H:$H,F103) -> 29475.713 | E103: =IFERROR(D103/IF(B103="Clientes",SUMIFS(PARÂMETROS!$B$8:$B$907,PARÂMETROS!$G$8:$G$907,F103),SUMIFS(PARÂMETROS!$C$8:$C$907,PARÂMETROS!$G$8:$G$907,F103)),0) -> 0.14628799 | F103: Julho/2026 | G103: =IF(B103="Clientes",SUMIFS(PARÂMETROS!$B$8:$B$907,PARÂMETROS!$G$8:$G$907,F103),SUMIFS(PARÂMETROS!$C$8:$C$907,PARÂMETROS!$G$8:$G$907,F103)) -> 201491
A104: Jurídico | B104: Clientes | C104: Jurídico atua nas demandas legais e contratuais da operação | D104: =SUMIFS('CUSTOS MENSAIS'!$F:$F,'CUSTOS MENSAIS'!$A:$A,A104,'CUSTOS MENSAIS'!$H:$H,F104) -> 15993.41 | E104: =IFERROR(D104/IF(B104="Clientes",SUMIFS(PARÂMETROS!$B$8:$B$907,PARÂMETROS!$G$8:$G$907,F104),SUMIFS(PARÂMETROS!$C$8:$C$907,PARÂMETROS!$G$8:$G$907,F104)),0) -> 0.079375307 | F104: Julho/2026 | G104: =IF(B104="Clientes",SUMIFS(PARÂMETROS!$B$8:$B$907,PARÂMETROS!$G$8:$G$907,F104),SUMIFS(PARÂMETROS!$C$8:$C$907,PARÂMETROS!$G$8:$G$907,F104)) -> 201491
A105: Marketing | B105: Clientes | C105: Marketing atua na captação, retenção e comunicação com a base de clientes | D105: =SUMIFS('CUSTOS MENSAIS'!$F:$F,'CUSTOS MENSAIS'!$A:$A,A105,'CUSTOS MENSAIS'!$H:$H,F105) -> 69876.447 | E105: =IFERROR(D105/IF(B105="Clientes",SUMIFS(PARÂMETROS!$B$8:$B$907,PARÂMETROS!$G$8:$G$907,F105),SUMIFS(PARÂMETROS!$C$8:$C$907,PARÂMETROS!$G$8:$G$907,F105)),0) -> 0.34679686 | F105: Julho/2026 | G105: =IF(B105="Clientes",SUMIFS(PARÂMETROS!$B$8:$B$907,PARÂMETROS!$G$8:$G$907,F105),SUMIFS(PARÂMETROS!$C$8:$C$907,PARÂMETROS!$G$8:$G$907,F105)) -> 201491
A106: TIC | B106: Clientes | C106: TIC dá suporte de infraestrutura de tecnologia à operação voltada aos clientes | D106: =SUMIFS('CUSTOS MENSAIS'!$F:$F,'CUSTOS MENSAIS'!$A:$A,A106,'CUSTOS MENSAIS'!$H:$H,F106) -> 34449.863 | E106: =IFERROR(D106/IF(B106="Clientes",SUMIFS(PARÂMETROS!$B$8:$B$907,PARÂMETROS!$G$8:$G$907,F106),SUMIFS(PARÂMETROS!$C$8:$C$907,PARÂMETROS!$G$8:$G$907,F106)),0) -> 0.1709747 | F106: Julho/2026 | G106: =IF(B106="Clientes",SUMIFS(PARÂMETROS!$B$8:$B$907,PARÂMETROS!$G$8:$G$907,F106),SUMIFS(PARÂMETROS!$C$8:$C$907,PARÂMETROS!$G$8:$G$907,F106)) -> 201491
A107: COE | B107: Clientes | C107: Centro de Operações Especiais (COE) trata despacho e demandas operacionais ligadas à base de clientes | D107: =SUMIFS('CUSTOS MENSAIS'!$F:$F,'CUSTOS MENSAIS'!$A:$A,A107,'CUSTOS MENSAIS'!$H:$H,F107) -> 78661.701 | E107: =IFERROR(D107/IF(B107="Clientes",SUMIFS(PARÂMETROS!$B$8:$B$907,PARÂMETROS!$G$8:$G$907,F107),SUMIFS(PARÂMETROS!$C$8:$C$907,PARÂMETROS!$G$8:$G$907,F107)),0) -> 0.39039809 | F107: Julho/2026 | G107: =IF(B107="Clientes",SUMIFS(PARÂMETROS!$B$8:$B$907,PARÂMETROS!$G$8:$G$907,F107),SUMIFS(PARÂMETROS!$C$8:$C$907,PARÂMETROS!$G$8:$G$907,F107)) -> 201491
A108: Fique Móvel | B108: Clientes | C108: Fique Móvel é equipe de vendas que atua diretamente na captação de clientes | D108: =SUMIFS('CUSTOS MENSAIS'!$F:$F,'CUSTOS MENSAIS'!$A:$A,A108,'CUSTOS MENSAIS'!$H:$H,F108) -> 14339.651 | E108: =IFERROR(D108/IF(B108="Clientes",SUMIFS(PARÂMETROS!$B$8:$B$907,PARÂMETROS!$G$8:$G$907,F108),SUMIFS(PARÂMETROS!$C$8:$C$907,PARÂMETROS!$G$8:$G$907,F108)),0) -> 0.071167701 | F108: Julho/2026 | G108: =IF(B108="Clientes",SUMIFS(PARÂMETROS!$B$8:$B$907,PARÂMETROS!$G$8:$G$907,F108),SUMIFS(PARÂMETROS!$C$8:$C$907,PARÂMETROS!$G$8:$G$907,F108)) -> 201491
A109: Lançamento | B109: Clientes | C109: Equipe de Lançamento realiza a instalação/lançamento de rede para atender novos clientes | D109: =SUMIFS('CUSTOS MENSAIS'!$F:$F,'CUSTOS MENSAIS'!$A:$A,A109,'CUSTOS MENSAIS'!$H:$H,F109) -> 180159.93 | E109: =IFERROR(D109/IF(B109="Clientes",SUMIFS(PARÂMETROS!$B$8:$B$907,PARÂMETROS!$G$8:$G$907,F109),SUMIFS(PARÂMETROS!$C$8:$C$907,PARÂMETROS!$G$8:$G$907,F109)),0) -> 0.89413388 | F109: Julho/2026 | G109: =IF(B109="Clientes",SUMIFS(PARÂMETROS!$B$8:$B$907,PARÂMETROS!$G$8:$G$907,F109),SUMIFS(PARÂMETROS!$C$8:$C$907,PARÂMETROS!$G$8:$G$907,F109)) -> 201491
A110: Fusão | B110: Clientes | C110: Equipe de Fusão realiza fusão/manutenção de fibra óptica para atender a base de clientes | D110: =SUMIFS('CUSTOS MENSAIS'!$F:$F,'CUSTOS MENSAIS'!$A:$A,A110,'CUSTOS MENSAIS'!$H:$H,F110) -> 75864.53 | E110: =IFERROR(D110/IF(B110="Clientes",SUMIFS(PARÂMETROS!$B$8:$B$907,PARÂMETROS!$G$8:$G$907,F110),SUMIFS(PARÂMETROS!$C$8:$C$907,PARÂMETROS!$G$8:$G$907,F110)),0) -> 0.37651573 | F110: Julho/2026 | G110: =IF(B110="Clientes",SUMIFS(PARÂMETROS!$B$8:$B$907,PARÂMETROS!$G$8:$G$907,F110),SUMIFS(PARÂMETROS!$C$8:$C$907,PARÂMETROS!$G$8:$G$907,F110)) -> 201491
A111: Diretoria Adm | B111: Clientes | C111: Diretoria Administrativa realiza a gestão administrativa executiva da operação | D111: =SUMIFS('CUSTOS MENSAIS'!$F:$F,'CUSTOS MENSAIS'!$A:$A,A111,'CUSTOS MENSAIS'!$H:$H,F111) -> 29274.583 | E111: =IFERROR(D111/IF(B111="Clientes",SUMIFS(PARÂMETROS!$B$8:$B$907,PARÂMETROS!$G$8:$G$907,F111),SUMIFS(PARÂMETROS!$C$8:$C$907,PARÂMETROS!$G$8:$G$907,F111)),0) -> 0.14528978 | F111: Julho/2026 | G111: =IF(B111="Clientes",SUMIFS(PARÂMETROS!$B$8:$B$907,PARÂMETROS!$G$8:$G$907,F111),SUMIFS(PARÂMETROS!$C$8:$C$907,PARÂMETROS!$G$8:$G$907,F111)) -> 201491
A112: Cozinha | B112: Funcionários | C112: Cozinha prepara as refeições dos colaboradores | D112: =SUMIFS('CUSTOS MENSAIS'!$F:$F,'CUSTOS MENSAIS'!$A:$A,A112,'CUSTOS MENSAIS'!$H:$H,F112) -> 120488.69 | E112: =IFERROR(D112/G112,0) -> 132.98973 | F112: Julho/2026 | G112: =SUMIFS(PARÂMETROS!$C$8:$C$907,PARÂMETROS!$G$8:$G$907,F112,PARÂMETROS!$A$8:$A$907,"DTEL (uso próprio)") -> 906
A113: TOTAL GERAL — Julho/2026 | D113: =SUM(D78:D112)+D116+D119+D122+D125 -> 2684845.2
A114: Backoffice Comercial Varejo | B114: Clientes | C114: Equipe de backoffice do Comercial Varejo dá suporte administrativo às vendas e atende à base de clientes | D114: =SUMIFS('CUSTOS MENSAIS'!$F:$F,'CUSTOS MENSAIS'!$A:$A,A114,'CUSTOS MENSAIS'!$H:$H,F114) -> 7773.6916 | E114: =IFERROR(D114/IF(B114="Clientes",SUMIFS(PARÂMETROS!$B$8:$B$907,PARÂMETROS!$G$8:$G$907,F114),SUMIFS(PARÂMETROS!$C$8:$C$907,PARÂMETROS!$G$8:$G$907,F114)),0) -> 0.040630395 | F114: Maio/2026 | G114: =IF(B114="Clientes",SUMIFS(PARÂMETROS!$B$8:$B$907,PARÂMETROS!$G$8:$G$907,F114),SUMIFS(PARÂMETROS!$C$8:$C$907,PARÂMETROS!$G$8:$G$907,F114)) -> 191327
A115: Backoffice Comercial Varejo | B115: Clientes | C115: Equipe de backoffice do Comercial Varejo dá suporte administrativo às vendas e atende à base de clientes | D115: =SUMIFS('CUSTOS MENSAIS'!$F:$F,'CUSTOS MENSAIS'!$A:$A,A115,'CUSTOS MENSAIS'!$H:$H,F115) -> 8501.6744 | E115: =IFERROR(D115/IF(B115="Clientes",SUMIFS(PARÂMETROS!$B$8:$B$907,PARÂMETROS!$G$8:$G$907,F115),SUMIFS(PARÂMETROS!$C$8:$C$907,PARÂMETROS!$G$8:$G$907,F115)),0) -> 0.043633461 | F115: Junho/2026 | G115: =IF(B115="Clientes",SUMIFS(PARÂMETROS!$B$8:$B$907,PARÂMETROS!$G$8:$G$907,F115),SUMIFS(PARÂMETROS!$C$8:$C$907,PARÂMETROS!$G$8:$G$907,F115)) -> 194843
A116: Backoffice Comercial Varejo | B116: Clientes | C116: Equipe de backoffice do Comercial Varejo dá suporte administrativo às vendas e atende à base de clientes | D116: =SUMIFS('CUSTOS MENSAIS'!$F:$F,'CUSTOS MENSAIS'!$A:$A,A116,'CUSTOS MENSAIS'!$H:$H,F116) -> 7791.2645 | E116: =IFERROR(D116/IF(B116="Clientes",SUMIFS(PARÂMETROS!$B$8:$B$907,PARÂMETROS!$G$8:$G$907,F116),SUMIFS(PARÂMETROS!$C$8:$C$907,PARÂMETROS!$G$8:$G$907,F116)),0) -> 0.038668052 | F116: Julho/2026 | G116: =IF(B116="Clientes",SUMIFS(PARÂMETROS!$B$8:$B$907,PARÂMETROS!$G$8:$G$907,F116),SUMIFS(PARÂMETROS!$C$8:$C$907,PARÂMETROS!$G$8:$G$907,F116)) -> 201491
A117: Serviços Gerais | B117: Funcionários | C117: Serviços Gerais realiza limpeza e apoio predial para os colaboradores | D117: =SUMIFS('CUSTOS MENSAIS'!$F:$F,'CUSTOS MENSAIS'!$A:$A,A117,'CUSTOS MENSAIS'!$H:$H,F117) -> 15250.17 | E117: =IFERROR(D117/IF(B117="Clientes",SUMIFS(PARÂMETROS!$B$8:$B$907,PARÂMETROS!$G$8:$G$907,F117),SUMIFS(PARÂMETROS!$C$8:$C$907,PARÂMETROS!$G$8:$G$907,F117)),0) -> 14.482593 | F117: Maio/2026 | G117: =IF(B117="Clientes",SUMIFS(PARÂMETROS!$B$8:$B$907,PARÂMETROS!$G$8:$G$907,F117),SUMIFS(PARÂMETROS!$C$8:$C$907,PARÂMETROS!$G$8:$G$907,F117)) -> 1053
A118: Serviços Gerais | B118: Funcionários | C118: Serviços Gerais realiza limpeza e apoio predial para os colaboradores | D118: =SUMIFS('CUSTOS MENSAIS'!$F:$F,'CUSTOS MENSAIS'!$A:$A,A118,'CUSTOS MENSAIS'!$H:$H,F118) -> 24041.25 | E118: =IFERROR(D118/IF(B118="Clientes",SUMIFS(PARÂMETROS!$B$8:$B$907,PARÂMETROS!$G$8:$G$907,F118),SUMIFS(PARÂMETROS!$C$8:$C$907,PARÂMETROS!$G$8:$G$907,F118)),0) -> 22.918255 | F118: Junho/2026 | G118: =IF(B118="Clientes",SUMIFS(PARÂMETROS!$B$8:$B$907,PARÂMETROS!$G$8:$G$907,F118),SUMIFS(PARÂMETROS!$C$8:$C$907,PARÂMETROS!$G$8:$G$907,F118)) -> 1049
A119: Serviços Gerais | B119: Funcionários | C119: Serviços Gerais realiza limpeza e apoio predial para os colaboradores | D119: =SUMIFS('CUSTOS MENSAIS'!$F:$F,'CUSTOS MENSAIS'!$A:$A,A119,'CUSTOS MENSAIS'!$H:$H,F119) -> 25265.37 | E119: =IFERROR(D119/IF(B119="Clientes",SUMIFS(PARÂMETROS!$B$8:$B$907,PARÂMETROS!$G$8:$G$907,F119),SUMIFS(PARÂMETROS!$C$8:$C$907,PARÂMETROS!$G$8:$G$907,F119)),0) -> 23.179239 | F119: Julho/2026 | G119: =IF(B119="Clientes",SUMIFS(PARÂMETROS!$B$8:$B$907,PARÂMETROS!$G$8:$G$907,F119),SUMIFS(PARÂMETROS!$C$8:$C$907,PARÂMETROS!$G$8:$G$907,F119)) -> 1090
A120: Desenvolvimento | B120: Clientes | C120: Desenvolvimento mantém e evolui os sistemas internos que atendem à operação e aos clientes | D120: =SUMIFS('CUSTOS MENSAIS'!$F:$F,'CUSTOS MENSAIS'!$A:$A,A120,'CUSTOS MENSAIS'!$H:$H,F120) -> 18352.58 | E120: =IFERROR(D120/IF(B120="Clientes",SUMIFS(PARÂMETROS!$B$8:$B$907,PARÂMETROS!$G$8:$G$907,F120),SUMIFS(PARÂMETROS!$C$8:$C$907,PARÂMETROS!$G$8:$G$907,F120)),0) -> 0.095922583 | F120: Maio/2026 | G120: =IF(B120="Clientes",SUMIFS(PARÂMETROS!$B$8:$B$907,PARÂMETROS!$G$8:$G$907,F120),SUMIFS(PARÂMETROS!$C$8:$C$907,PARÂMETROS!$G$8:$G$907,F120)) -> 191327
A121: Desenvolvimento | B121: Clientes | C121: Desenvolvimento mantém e evolui os sistemas internos que atendem à operação e aos clientes | D121: =SUMIFS('CUSTOS MENSAIS'!$F:$F,'CUSTOS MENSAIS'!$A:$A,A121,'CUSTOS MENSAIS'!$H:$H,F121) -> 20632.94 | E121: =IFERROR(D121/IF(B121="Clientes",SUMIFS(PARÂMETROS!$B$8:$B$907,PARÂMETROS!$G$8:$G$907,F121),SUMIFS(PARÂMETROS!$C$8:$C$907,PARÂMETROS!$G$8:$G$907,F121)),0) -> 0.10589521 | F121: Junho/2026 | G121: =IF(B121="Clientes",SUMIFS(PARÂMETROS!$B$8:$B$907,PARÂMETROS!$G$8:$G$907,F121),SUMIFS(PARÂMETROS!$C$8:$C$907,PARÂMETROS!$G$8:$G$907,F121)) -> 194843
A122: Desenvolvimento | B122: Clientes | C122: Desenvolvimento mantém e evolui os sistemas internos que atendem à operação e aos clientes | D122: =SUMIFS('CUSTOS MENSAIS'!$F:$F,'CUSTOS MENSAIS'!$A:$A,A122,'CUSTOS MENSAIS'!$H:$H,F122) -> 20362.12 | E122: =IFERROR(D122/IF(B122="Clientes",SUMIFS(PARÂMETROS!$B$8:$B$907,PARÂMETROS!$G$8:$G$907,F122),SUMIFS(PARÂMETROS!$C$8:$C$907,PARÂMETROS!$G$8:$G$907,F122)),0) -> 0.10105722 | F122: Julho/2026 | G122: =IF(B122="Clientes",SUMIFS(PARÂMETROS!$B$8:$B$907,PARÂMETROS!$G$8:$G$907,F122),SUMIFS(PARÂMETROS!$C$8:$C$907,PARÂMETROS!$G$8:$G$907,F122)) -> 201491
A123: Configuração | B123: Clientes | C123: Configuração dá suporte técnico de rede (operadores de redes) e escala com o nº de clientes ativos | D123: =SUMIFS('CUSTOS MENSAIS'!$F:$F,'CUSTOS MENSAIS'!$A:$A,A123,'CUSTOS MENSAIS'!$H:$H,F123) -> 35280.97 | E123: =IFERROR(D123/IF(B123="Clientes",SUMIFS(PARÂMETROS!$B$8:$B$907,PARÂMETROS!$G$8:$G$907,F123),SUMIFS(PARÂMETROS!$C$8:$C$907,PARÂMETROS!$G$8:$G$907,F123)),0) -> 0.18440142 | F123: Maio/2026 | G123: =IF(B123="Clientes",SUMIFS(PARÂMETROS!$B$8:$B$907,PARÂMETROS!$G$8:$G$907,F123),SUMIFS(PARÂMETROS!$C$8:$C$907,PARÂMETROS!$G$8:$G$907,F123)) -> 191327
A124: Configuração | B124: Clientes | C124: Configuração dá suporte técnico de rede (operadores de redes) e escala com o nº de clientes ativos | D124: =SUMIFS('CUSTOS MENSAIS'!$F:$F,'CUSTOS MENSAIS'!$A:$A,A124,'CUSTOS MENSAIS'!$H:$H,F124) -> 45450.81 | E124: =IFERROR(D124/IF(B124="Clientes",SUMIFS(PARÂMETROS!$B$8:$B$907,PARÂMETROS!$G$8:$G$907,F124),SUMIFS(PARÂMETROS!$C$8:$C$907,PARÂMETROS!$G$8:$G$907,F124)),0) -> 0.23326889 | F124: Junho/2026 | G124: =IF(B124="Clientes",SUMIFS(PARÂMETROS!$B$8:$B$907,PARÂMETROS!$G$8:$G$907,F124),SUMIFS(PARÂMETROS!$C$8:$C$907,PARÂMETROS!$G$8:$G$907,F124)) -> 194843
A125: Configuração | B125: Clientes | C125: Configuração dá suporte técnico de rede (operadores de redes) e escala com o nº de clientes ativos | D125: =SUMIFS('CUSTOS MENSAIS'!$F:$F,'CUSTOS MENSAIS'!$A:$A,A125,'CUSTOS MENSAIS'!$H:$H,F125) -> 47038.52 | E125: =IFERROR(D125/IF(B125="Clientes",SUMIFS(PARÂMETROS!$B$8:$B$907,PARÂMETROS!$G$8:$G$907,F125),SUMIFS(PARÂMETROS!$C$8:$C$907,PARÂMETROS!$G$8:$G$907,F125)),0) -> 0.23345221 | F125: Julho/2026 | G125: =IF(B125="Clientes",SUMIFS(PARÂMETROS!$B$8:$B$907,PARÂMETROS!$G$8:$G$907,F125),SUMIFS(PARÂMETROS!$C$8:$C$907,PARÂMETROS!$G$8:$G$907,F125)) -> 201491
... A148: Suporte da Central | B148: Clientes | C148: Suporte da Central dá suporte técnico à central de atendimento | D148: =SUMIFS('CUSTOS MENSAIS'!$F:$F,'CUSTOS MENSAIS'!$A:$A,A148,'CUSTOS MENSAIS'!$H:$H,F148) -> 118279.62 | E148: =IFERROR(D148/IF(B148="Clientes",SUMIFS(PARÂMETROS!$B$8:$B$907,PARÂMETROS!$G$8:$G$907,F148),SUMIFS(PARÂMETROS!$C$8:$C$907,PARÂMETROS!$G$8:$G$907,F148)),0) -> 0.59988649 | F148: Agosto/2026 | G148: =IF(B148="Clientes",SUMIFS(PARÂMETROS!$B$8:$B$907,PARÂMETROS!$G$8:$G$907,F148),SUMIFS(PARÂMETROS!$C$8:$C$907,PARÂMETROS!$G$8:$G$907,F148)) -> 197170
A149: Comercial Corporativo | B149: Vendas | C149: Comercial Corporativo realiza vendas para clientes corporativos | D149: =SUMIFS('CUSTOS MENSAIS'!$F:$F,'CUSTOS MENSAIS'!$A:$A,A149,'CUSTOS MENSAIS'!$H:$H,F149) -> 203018.86 | E149: =IFERROR(D149/G149,0) -> 1215.6818 | F149: Agosto/2026 | G149: 167
A150: Administrativo | B150: Funcionários | C150: Administrativo reúne os softwares e sistemas corporativos usados pela operação | D150: =SUMIFS('CUSTOS MENSAIS'!$F:$F,'CUSTOS MENSAIS'!$A:$A,A150,'CUSTOS MENSAIS'!$H:$H,F150) -> 23340.09 | E150: =IFERROR(D150/IF(B150="Clientes",SUMIFS(PARÂMETROS!$B$8:$B$907,PARÂMETROS!$G$8:$G$907,F150),SUMIFS(PARÂMETROS!$C$8:$C$907,PARÂMETROS!$G$8:$G$907,F150)),0) -> 22.186397 | F150: Agosto/2026 | G150: =IF(B150="Clientes",SUMIFS(PARÂMETROS!$B$8:$B$907,PARÂMETROS!$G$8:$G$907,F150),SUMIFS(PARÂMETROS!$C$8:$C$907,PARÂMETROS!$G$8:$G$907,F150)) -> 1052
A151: Qualidade | B151: Clientes | C151: Área de Qualidade garante o padrão de atendimento e dos serviços prestados aos clientes | D151: =SUMIFS('CUSTOS MENSAIS'!$F:$F,'CUSTOS MENSAIS'!$A:$A,A151,'CUSTOS MENSAIS'!$H:$H,F151) -> 45094.18 | E151: =IFERROR(D151/IF(B151="Clientes",SUMIFS(PARÂMETROS!$B$8:$B$907,PARÂMETROS!$G$8:$G$907,F151),SUMIFS(PARÂMETROS!$C$8:$C$907,PARÂMETROS!$G$8:$G$907,F151)),0) -> 0.22870711 | F151: Agosto/2026 | G151: =IF(B151="Clientes",SUMIFS(PARÂMETROS!$B$8:$B$907,PARÂMETROS!$G$8:$G$907,F151),SUMIFS(PARÂMETROS!$C$8:$C$907,PARÂMETROS!$G$8:$G$907,F151)) -> 197170
A152: Jurídico | B152: Clientes | C152: Jurídico atua nas demandas legais e contratuais da operação | D152: =SUMIFS('CUSTOS MENSAIS'!$F:$F,'CUSTOS MENSAIS'!$A:$A,A152,'CUSTOS MENSAIS'!$H:$H,F152) -> 17214.55 | E152: =IFERROR(D152/IF(B152="Clientes",SUMIFS(PARÂMETROS!$B$8:$B$907,PARÂMETROS!$G$8:$G$907,F152),SUMIFS(PARÂMETROS!$C$8:$C$907,PARÂMETROS!$G$8:$G$907,F152)),0) -> 0.08730816 | F152: Agosto/2026 | G152: =IF(B152="Clientes",SUMIFS(PARÂMETROS!$B$8:$B$907,PARÂMETROS!$G$8:$G$907,F152),SUMIFS(PARÂMETROS!$C$8:$C$907,PARÂMETROS!$G$8:$G$907,F152)) -> 197170
A153: Marketing | B153: Clientes | C153: Marketing atua na captação, retenção e comunicação com a base de clientes | D153: =SUMIFS('CUSTOS MENSAIS'!$F:$F,'CUSTOS MENSAIS'!$A:$A,A153,'CUSTOS MENSAIS'!$H:$H,F153) -> 68487.47 | E153: =IFERROR(D153/IF(B153="Clientes",SUMIFS(PARÂMETROS!$B$8:$B$907,PARÂMETROS!$G$8:$G$907,F153),SUMIFS(PARÂMETROS!$C$8:$C$907,PARÂMETROS!$G$8:$G$907,F153)),0) -> 0.34735239 | F153: Agosto/2026 | G153: =IF(B153="Clientes",SUMIFS(PARÂMETROS!$B$8:$B$907,PARÂMETROS!$G$8:$G$907,F153),SUMIFS(PARÂMETROS!$C$8:$C$907,PARÂMETROS!$G$8:$G$907,F153)) -> 197170
A154: TIC | B154: Clientes | C154: TIC dá suporte de infraestrutura de tecnologia à operação voltada aos clientes | D154: =SUMIFS('CUSTOS MENSAIS'!$F:$F,'CUSTOS MENSAIS'!$A:$A,A154,'CUSTOS MENSAIS'!$H:$H,F154) -> 36841.6 | E154: =IFERROR(D154/IF(B154="Clientes",SUMIFS(PARÂMETROS!$B$8:$B$907,PARÂMETROS!$G$8:$G$907,F154),SUMIFS(PARÂMETROS!$C$8:$C$907,PARÂMETROS!$G$8:$G$907,F154)),0) -> 0.18685196 | F154: Agosto/2026 | G154: =IF(B154="Clientes",SUMIFS(PARÂMETROS!$B$8:$B$907,PARÂMETROS!$G$8:$G$907,F154),SUMIFS(PARÂMETROS!$C$8:$C$907,PARÂMETROS!$G$8:$G$907,F154)) -> 197170
A155: COE | B155: Clientes | C155: Centro de Operações Especiais (COE) trata despacho e demandas operacionais ligadas à base de clientes | D155: =SUMIFS('CUSTOS MENSAIS'!$F:$F,'CUSTOS MENSAIS'!$A:$A,A155,'CUSTOS MENSAIS'!$H:$H,F155) -> 74343.28 | E155: =IFERROR(D155/IF(B155="Clientes",SUMIFS(PARÂMETROS!$B$8:$B$907,PARÂMETROS!$G$8:$G$907,F155),SUMIFS(PARÂMETROS!$C$8:$C$907,PARÂMETROS!$G$8:$G$907,F155)),0) -> 0.37705168 | F155: Agosto/2026 | G155: =IF(B155="Clientes",SUMIFS(PARÂMETROS!$B$8:$B$907,PARÂMETROS!$G$8:$G$907,F155),SUMIFS(PARÂMETROS!$C$8:$C$907,PARÂMETROS!$G$8:$G$907,F155)) -> 197170
A156: Fique Móvel | B156: Clientes | C156: Fique Móvel é equipe de vendas que atua diretamente na captação de clientes | D156: =SUMIFS('CUSTOS MENSAIS'!$F:$F,'CUSTOS MENSAIS'!$A:$A,A156,'CUSTOS MENSAIS'!$H:$H,F156) -> 14975.34 | E156: =IFERROR(D156/IF(B156="Clientes",SUMIFS(PARÂMETROS!$B$8:$B$907,PARÂMETROS!$G$8:$G$907,F156),SUMIFS(PARÂMETROS!$C$8:$C$907,PARÂMETROS!$G$8:$G$907,F156)),0) -> 0.075951412 | F156: Agosto/2026 | G156: =IF(B156="Clientes",SUMIFS(PARÂMETROS!$B$8:$B$907,PARÂMETROS!$G$8:$G$907,F156),SUMIFS(PARÂMETROS!$C$8:$C$907,PARÂMETROS!$G$8:$G$907,F156)) -> 197170
A157: Lançamento | B157: Clientes | C157: Equipe de Lançamento realiza a instalação/lançamento de rede para atender novos clientes | D157: =SUMIFS('CUSTOS MENSAIS'!$F:$F,'CUSTOS MENSAIS'!$A:$A,A157,'CUSTOS MENSAIS'!$H:$H,F157) -> 205883.68 | E157: =IFERROR(D157/IF(B157="Clientes",SUMIFS(PARÂMETROS!$B$8:$B$907,PARÂMETROS!$G$8:$G$907,F157),SUMIFS(PARÂMETROS!$C$8:$C$907,PARÂMETROS!$G$8:$G$907,F157)),0) -> 1.0441937 | F157: Agosto/2026 | G157: =IF(B157="Clientes",SUMIFS(PARÂMETROS!$B$8:$B$907,PARÂMETROS!$G$8:$G$907,F157),SUMIFS(PARÂMETROS!$C$8:$C$907,PARÂMETROS!$G$8:$G$907,F157)) -> 197170
A158: Fusão | B158: Clientes | C158: Equipe de Fusão realiza fusão/manutenção de fibra óptica para atender a base de clientes | D158: =SUMIFS('CUSTOS MENSAIS'!$F:$F,'CUSTOS MENSAIS'!$A:$A,A158,'CUSTOS MENSAIS'!$H:$H,F158) -> 132016.27 | E158: =IFERROR(D158/IF(B158="Clientes",SUMIFS(PARÂMETROS!$B$8:$B$907,PARÂMETROS!$G$8:$G$907,F158),SUMIFS(PARÂMETROS!$C$8:$C$907,PARÂMETROS!$G$8:$G$907,F158)),0) -> 0.66955556 | F158: Agosto/2026 | G158: =IF(B158="Clientes",SUMIFS(PARÂMETROS!$B$8:$B$907,PARÂMETROS!$G$8:$G$907,F158),SUMIFS(PARÂMETROS!$C$8:$C$907,PARÂMETROS!$G$8:$G$907,F158)) -> 197170
A159: Diretoria Adm | B159: Clientes | C159: Diretoria Administrativa realiza a gestão administrativa executiva da operação | D159: =SUMIFS('CUSTOS MENSAIS'!$F:$F,'CUSTOS MENSAIS'!$A:$A,A159,'CUSTOS MENSAIS'!$H:$H,F159) -> 11549.89 | E159: =IFERROR(D159/IF(B159="Clientes",SUMIFS(PARÂMETROS!$B$8:$B$907,PARÂMETROS!$G$8:$G$907,F159),SUMIFS(PARÂMETROS!$C$8:$C$907,PARÂMETROS!$G$8:$G$907,F159)),0) -> 0.058578333 | F159: Agosto/2026 | G159: =IF(B159="Clientes",SUMIFS(PARÂMETROS!$B$8:$B$907,PARÂMETROS!$G$8:$G$907,F159),SUMIFS(PARÂMETROS!$C$8:$C$907,PARÂMETROS!$G$8:$G$907,F159)) -> 197170
A160: Cozinha | B160: Funcionários | C160: Cozinha prepara as refeições dos colaboradores | D160: =SUMIFS('CUSTOS MENSAIS'!$F:$F,'CUSTOS MENSAIS'!$A:$A,A160,'CUSTOS MENSAIS'!$H:$H,F160) -> 25628.29 | E160: =IFERROR(D160/G160,0) -> 29.09 | F160: Agosto/2026 | G160: =SUMIFS(PARÂMETROS!$C$8:$C$907,PARÂMETROS!$G$8:$G$907,F160,PARÂMETROS!$A$8:$A$907,"DTEL (uso próprio)") -> 881
A161: TOTAL GERAL — Agosto/2026 | D161: =SUM(D126:D160)+D162+D163+D164+D165 -> 2601256.7
A162: Backoffice Comercial Varejo | B162: Clientes | C162: Equipe de backoffice do Comercial Varejo dá suporte administrativo às vendas e atende à base de clientes | D162: =SUMIFS('CUSTOS MENSAIS'!$F:$F,'CUSTOS MENSAIS'!$A:$A,A162,'CUSTOS MENSAIS'!$H:$H,F162) -> 8249.27 | E162: =IFERROR(D162/IF(B162="Clientes",SUMIFS(PARÂMETROS!$B$8:$B$907,PARÂMETROS!$G$8:$G$907,F162),SUMIFS(PARÂMETROS!$C$8:$C$907,PARÂMETROS!$G$8:$G$907,F162)),0) -> 0.041838363 | F162: Agosto/2026 | G162: =IF(B162="Clientes",SUMIFS(PARÂMETROS!$B$8:$B$907,PARÂMETROS!$G$8:$G$907,F162),SUMIFS(PARÂMETROS!$C$8:$C$907,PARÂMETROS!$G$8:$G$907,F162)) -> 197170
A163: Serviços Gerais | B163: Funcionários | C163: Serviços Gerais realiza limpeza e apoio predial para os colaboradores | D163: =SUMIFS('CUSTOS MENSAIS'!$F:$F,'CUSTOS MENSAIS'!$A:$A,A163,'CUSTOS MENSAIS'!$H:$H,F163) -> 29139.29 | E163: =IFERROR(D163/IF(B163="Clientes",SUMIFS(PARÂMETROS!$B$8:$B$907,PARÂMETROS!$G$8:$G$907,F163),SUMIFS(PARÂMETROS!$C$8:$C$907,PARÂMETROS!$G$8:$G$907,F163)),0) -> 27.698945 | F163: Agosto/2026 | G163: =IF(B163="Clientes",SUMIFS(PARÂMETROS!$B$8:$B$907,PARÂMETROS!$G$8:$G$907,F163),SUMIFS(PARÂMETROS!$C$8:$C$907,PARÂMETROS!$G$8:$G$907,F163)) -> 1052
A164: Desenvolvimento | B164: Clientes | C164: Desenvolvimento mantém e evolui os sistemas internos que atendem à operação e aos clientes | D164: =SUMIFS('CUSTOS MENSAIS'!$F:$F,'CUSTOS MENSAIS'!$A:$A,A164,'CUSTOS MENSAIS'!$H:$H,F164) -> 24636.91 | E164: =IFERROR(D164/IF(B164="Clientes",SUMIFS(PARÂMETROS!$B$8:$B$907,PARÂMETROS!$G$8:$G$907,F164),SUMIFS(PARÂMETROS!$C$8:$C$907,PARÂMETROS!$G$8:$G$907,F164)),0) -> 0.12495263 | F164: Agosto/2026 | G164: =IF(B164="Clientes",SUMIFS(PARÂMETROS!$B$8:$B$907,PARÂMETROS!$G$8:$G$907,F164),SUMIFS(PARÂMETROS!$C$8:$C$907,PARÂMETROS!$G$8:$G$907,F164)) -> 197170
...

Sheet CUSTOS MENSAIS
A1: CUSTOS MENSAIS — POR SETOR
A2: Preencha Quantidade e Valor Unitário (azul) — o Total do Mês é calculado automaticamente (Quantidade × Valor Unitário). Se só existir um valor total (sem quantidade/preço unitário), use Quantidade = 1 e Valor Unitário = o valor total. Linha 5 é um EXEMPLO — substitua pelos valores reais.
A4: Setor | B4: Categoria | C4: Descrição do Custo | D4: Quantidade | E4: Valor Unitário | F4: Total do Mês | G4: Critério de Rateio | H4: Mês
A5: Administrativo | B5: Custo Fixo | C5: Licença Google Workspace | D5: 1 | E5: 21454 | F5: =IFERROR(D5*E5,0) -> 21454 | G5: =INDEX(SETORES!$B:$B,MATCH(A5,SETORES!$A:$A,0)) -> Funcionários | H5: Agosto/2026
A6: Administrativo | B6: Custo Variável | C6: Rescisões trabalhistas | F6: =IFERROR(D6*E6,0) -> 0 | G6: =INDEX(SETORES!$B:$B,MATCH(A6,SETORES!$A:$A,0)) -> Funcionários | H6: Agosto/2026
A7: Administrativo | B7: Custo Fixo | C7: Sistema de assinatura eletronica (autentique) (TIC) | D7: 1 | E7: 99 | F7: =IFERROR(D7*E7,0) -> 99 | G7: =INDEX(SETORES!$B:$B,MATCH(A7,SETORES!$A:$A,0)) -> Funcionários | H7: Agosto/2026
A8: Administrativo | B8: Custo Fixo | C8: Software de sistema eletronico de alarme (administrativo) | F8: =IFERROR(D8*E8,0) -> 0 | G8: =INDEX(SETORES!$B:$B,MATCH(A8,SETORES!$A:$A,0)) -> Funcionários | H8: Agosto/2026
A9: Administrativo | B9: Custo Fixo | C9: Software Power BI Dynamics (f001796) | D9: 1 | E9: 1787.09 | F9: =IFERROR(D9*E9,0) -> 1787.09 | G9: =INDEX(SETORES!$B:$B,MATCH(A9,SETORES!$A:$A,0)) -> Funcionários | H9: Agosto/2026
A10: Backoffice Comercial Varejo | B10: Custo Fixo | C10: Água e esgoto (rateio) | F10: =IFERROR(D10*E10,0) -> 0 | G10: =INDEX(SETORES!$B:$B,MATCH(A10,SETORES!$A:$A,0)) -> Clientes | H10: Agosto/2026
A11: Backoffice Comercial Varejo | B11: Custo Fixo | C11: Chip móvel corporativo | D11: 1 | E11: 30 | F11: =IFERROR(D11*E11,0) -> 30 | G11: =INDEX(SETORES!$B:$B,MATCH(A11,SETORES!$A:$A,0)) -> Clientes | H11: Agosto/2026
A12: Backoffice Comercial Varejo | B12: Custo Fixo | C12: Custo de gestão administrativa (rateado — Renata Thaysa dos Santos Cunha) | D12: 1 | E12: 582.06 | F12: =IFERROR(D12*E12,0) -> 582.06 | G12: =INDEX(SETORES!$B:$B,MATCH(A12,SETORES!$A:$A,0)) -> Clientes | H12: Agosto/2026
A13: Backoffice Comercial Varejo | B13: Custo Fixo | C13: Despesas com DP | D13: 2 | E13: 52.09 | F13: =IFERROR(D13*E13,0) -> 104.18 | G13: Funcionários | H13: Agosto/2026
A14: Backoffice Comercial Varejo | B14: Custo Fixo | C14: Despesas com RH | D14: 2 | E14: 32.55 | F14: =IFERROR(D14*E14,0) -> 65.1 | G14: Funcionários | H14: Agosto/2026
A15: Backoffice Comercial Varejo | B15: Custo Fixo | C15: Despesas com SST | D15: 2 | E15: 52.35 | F15: =IFERROR(D15*E15,0) -> 104.7 | G15: Funcionários | H15: Agosto/2026
A16: Backoffice Comercial Varejo | B16: Custo Fixo | C16: Energia elétrica (rateio) | F16: =IFERROR(D16*E16,0) -> 0 | G16: =INDEX(SETORES!$B:$B,MATCH(A16,SETORES!$A:$A,0)) -> Clientes | H16: Agosto/2026
A17: Backoffice Comercial Varejo | B17: Custo Fixo | C17: Folha de pagamento (salários) | D17: 1 | E17: 7220.72 | F17: =IFERROR(D17*E17,0) -> 7220.72 | G17: =INDEX(SETORES!$B:$B,MATCH(A17,SETORES!$A:$A,0)) -> Clientes | H17: Agosto/2026
A18: Backoffice Comercial Varejo | B18: Custo Fixo | C18: Gympass | F18: =IFERROR(D18*E18,0) -> 0 | G18: =INDEX(SETORES!$B:$B,MATCH(A18,SETORES!$A:$A,0)) -> Clientes | H18: Agosto/2026
A19: Backoffice Comercial Varejo | B19: Custo Fixo | C19: Instalações - corredores e alojamentos (rateio) | D19: 1 | E19: 38.77 | F19: =IFERROR(D19*E19,0) -> 38.77 | G19: =INDEX(SETORES!$B:$B,MATCH(A19,SETORES!$A:$A,0)) -> Clientes | H19: Agosto/2026
A20: Backoffice Comercial Varejo | B20: Custo Fixo | C20: Licença de e-mail corporativo | D20: 2 | E20: 50 | F20: =IFERROR(D20*E20,0) -> 100 | G20: =INDEX(SETORES!$B:$B,MATCH(A20,SETORES!$A:$A,0)) -> Clientes | H20: Agosto/2026
A21: Backoffice Comercial Varejo | B21: Custo Fixo | C21: Stargrid | D21: 2 | E21: 1.87 | F21: =IFERROR(D21*E21,0) -> 3.74 | G21: =INDEX(SETORES!$B:$B,MATCH(A21,SETORES!$A:$A,0)) -> Clientes | H21: Agosto/2026
A22: CAC | B22: Custo Fixo | C22: Água e esgoto (rateio) | F22: =IFERROR(D22*E22,0) -> 0 | G22: =INDEX(SETORES!$B:$B,MATCH(A22,SETORES!$A:$A,0)) -> Clientes | H22: Agosto/2026
A23: CAC | B23: Custo Fixo | C23: Chip móvel corporativo | D23: 1 | E23: 30 | F23: =IFERROR(D23*E23,0) -> 30 | G23: =INDEX(SETORES!$B:$B,MATCH(A23,SETORES!$A:$A,0)) -> Clientes | H23: Agosto/2026
A24: CAC | B24: Custo Fixo | C24: Custo de gestão administrativa (rateado — Renata Thaysa dos Santos Cunha) | D24: 1 | E24: 1455.14 | F24: =IFERROR(D24*E24,0) -> 1455.14 | G24: =INDEX(SETORES!$B:$B,MATCH(A24,SETORES!$A:$A,0)) -> Clientes | H24: Agosto/2026
A25: CAC | B25: Custo Fixo | C25: Despesas com DP | D25: 5 | E25: 52.09 | F25: =IFERROR(D25*E25,0) -> 260.45 | G25: Funcionários | H25: Agosto/2026
A26: CAC | B26: Custo Fixo | C26: Despesas com RH | D26: 5 | E26: 32.55 | F26: =IFERROR(D26*E26,0) -> 162.75 | G26: Funcionários | H26: Agosto/2026
A27: CAC | B27: Custo Fixo | C27: Despesas com SST | D27: 5 | E27: 52.35 | F27: =IFERROR(D27*E27,0) -> 261.75 | G27: Funcionários | H27: Agosto/2026
A28: CAC | B28: Custo Fixo | C28: Energia elétrica (rateio) | F28: =IFERROR(D28*E28,0) -> 0 | G28: =INDEX(SETORES!$B:$B,MATCH(A28,SETORES!$A:$A,0)) -> Clientes | H28: Agosto/2026
A29: CAC | B29: Custo Variável | C29: Exames médicos | F29: =IFERROR(D29*E29,0) -> 0 | G29: =INDEX(SETORES!$B:$B,MATCH(A29,SETORES!$A:$A,0)) -> Clientes | H29: Agosto/2026
A30: CAC | B30: Custo Variável | C30: Fardamento novo | F30: =IFERROR(D30*E30,0) -> 0 | G30: =INDEX(SETORES!$B:$B,MATCH(A30,SETORES!$A:$A,0)) -> Clientes | H30: Agosto/2026
A31: CAC | B31: Custo Variável | C31: Fardamento substituição | F31: =IFERROR(D31*E31,0) -> 0 | G31: =INDEX(SETORES!$B:$B,MATCH(A31,SETORES!$A:$A,0)) -> Clientes | H31: Agosto/2026
A32: CAC | B32: Custo Fixo | C32: Folha de pagamento (salários) | D32: 1 | E32: 21051.01 | F32: =IFERROR(D32*E32,0) -> 21051.01 | G32: =INDEX(SETORES!$B:$B,MATCH(A32,SETORES!$A:$A,0)) -> Clientes | H32: Agosto/2026
A33: CAC | B33: Custo Fixo | C33: Gympass | F33: =IFERROR(D33*E33,0) -> 0 | G33: =INDEX(SETORES!$B:$B,MATCH(A33,SETORES!$A:$A,0)) -> Clientes | H33: Agosto/2026
A34: CAC | B34: Custo Fixo | C34: Instalações - corredores e alojamentos (rateio) | D34: 1 | E34: 96.93 | F34: =IFERROR(D34*E34,0) -> 96.93 | G34: =INDEX(SETORES!$B:$B,MATCH(A34,SETORES!$A:$A,0)) -> Clientes | H34: Agosto/2026
A35: CAC | B35: Custo Fixo | C35: Licença de e-mail corporativo | D35: 5 | E35: 50 | F35: =IFERROR(D35*E35,0) -> 250 | G35: =INDEX(SETORES!$B:$B,MATCH(A35,SETORES!$A:$A,0)) -> Clientes | H35: Agosto/2026
A36: CAC | B36: Custo Fixo | C36: Material de escritório (suprimentos de informática) | F36: =IFERROR(D36*E36,0) -> 0 | G36: =INDEX(SETORES!$B:$B,MATCH(A36,SETORES!$A:$A,0)) -> Clientes | H36: Agosto/2026
A37: CAC | B37: Custo Fixo | C37: Material de uso coletivo (copa/limpeza) | F37: =IFERROR(D37*E37,0) -> 0 | G37: =INDEX(SETORES!$B:$B,MATCH(A37,SETORES!$A:$A,0)) -> Clientes | H37: Agosto/2026
A38: CAC | B38: Custo Variável | C38: Rescisões trabalhistas | F38: =IFERROR(D38*E38,0) -> 0 | G38: =INDEX(SETORES!$B:$B,MATCH(A38,SETORES!$A:$A,0)) -> Clientes | H38: Agosto/2026
A39: CAC | B39: Custo Fixo | C39: Stargrid | D39: 5 | E39: 1.87 | F39: =IFERROR(D39*E39,0) -> 9.35 | G39: =INDEX(SETORES!$B:$B,MATCH(A39,SETORES!$A:$A,0)) -> Clientes | H39: Agosto/2026
A40: CAC | B40: Custo Fixo | C40: Telefonia móvel corporativa | F40: =IFERROR(D40*E40,0) -> 0 | G40: =INDEX(SETORES!$B:$B,MATCH(A40,SETORES!$A:$A,0)) -> Clientes | H40: Agosto/2026
A41: Cobrança | B41: Custo Fixo | C41: Água e esgoto (rateio) | F41: =IFERROR(D41*E41,0) -> 0 | G41: =INDEX(SETORES!$B:$B,MATCH(A41,SETORES!$A:$A,0)) -> Clientes | H41: Agosto/2026
A42: Cobrança | B42: Custo Fixo | C42: Custo de gestão administrativa (rateado — Ayrton da Silva Lima) | D42: 1 | E42: 1013 | F42: =IFERROR(D42*E42,0) -> 1013 | G42: =INDEX(SETORES!$B:$B,MATCH(A42,SETORES!$A:$A,0)) -> Clientes | H42: Agosto/2026
A43: Cobrança | B43: Custo Fixo | C43: Despesas com DP | D43: 13 | E43: 52.09 | F43: =IFERROR(D43*E43,0) -> 677.17 | G43: Funcionários | H43: Agosto/2026
A44: Cobrança | B44: Custo Fixo | C44: Despesas com RH | D44: 13 | E44: 32.55 | F44: =IFERROR(D44*E44,0) -> 423.15 | G44: Funcionários | H44: Agosto/2026
A45: Cobrança | B45: Custo Fixo | C45: Despesas com SST | D45: 13 | E45: 52.35 | F45: =IFERROR(D45*E45,0) -> 680.55 | G45: Funcionários | H45: Agosto/2026
A46: Cobrança | B46: Custo Fixo | C46: Energia elétrica (rateio) | F46: =IFERROR(D46*E46,0) -> 0 | G46: =INDEX(SETORES!$B:$B,MATCH(A46,SETORES!$A:$A,0)) -> Clientes | H46: Agosto/2026
A47: Cobrança | B47: Custo Variável | C47: Exames médicos | F47: =IFERROR(D47*E47,0) -> 0 | G47: =INDEX(SETORES!$B:$B,MATCH(A47,SETORES!$A:$A,0)) -> Clientes | H47: Agosto/2026
A48: Cobrança | B48: Custo Variável | C48: Fardamento novo | F48: =IFERROR(D48*E48,0) -> 0 | G48: =INDEX(SETORES!$B:$B,MATCH(A48,SETORES!$A:$A,0)) -> Clientes | H48: Agosto/2026
A49: Cobrança | B49: Custo Variável | C49: Fardamento substituição | F49: =IFERROR(D49*E49,0) -> 0 | G49: =INDEX(SETORES!$B:$B,MATCH(A49,SETORES!$A:$A,0)) -> Clientes | H49: Agosto/2026
A50: Cobrança | B50: Custo Fixo | C50: Folha de pagamento (salários) | D50: 1 | E50: 42492.05 | F50: =IFERROR(D50*E50,0) -> 42492.05 | G50: =INDEX(SETORES!$B:$B,MATCH(A50,SETORES!$A:$A,0)) -> Clientes | H50: Agosto/2026
A51: Cobrança | B51: Custo Fixo | C51: Gympass | F51: =IFERROR(D51*E51,0) -> 0 | G51: =INDEX(SETORES!$B:$B,MATCH(A51,SETORES!$A:$A,0)) -> Clientes | H51: Agosto/2026
A52: Cobrança | B52: Custo Fixo | C52: Impressora (rateio equipe Relacionamento) | F52: =IFERROR(D52*E52,0) -> 0 | G52: =INDEX(SETORES!$B:$B,MATCH(A52,SETORES!$A:$A,0)) -> Clientes | H52: Agosto/2026
A53: Cobrança | B53: Custo Fixo | C53: Instalações - corredores e alojamentos (rateio) | D53: 1 | E53: 252.02 | F53: =IFERROR(D53*E53,0) -> 252.02 | G53: =INDEX(SETORES!$B:$B,MATCH(A53,SETORES!$A:$A,0)) -> Clientes | H53: Agosto/2026
A54: Cobrança | B54: Custo Fixo | C54: Licença de e-mail corporativo | D54: 13 | E54: 50 | F54: =IFERROR(D54*E54,0) -> 650 | G54: =INDEX(SETORES!$B:$B,MATCH(A54,SETORES!$A:$A,0)) -> Clientes | H54: Agosto/2026
A55: Cobrança | B55: Custo Fixo | C55: Material de escritório (suprimentos de informática) | D55: 1 | E55: 3.74 | F55: =IFERROR(D55*E55,0) -> 3.74 | G55: =INDEX(SETORES!$B:$B,MATCH(A55,SETORES!$A:$A,0)) -> Clientes | H55: Agosto/2026
A56: Cobrança | B56: Custo Fixo | C56: Material de uso coletivo (copa/limpeza) | D56: 1 | E56: 657.21 | F56: =IFERROR(D56*E56,0) -> 657.21 | G56: =INDEX(SETORES!$B:$B,MATCH(A56,SETORES!$A:$A,0)) -> Clientes | H56: Agosto/2026
A57: Cobrança | B57: Custo Variável | C57: Rescisões trabalhistas | F57: =IFERROR(D57*E57,0) -> 0 | G57: =INDEX(SETORES!$B:$B,MATCH(A57,SETORES!$A:$A,0)) -> Clientes | H57: Agosto/2026
A58: Cobrança | B58: Custo Fixo | C58: Software MATRIX (rateio equipe Relacionamento) | F58: =IFERROR(D58*E58,0) -> 0 | G58: =INDEX(SETORES!$B:$B,MATCH(A58,SETORES!$A:$A,0)) -> Clientes | H58: Agosto/2026
A59: Cobrança | B59: Custo Fixo | C59: Stargrid | D59: 13 | E59: 1.87 | F59: =IFERROR(D59*E59,0) -> 24.31 | G59: =INDEX(SETORES!$B:$B,MATCH(A59,SETORES!$A:$A,0)) -> Clientes | H59: Agosto/2026
A60: Cobrança | B60: Custo Fixo | C60: Telefonia móvel corporativa | F60: =IFERROR(D60*E60,0) -> 0 | G60: =INDEX(SETORES!$B:$B,MATCH(A60,SETORES!$A:$A,0)) -> Clientes | H60: Agosto/2026
A61: COE | B61: Custo Fixo | C61: Água e esgoto (rateio) | F61: =IFERROR(D61*E61,0) -> 0 | G61: =INDEX(SETORES!$B:$B,MATCH(A61,SETORES!$A:$A,0)) -> Clientes | H61: Agosto/2026
A62: COE | B62: Custo Fixo | C62: Chip móvel corporativo | D62: 12 | E62: 30 | F62: =IFERROR(D62*E62,0) -> 360 | G62: =INDEX(SETORES!$B:$B,MATCH(A62,SETORES!$A:$A,0)) -> Clientes | H62: Agosto/2026
A63: COE | B63: Custo Fixo | C63: Despesas com DP | D63: 11 | E63: 52.09 | F63: =IFERROR(D63*E63,0) -> 572.99 | G63: Funcionários | H63: Agosto/2026
A64: COE | B64: Custo Fixo | C64: Despesas com RH | D64: 11 | E64: 32.55 | F64: =IFERROR(D64*E64,0) -> 358.05 | G64: Funcionários | H64: Agosto/2026
A65: COE | B65: Custo Fixo | C65: Despesas com SST | D65: 11 | E65: 52.35 | F65: =IFERROR(D65*E65,0) -> 575.85 | G65: Funcionários | H65: Agosto/2026
A66: COE | B66: Custo Fixo | C66: Energia elétrica (rateio) | F66: =IFERROR(D66*E66,0) -> 0 | G66: =INDEX(SETORES!$B:$B,MATCH(A66,SETORES!$A:$A,0)) -> Clientes | H66: Agosto/2026
A67: COE | B67: Custo Fixo | C67: Folha de pagamento (salários) | D67: 1 | E67: 71692.57 | F67: =IFERROR(D67*E67,0) -> 71692.57 | G67: =INDEX(SETORES!$B:$B,MATCH(A67,SETORES!$A:$A,0)) -> Clientes | H67: Agosto/2026
A68: COE | B68: Custo Fixo | C68: Gympass | F68: =IFERROR(D68*E68,0) -> 0 | G68: =INDEX(SETORES!$B:$B,MATCH(A68,SETORES!$A:$A,0)) -> Clientes | H68: Agosto/2026
A69: COE | B69: Custo Fixo | C69: Impressora | F69: =IFERROR(D69*E69,0) -> 0 | G69: =INDEX(SETORES!$B:$B,MATCH(A69,SETORES!$A:$A,0)) -> Clientes | H69: Agosto/2026
A70: COE | B70: Custo Fixo | C70: Instalações - corredores e alojamentos (rateio) | D70: 1 | E70: 213.25 | F70: =IFERROR(D70*E70,0) -> 213.25 | G70: =INDEX(SETORES!$B:$B,MATCH(A70,SETORES!$A:$A,0)) -> Clientes | H70: Agosto/2026
A71: COE | B71: Custo Fixo | C71: Licença de e-mail corporativo | D71: 11 | E71: 50 | F71: =IFERROR(D71*E71,0) -> 550 | G71: =INDEX(SETORES!$B:$B,MATCH(A71,SETORES!$A:$A,0)) -> Clientes | H71: Agosto/2026
A72: COE | B72: Custo Variável | C72: Rateio de transporte coletivo | F72: =IFERROR(D72*E72,0) -> 0 | G72: =INDEX(SETORES!$B:$B,MATCH(A72,SETORES!$A:$A,0)) -> Clientes | H72: Agosto/2026
A73: COE | B73: Custo Variável | C73: Rescisões trabalhistas | F73: =IFERROR(D73*E73,0) -> 0 | G73: =INDEX(SETORES!$B:$B,MATCH(A73,SETORES!$A:$A,0)) -> Clientes | H73: Agosto/2026
A74: COE | B74: Custo Fixo | C74: Stargrid | D74: 11 | E74: 1.87 | F74: =IFERROR(D74*E74,0) -> 20.57 | G74: =INDEX(SETORES!$B:$B,MATCH(A74,SETORES!$A:$A,0)) -> Clientes | H74: Agosto/2026
A75: Comercial Corporativo | B75: Custo Fixo | C75: Agendor (válido por 3 meses) | D75: 1 | E75: 545.99 | F75: =IFERROR(D75*E75,0) -> 545.99 | G75: =INDEX(SETORES!$B:$B,MATCH(A75,SETORES!$A:$A,0)) -> Clientes | H75: Agosto/2026
A76: Comercial Corporativo | B76: Custo Fixo | C76: Água e esgoto (rateio) | F76: =IFERROR(D76*E76,0) -> 0 | G76: =INDEX(SETORES!$B:$B,MATCH(A76,SETORES!$A:$A,0)) -> Clientes | H76: Agosto/2026
A77: Comercial Corporativo | B77: Custo Variável | C77: Consumo de combustível | D77: 1 | E77: 3995.53 | F77: =IFERROR(D77*E77,0) -> 3995.53 | G77: =INDEX(SETORES!$B:$B,MATCH(A77,SETORES!$A:$A,0)) -> Clientes | H77: Agosto/2026
A78: Comercial Corporativo | B78: Custo Fixo | C78: Datlo | D78: 1 | E78: 2997 | F78: =IFERROR(D78*E78,0) -> 2997 | G78: =INDEX(SETORES!$B:$B,MATCH(A78,SETORES!$A:$A,0)) -> Clientes | H78: Agosto/2026
A79: Comercial Corporativo | B79: Custo Fixo | C79: Despesas com DP | D79: 12 | E79: 52.09 | F79: =IFERROR(D79*E79,0) -> 625.08 | G79: Funcionários | H79: Agosto/2026
A80: Comercial Corporativo | B80: Custo Fixo | C80: Despesas com RH | D80: 12 | E80: 32.55 | F80: =IFERROR(D80*E80,0) -> 390.6 | G80: Funcionários | H80: Agosto/2026
A81: Comercial Corporativo | B81: Custo Fixo | C81: Despesas com SST | D81: 12 | E81: 52.35 | F81: =IFERROR(D81*E81,0) -> 628.2 | G81: Funcionários | H81: Agosto/2026
A82: Comercial Corporativo | B82: Custo Variável | C82: Devolução de fardamento | F82: =IFERROR(D82*E82,0) -> 0 | G82: =INDEX(SETORES!$B:$B,MATCH(A82,SETORES!$A:$A,0)) -> Clientes | H82: Agosto/2026
A83: Comercial Corporativo | B83: Custo Fixo | C83: Dynamics (f001796) | F83: =IFERROR(D83*E83,0) -> 0 | G83: =INDEX(SETORES!$B:$B,MATCH(A83,SETORES!$A:$A,0)) -> Clientes | H83: Agosto/2026
A84: Comercial Corporativo | B84: Custo Fixo | C84: E-mail do departamento | D84: 12 | E84: 50 | F84: =IFERROR(D84*E84,0) -> 600 | G84: =INDEX(SETORES!$B:$B,MATCH(A84,SETORES!$A:$A,0)) -> Clientes | H84: Agosto/2026
A85: Comercial Corporativo | B85: Custo Variável | C85: Endomarketing | F85: =IFERROR(D85*E85,0) -> 0 | G85: =INDEX(SETORES!$B:$B,MATCH(A85,SETORES!$A:$A,0)) -> Clientes | H85: Agosto/2026
A86: Comercial Corporativo | B86: Custo Fixo | C86: Energia elétrica (rateio) | F86: =IFERROR(D86*E86,0) -> 0 | G86: =INDEX(SETORES!$B:$B,MATCH(A86,SETORES!$A:$A,0)) -> Clientes | H86: Agosto/2026
A87: Comercial Corporativo | B87: Custo Variável | C87: Exames médicos | F87: =IFERROR(D87*E87,0) -> 0 | G87: =INDEX(SETORES!$B:$B,MATCH(A87,SETORES!$A:$A,0)) -> Clientes | H87: Agosto/2026
A88: Comercial Corporativo | B88: Custo Fixo | C88: Folha de pagamento (salários) | D88: 1 | E88: 189839.41 | F88: =IFERROR(D88*E88,0) -> 189839.41 | G88: =INDEX(SETORES!$B:$B,MATCH(A88,SETORES!$A:$A,0)) -> Clientes | H88: Agosto/2026
A89: Comercial Corporativo | B89: Custo Fixo | C89: Gympass | F89: =IFERROR(D89*E89,0) -> 0 | G89: =INDEX(SETORES!$B:$B,MATCH(A89,SETORES!$A:$A,0)) -> Clientes | H89: Agosto/2026
A90: Comercial Corporativo | B90: Custo Fixo | C90: Impressora | F90: =IFERROR(D90*E90,0) -> 0 | G90: =INDEX(SETORES!$B:$B,MATCH(A90,SETORES!$A:$A,0)) -> Clientes | H90: Agosto/2026
A91: Comercial Corporativo | B91: Custo Fixo | C91: Instalações - corredores e alojamentos (rateio) | D91: 1 | E91: 232.63 | F91: =IFERROR(D91*E91,0) -> 232.63 | G91: =INDEX(SETORES!$B:$B,MATCH(A91,SETORES!$A:$A,0)) -> Clientes | H91: Agosto/2026
A92: Comercial Corporativo | B92: Custo Fixo | C92: Linhas moveis (FIQUE MÓVEL) | F92: =IFERROR(D92*E92,0) -> 0 | G92: =INDEX(SETORES!$B:$B,MATCH(A92,SETORES!$A:$A,0)) -> Clientes | H92: Agosto/2026
A93: Comercial Corporativo | B93: Custo Variável | C93: Marketing direto | F93: =IFERROR(D93*E93,0) -> 0 | G93: =INDEX(SETORES!$B:$B,MATCH(A93,SETORES!$A:$A,0)) -> Clientes | H93: Agosto/2026
A94: Comercial Corporativo | B94: Custo Variável | C94: Material de escritório (suprimentos de informática) | D94: 1 | E94: 9.64 | F94: =IFERROR(D94*E94,0) -> 9.64 | G94: =INDEX(SETORES!$B:$B,MATCH(A94,SETORES!$A:$A,0)) -> Clientes | H94: Agosto/2026
A95: Comercial Corporativo | B95: Custo Fixo | C95: Material de uso coletivo (copa/limpeza) | F95: =IFERROR(D95*E95,0) -> 0 | G95: =INDEX(SETORES!$B:$B,MATCH(A95,SETORES!$A:$A,0)) -> Clientes | H95: Agosto/2026
A96: Comercial Corporativo | B96: Custo Variável | C96: Novo Fardamento | D96: 1 | E96: 90 | F96: =IFERROR(D96*E96,0) -> 90 | G96: =INDEX(SETORES!$B:$B,MATCH(A96,SETORES!$A:$A,0)) -> Clientes | H96: Agosto/2026
A97: Comercial Corporativo | B97: Custo Fixo | C97: Plataforma de licitações (pago anual em julho, ref. 12 meses) | F97: =IFERROR(D97*E97,0) -> 0 | G97: =INDEX(SETORES!$B:$B,MATCH(A97,SETORES!$A:$A,0)) -> Clientes | H97: Agosto/2026
A98: Comercial Corporativo | B98: Custo Variável | C98: Rescisões/Despesas Trabalhistas extra folha | F98: =IFERROR(D98*E98,0) -> 0 | G98: =INDEX(SETORES!$B:$B,MATCH(A98,SETORES!$A:$A,0)) -> Clientes | H98: Agosto/2026
A99: Comercial Corporativo | B99: Custo Fixo | C99: Salesforce | D99: 1 | E99: 3042.34 | F99: =IFERROR(D99*E99,0) -> 3042.34 | G99: =INDEX(SETORES!$B:$B,MATCH(A99,SETORES!$A:$A,0)) -> Clientes | H99: Agosto/2026
A100: Comercial Corporativo | B100: Custo Fixo | C100: Stargrid | D100: 12 | E100: 1.87 | F100: =IFERROR(D100*E100,0) -> 22.44 | G100: =INDEX(SETORES!$B:$B,MATCH(A100,SETORES!$A:$A,0)) -> Clientes | H100: Agosto/2026
A101: Comercial Corporativo | B101: Custo Variável | C101: Substituição extra de Fardamento | F101: =IFERROR(D101*E101,0) -> 0 | G101: =INDEX(SETORES!$B:$B,MATCH(A101,SETORES!$A:$A,0)) -> Clientes | H101: Agosto/2026
...

Sheet RESUMO REEMBOLSO
A1: RESUMO — REEMBOLSO POR EMPRESA
A3: Empresa | B3: Total de Custo Rateado (R$) | C3: Total de Royalty (R$) | D3: Custos Comerciais Diretos (R$) | E3: Total Geral a Cobrar (R$) | F3: % do Total Geral (custo) | G3: Mês
A4: Empresa Licenciada DX2 | B4: =SUMIFS(PARÂMETROS!$F:$F,PARÂMETROS!$C:$C,A4,PARÂMETROS!$J:$J,G4) -> 76157.1 | C4: =SUMIFS(PARÂMETROS!$H:$H,PARÂMETROS!$C:$C,A4,PARÂMETROS!$J:$J,G4) -> 0 | D4: =SUMIFS('COMERCIAL VAREJO'!$H:$H,'COMERCIAL VAREJO'!$B:$B,A4,'COMERCIAL VAREJO'!$A:$A,G4,'COMERCIAL VAREJO'!$C:$C,"<>") -> 0 | E4: =B4+C4+D4 -> 76157.1 | F4: =IFERROR(B4/B$12,0) -> 0.031841629 | G4: Junho/2026
A5: Empresa Licenciada H&A | B5: =SUMIFS(PARÂMETROS!$F:$F,PARÂMETROS!$C:$C,A5,PARÂMETROS!$J:$J,G5) -> 150715.63 | C5: =SUMIFS(PARÂMETROS!$H:$H,PARÂMETROS!$C:$C,A5,PARÂMETROS!$J:$J,G5) -> 0 | D5: =SUMIFS('COMERCIAL VAREJO'!$H:$H,'COMERCIAL VAREJO'!$B:$B,A5,'COMERCIAL VAREJO'!$A:$A,G5,'COMERCIAL VAREJO'!$C:$C,"<>") -> 0 | E5: =B5+C5+D5 -> 150715.63 | F5: =IFERROR(B5/B$12,0) -> 0.063014889 | G5: Junho/2026
A6: Empresa Licenciada SOLON ARAUJO | B6: =SUMIFS(PARÂMETROS!$F:$F,PARÂMETROS!$C:$C,A6,PARÂMETROS!$J:$J,G6) -> 171875.74 | C6: =SUMIFS(PARÂMETROS!$H:$H,PARÂMETROS!$C:$C,A6,PARÂMETROS!$J:$J,G6) -> 0 | D6: =SUMIFS('COMERCIAL VAREJO'!$H:$H,'COMERCIAL VAREJO'!$B:$B,A6,'COMERCIAL VAREJO'!$A:$A,G6,'COMERCIAL VAREJO'!$C:$C,"<>") -> 0 | E6: =B6+C6+D6 -> 171875.74 | F6: =IFERROR(B6/B$12,0) -> 0.071862029 | G6: Junho/2026
A7: Empresa Licenciada SOARES E LINS | B7: =SUMIFS(PARÂMETROS!$F:$F,PARÂMETROS!$C:$C,A7,PARÂMETROS!$J:$J,G7) -> 44130.681 | C7: =SUMIFS(PARÂMETROS!$H:$H,PARÂMETROS!$C:$C,A7,PARÂMETROS!$J:$J,G7) -> 0 | D7: =SUMIFS('COMERCIAL VAREJO'!$H:$H,'COMERCIAL VAREJO'!$B:$B,A7,'COMERCIAL VAREJO'!$A:$A,G7,'COMERCIAL VAREJO'!$C:$C,"<>") -> 0 | E7: =B7+C7+D7 -> 44130.681 | F7: =IFERROR(B7/B$12,0) -> 0.018451238 | G7: Junho/2026
A8: Empresa Licenciada SOARES E SILVA | B8: =SUMIFS(PARÂMETROS!$F:$F,PARÂMETROS!$C:$C,A8,PARÂMETROS!$J:$J,G8) -> 81282.875 | C8: =SUMIFS(PARÂMETROS!$H:$H,PARÂMETROS!$C:$C,A8,PARÂMETROS!$J:$J,G8) -> 0 | D8: =SUMIFS('COMERCIAL VAREJO'!$H:$H,'COMERCIAL VAREJO'!$B:$B,A8,'COMERCIAL VAREJO'!$A:$A,G8,'COMERCIAL VAREJO'!$C:$C,"<>") -> 0 | E8: =B8+C8+D8 -> 81282.875 | F8: =IFERROR(B8/B$12,0) -> 0.033984739 | G8: Junho/2026
A9: Empresa Licenciada SOUZA E SILVA | B9: =SUMIFS(PARÂMETROS!$F:$F,PARÂMETROS!$C:$C,A9,PARÂMETROS!$J:$J,G9) -> 54691.145 | C9: =SUMIFS(PARÂMETROS!$H:$H,PARÂMETROS!$C:$C,A9,PARÂMETROS!$J:$J,G9) -> 0 | D9: =SUMIFS('COMERCIAL VAREJO'!$H:$H,'COMERCIAL VAREJO'!$B:$B,A9,'COMERCIAL VAREJO'!$A:$A,G9,'COMERCIAL VAREJO'!$C:$C,"<>") -> 0 | E9: =B9+C9+D9 -> 54691.145 | F9: =IFERROR(B9/B$12,0) -> 0.022866616 | G9: Junho/2026
A10: Empresa Licenciada VOICENET | B10: =SUMIFS(PARÂMETROS!$F:$F,PARÂMETROS!$C:$C,A10,PARÂMETROS!$J:$J,G10) -> 57686.948 | C10: =SUMIFS(PARÂMETROS!$H:$H,PARÂMETROS!$C:$C,A10,PARÂMETROS!$J:$J,G10) -> 0 | D10: =SUMIFS('COMERCIAL VAREJO'!$H:$H,'COMERCIAL VAREJO'!$B:$B,A10,'COMERCIAL VAREJO'!$A:$A,G10,'COMERCIAL VAREJO'!$C:$C,"<>") -> 0 | E10: =B10+C10+D10 -> 57686.948 | F10: =IFERROR(B10/B$12,0) -> 0.024119175 | G10: Junho/2026
A11: DTEL (uso próprio) | B11: =SUMIFS(PARÂMETROS!$F:$F,PARÂMETROS!$C:$C,A11,PARÂMETROS!$J:$J,G11) -> 1755206.2 | C11: =SUMIFS(PARÂMETROS!$H:$H,PARÂMETROS!$C:$C,A11,PARÂMETROS!$J:$J,G11) -> 0 | D11: =SUMIFS('COMERCIAL VAREJO'!$H:$H,'COMERCIAL VAREJO'!$B:$B,A11,'COMERCIAL VAREJO'!$A:$A,G11,'COMERCIAL VAREJO'!$C:$C,"<>") -> 0 | E11: =B11+C11+D11 -> 1755206.2 | F11: =IFERROR(B11/B$12,0) -> 0.73385968 | G11: Junho/2026
A12: TOTAL GERAL — Junho/2026 | B12: =SUM(B4:B11) -> 2391746.3 | C12: =SUM(C4:C11) -> 0 | D12: =SUM(D4:D11) -> 0 | E12: =SUM(E4:E11) -> 2391746.3
A14: Empresa Licenciada DX2 | B14: =SUMIFS(PARÂMETROS!$F:$F,PARÂMETROS!$C:$C,A14,PARÂMETROS!$J:$J,G14) -> 65465.085 | C14: =SUMIFS(PARÂMETROS!$H:$H,PARÂMETROS!$C:$C,A14,PARÂMETROS!$J:$J,G14) -> 0 | D14: =SUMIFS('COMERCIAL VAREJO'!$H:$H,'COMERCIAL VAREJO'!$B:$B,A14,'COMERCIAL VAREJO'!$A:$A,G14,'COMERCIAL VAREJO'!$C:$C,"<>") -> 0 | E14: =B14+C14+D14 -> 65465.085 | F14: =IFERROR(B14/B$22,0) -> 0.031665912 | G14: Maio/2026
A15: Empresa Licenciada H&A | B15: =SUMIFS(PARÂMETROS!$F:$F,PARÂMETROS!$C:$C,A15,PARÂMETROS!$J:$J,G15) -> 132760.39 | C15: =SUMIFS(PARÂMETROS!$H:$H,PARÂMETROS!$C:$C,A15,PARÂMETROS!$J:$J,G15) -> 0 | D15: =SUMIFS('COMERCIAL VAREJO'!$H:$H,'COMERCIAL VAREJO'!$B:$B,A15,'COMERCIAL VAREJO'!$A:$A,G15,'COMERCIAL VAREJO'!$C:$C,"<>") -> 0 | E15: =B15+C15+D15 -> 132760.39 | F15: =IFERROR(B15/B$22,0) -> 0.064217114 | G15: Maio/2026
A16: Empresa Licenciada SOLON ARAUJO | B16: =SUMIFS(PARÂMETROS!$F:$F,PARÂMETROS!$C:$C,A16,PARÂMETROS!$J:$J,G16) -> 150306.29 | C16: =SUMIFS(PARÂMETROS!$H:$H,PARÂMETROS!$C:$C,A16,PARÂMETROS!$J:$J,G16) -> 0 | D16: =SUMIFS('COMERCIAL VAREJO'!$H:$H,'COMERCIAL VAREJO'!$B:$B,A16,'COMERCIAL VAREJO'!$A:$A,G16,'COMERCIAL VAREJO'!$C:$C,"<>") -> 0 | E16: =B16+C16+D16 -> 150306.29 | F16: =IFERROR(B16/B$22,0) -> 0.072704185 | G16: Maio/2026
A17: Empresa Licenciada SOARES E LINS | B17: =SUMIFS(PARÂMETROS!$F:$F,PARÂMETROS!$C:$C,A17,PARÂMETROS!$J:$J,G17) -> 38334.918 | C17: =SUMIFS(PARÂMETROS!$H:$H,PARÂMETROS!$C:$C,A17,PARÂMETROS!$J:$J,G17) -> 0 | D17: =SUMIFS('COMERCIAL VAREJO'!$H:$H,'COMERCIAL VAREJO'!$B:$B,A17,'COMERCIAL VAREJO'!$A:$A,G17,'COMERCIAL VAREJO'!$C:$C,"<>") -> 0 | E17: =B17+C17+D17 -> 38334.918 | F17: =IFERROR(B17/B$22,0) -> 0.018542864 | G17: Maio/2026
A18: Empresa Licenciada SOARES E SILVA | B18: =SUMIFS(PARÂMETROS!$F:$F,PARÂMETROS!$C:$C,A18,PARÂMETROS!$J:$J,G18) -> 71152.656 | C18: =SUMIFS(PARÂMETROS!$H:$H,PARÂMETROS!$C:$C,A18,PARÂMETROS!$J:$J,G18) -> 0 | D18: =SUMIFS('COMERCIAL VAREJO'!$H:$H,'COMERCIAL VAREJO'!$B:$B,A18,'COMERCIAL VAREJO'!$A:$A,G18,'COMERCIAL VAREJO'!$C:$C,"<>") -> 0 | E18: =B18+C18+D18 -> 71152.656 | F18: =IFERROR(B18/B$22,0) -> 0.03441703 | G18: Maio/2026
A19: Empresa Licenciada SOUZA E SILVA | B19: =SUMIFS(PARÂMETROS!$F:$F,PARÂMETROS!$C:$C,A19,PARÂMETROS!$J:$J,G19) -> 47843.858 | C19: =SUMIFS(PARÂMETROS!$H:$H,PARÂMETROS!$C:$C,A19,PARÂMETROS!$J:$J,G19) -> 0 | D19: =SUMIFS('COMERCIAL VAREJO'!$H:$H,'COMERCIAL VAREJO'!$B:$B,A19,'COMERCIAL VAREJO'!$A:$A,G19,'COMERCIAL VAREJO'!$C:$C,"<>") -> 0 | E19: =B19+C19+D19 -> 47843.858 | F19: =IFERROR(B19/B$22,0) -> 0.023142403 | G19: Maio/2026
A20: Empresa Licenciada VOICENET | B20: =SUMIFS(PARÂMETROS!$F:$F,PARÂMETROS!$C:$C,A20,PARÂMETROS!$J:$J,G20) -> 51202.106 | C20: =SUMIFS(PARÂMETROS!$H:$H,PARÂMETROS!$C:$C,A20,PARÂMETROS!$J:$J,G20) -> 0 | D20: =SUMIFS('COMERCIAL VAREJO'!$H:$H,'COMERCIAL VAREJO'!$B:$B,A20,'COMERCIAL VAREJO'!$A:$A,G20,'COMERCIAL VAREJO'!$C:$C,"<>") -> 0 | E20: =B20+C20+D20 -> 51202.106 | F20: =IFERROR(B20/B$22,0) -> 0.024766811 | G20: Maio/2026
A21: DTEL (uso próprio) | B21: =SUMIFS(PARÂMETROS!$F:$F,PARÂMETROS!$C:$C,A21,PARÂMETROS!$J:$J,G21) -> 1510302.4 | C21: =SUMIFS(PARÂMETROS!$H:$H,PARÂMETROS!$C:$C,A21,PARÂMETROS!$J:$J,G21) -> 0 | D21: =SUMIFS('COMERCIAL VAREJO'!$H:$H,'COMERCIAL VAREJO'!$B:$B,A21,'COMERCIAL VAREJO'!$A:$A,G21,'COMERCIAL VAREJO'!$C:$C,"<>") -> 0 | E21: =B21+C21+D21 -> 1510302.4 | F21: =IFERROR(B21/B$22,0) -> 0.73054368 | G21: Maio/2026
A22: TOTAL GERAL — Maio/2026 | B22: =SUM(B14:B21) -> 2067367.7 | C22: =SUM(C14:C21) -> 0 | D22: =SUM(D14:D21) -> 0 | E22: =SUM(E14:E21) -> 2067367.7
A24: Empresa Licenciada DX2 | B24: =SUMIFS(PARÂMETROS!$F:$F,PARÂMETROS!$C:$C,A24,PARÂMETROS!$J:$J,G24) -> 81468.123 | C24: =SUMIFS(PARÂMETROS!$H:$H,PARÂMETROS!$C:$C,A24,PARÂMETROS!$J:$J,G24) -> 0 | D24: =SUMIFS('COMERCIAL VAREJO'!$H:$H,'COMERCIAL VAREJO'!$B:$B,A24,'COMERCIAL VAREJO'!$A:$A,G24,'COMERCIAL VAREJO'!$C:$C,"<>") -> 0 | E24: =B24+C24+D24 -> 81468.123 | F24: =IFERROR(B24/B$32,0) -> 0.031662514 | G24: Julho/2026
A25: Empresa Licenciada H&A | B25: =SUMIFS(PARÂMETROS!$F:$F,PARÂMETROS!$C:$C,A25,PARÂMETROS!$J:$J,G25) -> 147726.92 | C25: =SUMIFS(PARÂMETROS!$H:$H,PARÂMETROS!$C:$C,A25,PARÂMETROS!$J:$J,G25) -> 0 | D25: =SUMIFS('COMERCIAL VAREJO'!$H:$H,'COMERCIAL VAREJO'!$B:$B,A25,'COMERCIAL VAREJO'!$A:$A,G25,'COMERCIAL VAREJO'!$C:$C,"<>") -> 0 | E25: =B25+C25+D25 -> 147726.92 | F25: =IFERROR(B25/B$32,0) -> 0.057413936 | G25: Julho/2026
A26: Empresa Licenciada SOLON ARAUJO | B26: =SUMIFS(PARÂMETROS!$F:$F,PARÂMETROS!$C:$C,A26,PARÂMETROS!$J:$J,G26) -> 179881.52 | C26: =SUMIFS(PARÂMETROS!$H:$H,PARÂMETROS!$C:$C,A26,PARÂMETROS!$J:$J,G26) -> 0 | D26: =SUMIFS('COMERCIAL VAREJO'!$H:$H,'COMERCIAL VAREJO'!$B:$B,A26,'COMERCIAL VAREJO'!$A:$A,G26,'COMERCIAL VAREJO'!$C:$C,"<>") -> 0 | E26: =B26+C26+D26 -> 179881.52 | F26: =IFERROR(B26/B$32,0) -> 0.069910793 | G26: Julho/2026
A27: Empresa Licenciada SOARES E LINS | B27: =SUMIFS(PARÂMETROS!$F:$F,PARÂMETROS!$C:$C,A27,PARÂMETROS!$J:$J,G27) -> 45812.57 | C27: =SUMIFS(PARÂMETROS!$H:$H,PARÂMETROS!$C:$C,A27,PARÂMETROS!$J:$J,G27) -> 0 | D27: =SUMIFS('COMERCIAL VAREJO'!$H:$H,'COMERCIAL VAREJO'!$B:$B,A27,'COMERCIAL VAREJO'!$A:$A,G27,'COMERCIAL VAREJO'!$C:$C,"<>") -> 0 | E27: =B27+C27+D27 -> 45812.57 | F27: =IFERROR(B27/B$32,0) -> 0.017805015 | G27: Julho/2026
A28: Empresa Licenciada SOARES E SILVA | B28: =SUMIFS(PARÂMETROS!$F:$F,PARÂMETROS!$C:$C,A28,PARÂMETROS!$J:$J,G28) -> 85737.863 | C28: =SUMIFS(PARÂMETROS!$H:$H,PARÂMETROS!$C:$C,A28,PARÂMETROS!$J:$J,G28) -> 0 | D28: =SUMIFS('COMERCIAL VAREJO'!$H:$H,'COMERCIAL VAREJO'!$B:$B,A28,'COMERCIAL VAREJO'!$A:$A,G28,'COMERCIAL VAREJO'!$C:$C,"<>") -> 0 | E28: =B28+C28+D28 -> 85737.863 | F28: =IFERROR(B28/B$32,0) -> 0.033321944 | G28: Julho/2026
A29: Empresa Licenciada SOUZA E SILVA | B29: =SUMIFS(PARÂMETROS!$F:$F,PARÂMETROS!$C:$C,A29,PARÂMETROS!$J:$J,G29) -> 57512.379 | C29: =SUMIFS(PARÂMETROS!$H:$H,PARÂMETROS!$C:$C,A29,PARÂMETROS!$J:$J,G29) -> 0 | D29: =SUMIFS('COMERCIAL VAREJO'!$H:$H,'COMERCIAL VAREJO'!$B:$B,A29,'COMERCIAL VAREJO'!$A:$A,G29,'COMERCIAL VAREJO'!$C:$C,"<>") -> 0 | E29: =B29+C29+D29 -> 57512.379 | F29: =IFERROR(B29/B$32,0) -> 0.022352135 | G29: Julho/2026
A30: Empresa Licenciada VOICENET | B30: =SUMIFS(PARÂMETROS!$F:$F,PARÂMETROS!$C:$C,A30,PARÂMETROS!$J:$J,G30) -> 61272.918 | C30: =SUMIFS(PARÂMETROS!$H:$H,PARÂMETROS!$C:$C,A30,PARÂMETROS!$J:$J,G30) -> 0 | D30: =SUMIFS('COMERCIAL VAREJO'!$H:$H,'COMERCIAL VAREJO'!$B:$B,A30,'COMERCIAL VAREJO'!$A:$A,G30,'COMERCIAL VAREJO'!$C:$C,"<>") -> 0 | E30: =B30+C30+D30 -> 61272.918 | F30: =IFERROR(B30/B$32,0) -> 0.023813665 | G30: Julho/2026
A31: DTEL (uso próprio) | B31: =SUMIFS(PARÂMETROS!$F:$F,PARÂMETROS!$C:$C,A31,PARÂMETROS!$J:$J,G31) -> 1913602.7 | C31: =SUMIFS(PARÂMETROS!$H:$H,PARÂMETROS!$C:$C,A31,PARÂMETROS!$J:$J,G31) -> 0 | D31: =SUMIFS('COMERCIAL VAREJO'!$H:$H,'COMERCIAL VAREJO'!$B:$B,A31,'COMERCIAL VAREJO'!$A:$A,G31,'COMERCIAL VAREJO'!$C:$C,"<>") -> 0 | E31: =B31+C31+D31 -> 1913602.7 | F31: =IFERROR(B31/B$32,0) -> 0.74372 | G31: Julho/2026
A32: TOTAL GERAL — Julho/2026 | B32: =SUM(B24:B31) -> 2573015 | C32: =SUM(C24:C31) -> 0 | D32: =SUM(D24:D31) -> 0 | E32: =SUM(E24:E31) -> 2573015
A33: Empresa Licenciada DX2 | B33: =SUMIFS(PARÂMETROS!$F:$F,PARÂMETROS!$C:$C,A33,PARÂMETROS!$J:$J,G33) -> 80480.054 | C33: =SUMIFS(PARÂMETROS!$H:$H,PARÂMETROS!$C:$C,A33,PARÂMETROS!$J:$J,G33) -> 0 | D33: =SUMIFS('COMERCIAL VAREJO'!$H:$H,'COMERCIAL VAREJO'!$B:$B,A33,'COMERCIAL VAREJO'!$A:$A,G33,'COMERCIAL VAREJO'!$C:$C,"<>") -> 0 | E33: =B33+C33+D33 -> 80480.054 | F33: =IFERROR(B33/B$32,0) -> 0.031278502 | G33: Agosto/2026
A34: Empresa Licenciada H&A | G34: Agosto/2026
A35: Empresa Licenciada SOLON ARAUJO | B35: =SUMIFS(PARÂMETROS!$F:$F,PARÂMETROS!$C:$C,A35,PARÂMETROS!$J:$J,G35) -> 180230.56 | C35: =SUMIFS(PARÂMETROS!$H:$H,PARÂMETROS!$C:$C,A35,PARÂMETROS!$J:$J,G35) -> 0 | D35: =SUMIFS('COMERCIAL VAREJO'!$H:$H,'COMERCIAL VAREJO'!$B:$B,A35,'COMERCIAL VAREJO'!$A:$A,G35,'COMERCIAL VAREJO'!$C:$C,"<>") -> 0 | E35: =B35+C35+D35 -> 180230.56 | F35: =IFERROR(B35/B$32,0) -> 0.070046447 | G35: Agosto/2026
A36: Empresa Licenciada SOARES E LINS | B36: =SUMIFS(PARÂMETROS!$F:$F,PARÂMETROS!$C:$C,A36,PARÂMETROS!$J:$J,G36) -> 45544.912 | C36: =SUMIFS(PARÂMETROS!$H:$H,PARÂMETROS!$C:$C,A36,PARÂMETROS!$J:$J,G36) -> 0 | D36: =SUMIFS('COMERCIAL VAREJO'!$H:$H,'COMERCIAL VAREJO'!$B:$B,A36,'COMERCIAL VAREJO'!$A:$A,G36,'COMERCIAL VAREJO'!$C:$C,"<>") -> 0 | E36: =B36+C36+D36 -> 45544.912 | F36: =IFERROR(B36/B$32,0) -> 0.01770099 | G36: Agosto/2026
A37: Empresa Licenciada SOARES E SILVA | B37: =SUMIFS(PARÂMETROS!$F:$F,PARÂMETROS!$C:$C,A37,PARÂMETROS!$J:$J,G37) -> 82987.231 | C37: =SUMIFS(PARÂMETROS!$H:$H,PARÂMETROS!$C:$C,A37,PARÂMETROS!$J:$J,G37) -> 0 | D37: =SUMIFS('COMERCIAL VAREJO'!$H:$H,'COMERCIAL VAREJO'!$B:$B,A37,'COMERCIAL VAREJO'!$A:$A,G37,'COMERCIAL VAREJO'!$C:$C,"<>") -> 0 | E37: =B37+C37+D37 -> 82987.231 | F37: =IFERROR(B37/B$32,0) -> 0.032252914 | G37: Agosto/2026
A38: Empresa Licenciada SOUZA E SILVA | B38: =SUMIFS(PARÂMETROS!$F:$F,PARÂMETROS!$C:$C,A38,PARÂMETROS!$J:$J,G38) -> 57111.55 | C38: =SUMIFS(PARÂMETROS!$H:$H,PARÂMETROS!$C:$C,A38,PARÂMETROS!$J:$J,G38) -> 0 | D38: =SUMIFS('COMERCIAL VAREJO'!$H:$H,'COMERCIAL VAREJO'!$B:$B,A38,'COMERCIAL VAREJO'!$A:$A,G38,'COMERCIAL VAREJO'!$C:$C,"<>") -> 0 | E38: =B38+C38+D38 -> 57111.55 | F38: =IFERROR(B38/B$32,0) -> 0.022196353 | G38: Agosto/2026
A39: Empresa Licenciada VOICENET | B39: =SUMIFS(PARÂMETROS!$F:$F,PARÂMETROS!$C:$C,A39,PARÂMETROS!$J:$J,G39) -> 60391.242 | C39: =SUMIFS(PARÂMETROS!$H:$H,PARÂMETROS!$C:$C,A39,PARÂMETROS!$J:$J,G39) -> 0 | D39: =SUMIFS('COMERCIAL VAREJO'!$H:$H,'COMERCIAL VAREJO'!$B:$B,A39,'COMERCIAL VAREJO'!$A:$A,G39,'COMERCIAL VAREJO'!$C:$C,"<>") -> 0 | E39: =B39+C39+D39 -> 60391.242 | F39: =IFERROR(B39/B$32,0) -> 0.023471002 | G39: Agosto/2026
A40: DTEL (uso próprio) | B40: =SUMIFS(PARÂMETROS!$F:$F,PARÂMETROS!$C:$C,A40,PARÂMETROS!$J:$J,G40) -> 1822826.8 | C40: =SUMIFS(PARÂMETROS!$H:$H,PARÂMETROS!$C:$C,A40,PARÂMETROS!$J:$J,G40) -> 0 | D40: =SUMIFS('COMERCIAL VAREJO'!$H:$H,'COMERCIAL VAREJO'!$B:$B,A40,'COMERCIAL VAREJO'!$A:$A,G40,'COMERCIAL VAREJO'!$C:$C,"<>") -> 0 | E40: =B40+C40+D40 -> 1822826.8 | F40: =IFERROR(B40/B$32,0) -> 0.70844001 | G40: Agosto/2026
A41: TOTAL GERAL — Agosto/2026 | B41: =SUM(B33:B40) -> 2329572.3 | C41: =SUM(C33:C40) -> 0 | D41: =SUM(D33:D40) -> 0 | E41: =SUM(E33:E40) -> 2329572.3
A44: Nota: o Total de Custo Rateado deve ser igual ao TOTAL GERAL da aba SETORES. Custos Comerciais Diretos vêm da aba COMERCIAL (custos já atribuídos diretamente a cada empresa, sem % de rateio). O Total de Royalty só existe se algum % Royalty foi definido em PARÂMETROS (padrão é 0%, sem royalty).

Sheet COMERCIAL VAREJO
A1: COMERCIAL VAREJO — CUSTOS DIRETOS POR COORDENADOR/EQUIPE (equipe de vendas externas)
A2: Cada equipe é o COORDENADOR/GERENTE da planilha de vendas PAP. Folha Trabalhista e Combustível são valores REAIS, cruzados pelo nome do colaborador (folha: 99 de 120 ativos encontrados; combustível: conforme arquivo de combustível). Vale Transporte, RH, DP, SST, Gympass, Stargrid, Fardamento e Linhas móveis não têm nome de colaborador na fonte — o valor total de cada empresa é RATEADO entre as equipes que têm gente daquela empresa, proporcional ao nº de colaboradores (E-mail do departamento é rateado só entre executivo/supervisor/coordenador/líder, que são quem usa). Rescisões foram excluídas da cobrança (sem fonte confirmada de nome/empresa/mês). Estes valores somados alimentam a coluna 'Custos Comerciais Diretos' do RESUMO REEMBOLSO.
A4: COMPOSIÇÃO DAS EQUIPES
A5: Coordenador/Equipe | B5: Empresa | C5: Total Ativos | D5: Vendedores Fixos (PAP) | E5: Executivos | F5: Outros cargos
A6: ELTHON MENEZES | B6: DTEL | C6: 39 | D6: 33 | E6: 2 | F6: MOTORISTA: 2, SUPERVISOR: 2
A7: GABRIEL LIMA | B7: DTEL | C7: 9 | D7: 9 | E7: 0 | F7: —
A8: LUCAS BONIFÁCIO | B8: DTEL | C8: 7 | D8: 6 | E8: 1 | F8: —
A9: MICHELANGELO | B9: DTEL | C9: 11 | D9: 8 | E9: 1 | F9: MOTORISTA: 1, SUPERVISOR: 1
A10: MICHELANGELO | B10: Voicenet | C10: 2 | D10: 1 | E10: 1 | F10: —
A11: TARCIZIO MEIRELES | B11: DTEL | C11: 18 | D11: 14 | E11: 2 | F11: MOTORISTA: 1, SUPERVISOR: 1
A12: TARCIZIO MEIRELES | B12: Solon Araújo | C12: 2 | D12: 1 | E12: 1 | F12: —
A13: TARCIZIO MEIRELES | B13: Souza e Silva | C13: 5 | D13: 5 | E13: 0 | F13: —
A14: TIAGO | B14: DX2 | C14: 8 | D14: 7 | E14: 0 | F14: LÍDER: 1
A15: TIAGO | B15: H&A | C15: 2 | D15: 1 | E15: 0 | F15: LÍDER: 1
A16: TIAGO | B16: Soares e Silva | C16: 11 | D16: 9 | E16: 1 | F16: SUPERVISOR: 1
A17: VITOR LINS | B17: Soares e Lins | C17: 1 | D17: 0 | E17: 0 | F17: LÍDER: 1
A19: CUSTOS DIRETOS — RATEADOS/REAIS POR COORDENADOR/EQUIPE
A20: Mês | B20: Empresa | C20: Categoria | D20: Despesa | E20: Coordenador/Equipe | F20: Quantidade | G20: Valor Unitário (R$) | H20: Valor (R$) | I20: Origem
A21: Junho/2026 | B21: DTEL | C21: Pessoal | D21: Folha Trabalhista com impostos do mês | E21: ELTHON MENEZES | F21: 1 | G21: 59982.059 | H21: 59982.059 | I21: Real (cruzado por nome, 38/42 encontrados) | Ajustado 24/08/2026: subtraído o custo de folha de Pedro Moreira do Amaral (R$ 4741.11), que passou a ter linha própria de van/kombi, para não contar 2x. | Ajustado 24/08/2026: subtraído o custo de folha de Felipe Lopes de Souza (R$ 5374.25), que passou a ter linha própria de van/kombi, para não contar 2x. | Ajustado 24/08/2026: subtraído o custo de folha de Alvaro Henrique de Sousa (R$ 4859.05), que passou a ter linha própria de van/kombi, para não contar 2x.
A22: Junho/2026 | B22: DTEL | C22: Pessoal | D22: Vale Transporte | E22: ELTHON MENEZES | F22: 1 | G22: 1236.86 | H22: 1236.86 | I22: Estimado (fatia proporcional ao nº de colaboradores da equipe, sem taxa fixa por pessoa), fatia de 39 colaboradores da equipe
A23: Junho/2026 | B23: DTEL | C23: Pessoal | D23: Despesas com RH | E23: ELTHON MENEZES | F23: 39 | G23: 28.31 | H23: 1104.09 | I23: Real (taxa fixa por colaborador, confirmada em todas as empresas)
A24: Junho/2026 | B24: DTEL | C24: Pessoal | D24: Despesas com DP | E24: ELTHON MENEZES | F24: 39 | G24: 47.79 | H24: 1863.81 | I24: Real (taxa fixa por colaborador, confirmada em todas as empresas)
A25: Junho/2026 | B25: DTEL | C25: Segurança do Trabalho | D25: Despesas com SST | E25: ELTHON MENEZES | F25: 39 | G25: 64.54 | H25: 2517.06 | I25: Real (taxa fixa por colaborador, confirmada em todas as empresas)
A26: Junho/2026 | B26: DTEL | C26: Segurança do Trabalho | D26: Despesas SST exames | E26: ELTHON MENEZES | F26: 1 | G26: 142.07 | H26: 142.07 | I26: Estimado (fatia proporcional ao nº de colaboradores da equipe, sem taxa fixa por pessoa), fatia de 39 colaboradores da equipe
A27: Junho/2026 | B27: DTEL | C27: Benefícios | D27: Gympass | E27: ELTHON MENEZES | F27: 39 | G27: 10.05 | H27: 391.95 | I27: Real (taxa fixa por colaborador, confirmada em todas as empresas)
A28: Junho/2026 | B28: DTEL | C28: Benefícios | D28: Stargrid | E28: ELTHON MENEZES | F28: 39 | G28: 2.07 | H28: 80.73 | I28: Real (taxa fixa por colaborador, confirmada em todas as empresas)
A29: Junho/2026 | B29: DTEL | C29: Fardamento | D29: Novo Fardamento | E29: ELTHON MENEZES | F29: 1 | G29: 764.48 | H29: 764.48 | I29: Estimado (fatia proporcional ao nº de colaboradores da equipe, sem taxa fixa por pessoa), fatia de 39 colaboradores da equipe
A30: Junho/2026 | B30: DTEL | C30: Fardamento | D30: Substituição extra de Fardamento | E30: ELTHON MENEZES | F30: 1 | G30: 1150.7 | H30: 1150.7 | I30: Estimado (fatia proporcional ao nº de colaboradores da equipe, sem taxa fixa por pessoa), fatia de 39 colaboradores da equipe
A31: Junho/2026 | B31: DTEL | C31: Estrutura/Infra | D31: Linhas moveis (FIQUE MÓVEL) | E31: ELTHON MENEZES | F31: 42 | G31: 30 | H31: =F31*G31 -> 1260 | I31: Real (taxa fixa por colaborador, confirmada em todas as empresas)
A32: Junho/2026 | B32: DTEL | C32: Frota/Combustível | D32: Consumo de combustível | E32: ELTHON MENEZES | F32: 1 | G32: 370.8 | H32: =F32*G32 -> 370.8 | I32: Real (cruzado por nome, planilha de combustível) | Ajustado 24/08/2026: subtraído o combustível de Pedro Moreira do Amaral (R$ 1887.24), que passou a ter linha própria de van/kombi, para não contar 2x. | Ajustado 24/08/2026: subtraído o combustível de Felipe Lopes de Souza (R$ 3112.86), que passou a ter linha própria de van/kombi, para não contar 2x.
A33: Junho/2026 | B33: DTEL | C33: Pessoal | D33: Folha Trabalhista com impostos do mês | E33: GABRIEL LIMA | F33: 1 | G33: 7035.95 | H33: =F33*G33 -> 7035.95 | I33: Real (cruzado por nome, 3/9 encontrados)
A34: Junho/2026 | B34: DTEL | C34: Pessoal | D34: Vale Transporte | E34: GABRIEL LIMA | F34: 1 | G34: 285.43 | H34: 285.43 | I34: Estimado (fatia proporcional ao nº de colaboradores da equipe, sem taxa fixa por pessoa), fatia de 9 colaboradores da equipe
A35: Junho/2026 | B35: DTEL | C35: Pessoal | D35: Despesas com RH | E35: GABRIEL LIMA | F35: 9 | G35: 28.31 | H35: =F35*G35 -> 254.79 | I35: Real (taxa fixa por colaborador, confirmada em todas as empresas)
A36: Junho/2026 | B36: DTEL | C36: Pessoal | D36: Despesas com DP | E36: GABRIEL LIMA | F36: 9 | G36: 47.79 | H36: =F36*G36 -> 430.11 | I36: Real (taxa fixa por colaborador, confirmada em todas as empresas)
A37: Junho/2026 | B37: DTEL | C37: Segurança do Trabalho | D37: Despesas com SST | E37: GABRIEL LIMA | F37: 9 | G37: 64.54 | H37: =F37*G37 -> 580.86 | I37: Real (taxa fixa por colaborador, confirmada em todas as empresas)
A38: Junho/2026 | B38: DTEL | C38: Segurança do Trabalho | D38: Despesas SST exames | E38: GABRIEL LIMA | F38: 1 | G38: 32.79 | H38: 32.79 | I38: Estimado (fatia proporcional ao nº de colaboradores da equipe, sem taxa fixa por pessoa), fatia de 9 colaboradores da equipe
A39: Junho/2026 | B39: DTEL | C39: Benefícios | D39: Gympass | E39: GABRIEL LIMA | F39: 9 | G39: 10.05 | H39: =F39*G39 -> 90.45 | I39: Real (taxa fixa por colaborador, confirmada em todas as empresas)
A40: Junho/2026 | B40: DTEL | C40: Benefícios | D40: Stargrid | E40: GABRIEL LIMA | F40: 9 | G40: 2.07 | H40: =F40*G40 -> 18.63 | I40: Real (taxa fixa por colaborador, confirmada em todas as empresas)
A41: Junho/2026 | B41: DTEL | C41: Fardamento | D41: Novo Fardamento | E41: GABRIEL LIMA | F41: 1 | G41: 176.42 | H41: 176.42 | I41: Estimado (fatia proporcional ao nº de colaboradores da equipe, sem taxa fixa por pessoa), fatia de 9 colaboradores da equipe
A42: Junho/2026 | B42: DTEL | C42: Fardamento | D42: Substituição extra de Fardamento | E42: GABRIEL LIMA | F42: 1 | G42: 265.55 | H42: 265.55 | I42: Estimado (fatia proporcional ao nº de colaboradores da equipe, sem taxa fixa por pessoa), fatia de 9 colaboradores da equipe
A43: Junho/2026 | B43: DTEL | C43: Estrutura/Infra | D43: Linhas moveis (FIQUE MÓVEL) | E43: GABRIEL LIMA | F43: 9 | G43: 30 | H43: =F43*G43 -> 270 | I43: Real (taxa fixa por colaborador, confirmada em todas as empresas)
A44: Junho/2026 | B44: DTEL | C44: Pessoal | D44: Folha Trabalhista com impostos do mês | E44: LUCAS BONIFÁCIO | F44: 1 | G44: 31149.92 | H44: =F44*G44 -> 31149.92 | I44: Real (cruzado por nome, 7/7 encontrados)
A45: Junho/2026 | B45: DTEL | C45: Pessoal | D45: Vale Transporte | E45: LUCAS BONIFÁCIO | F45: 1 | G45: 222 | H45: 222 | I45: Estimado (fatia proporcional ao nº de colaboradores da equipe, sem taxa fixa por pessoa), fatia de 7 colaboradores da equipe
A46: Junho/2026 | B46: DTEL | C46: Pessoal | D46: Despesas com RH | E46: LUCAS BONIFÁCIO | F46: 7 | G46: 28.31 | H46: =F46*G46 -> 198.17 | I46: Real (taxa fixa por colaborador, confirmada em todas as empresas)
A47: Junho/2026 | B47: DTEL | C47: Pessoal | D47: Despesas com DP | E47: LUCAS BONIFÁCIO | F47: 7 | G47: 47.79 | H47: =F47*G47 -> 334.53 | I47: Real (taxa fixa por colaborador, confirmada em todas as empresas)
A48: Junho/2026 | B48: DTEL | C48: Segurança do Trabalho | D48: Despesas com SST | E48: LUCAS BONIFÁCIO | F48: 7 | G48: 64.54 | H48: =F48*G48 -> 451.78 | I48: Real (taxa fixa por colaborador, confirmada em todas as empresas)
A49: Junho/2026 | B49: DTEL | C49: Segurança do Trabalho | D49: Despesas SST exames | E49: LUCAS BONIFÁCIO | F49: 1 | G49: 25.5 | H49: 25.5 | I49: Estimado (fatia proporcional ao nº de colaboradores da equipe, sem taxa fixa por pessoa), fatia de 7 colaboradores da equipe
A50: Junho/2026 | B50: DTEL | C50: Benefícios | D50: Gympass | E50: LUCAS BONIFÁCIO | F50: 7 | G50: 10.05 | H50: =F50*G50 -> 70.35 | I50: Real (taxa fixa por colaborador, confirmada em todas as empresas)
A51: Junho/2026 | B51: DTEL | C51: Benefícios | D51: Stargrid | E51: LUCAS BONIFÁCIO | F51: 7 | G51: 2.07 | H51: =F51*G51 -> 14.49 | I51: Real (taxa fixa por colaborador, confirmada em todas as empresas)
A52: Junho/2026 | B52: DTEL | C52: Fardamento | D52: Novo Fardamento | E52: LUCAS BONIFÁCIO | F52: 1 | G52: 137.22 | H52: 137.22 | I52: Estimado (fatia proporcional ao nº de colaboradores da equipe, sem taxa fixa por pessoa), fatia de 7 colaboradores da equipe
A53: Junho/2026 | B53: DTEL | C53: Fardamento | D53: Substituição extra de Fardamento | E53: LUCAS BONIFÁCIO | F53: 1 | G53: 206.54 | H53: 206.54 | I53: Estimado (fatia proporcional ao nº de colaboradores da equipe, sem taxa fixa por pessoa), fatia de 7 colaboradores da equipe
A54: Junho/2026 | B54: DTEL | C54: Estrutura/Infra | D54: Linhas moveis (FIQUE MÓVEL) | E54: LUCAS BONIFÁCIO | F54: 7 | G54: 30 | H54: =F54*G54 -> 210 | I54: Real (taxa fixa por colaborador, confirmada em todas as empresas)
A55: Junho/2026 | B55: DTEL | C55: Frota/Combustível | D55: Consumo de combustível | E55: LUCAS BONIFÁCIO | F55: 1 | G55: 1081.14 | H55: =F55*G55 -> 1081.14 | I55: Real (cruzado por nome, planilha de combustível)
A56: Junho/2026 | B56: DTEL | C56: Pessoal | D56: Folha Trabalhista com impostos do mês | E56: MICHELANGELO | F56: 1 | G56: 30187.419 | H56: =F56*G56 -> 30187.419 | I56: Real (cruzado por nome, 11/11 encontrados) | Ajustado 24/08/2026: subtraído o custo de folha de Clovis Mendes da Silva (R$ 4741.11), que passou a ter linha própria de van/kombi, para não contar 2x.
A57: Junho/2026 | B57: DTEL | C57: Pessoal | D57: Vale Transporte | E57: MICHELANGELO | F57: 1 | G57: 348.86 | H57: 348.86 | I57: Estimado (fatia proporcional ao nº de colaboradores da equipe, sem taxa fixa por pessoa), fatia de 11 colaboradores da equipe
A58: Junho/2026 | B58: DTEL | C58: Pessoal | D58: Despesas com RH | E58: MICHELANGELO | F58: 11 | G58: 28.31 | H58: =F58*G58 -> 311.41 | I58: Real (taxa fixa por colaborador, confirmada em todas as empresas)
A59: Junho/2026 | B59: DTEL | C59: Pessoal | D59: Despesas com DP | E59: MICHELANGELO | F59: 11 | G59: 47.79 | H59: =F59*G59 -> 525.69 | I59: Real (taxa fixa por colaborador, confirmada em todas as empresas)
A60: Junho/2026 | B60: DTEL | C60: Segurança do Trabalho | D60: Despesas com SST | E60: MICHELANGELO | F60: 11 | G60: 64.54 | H60: =F60*G60 -> 709.94 | I60: Real (taxa fixa por colaborador, confirmada em todas as empresas)
A61: Junho/2026 | B61: DTEL | C61: Segurança do Trabalho | D61: Despesas SST exames | E61: MICHELANGELO | F61: 1 | G61: 40.07 | H61: 40.07 | I61: Estimado (fatia proporcional ao nº de colaboradores da equipe, sem taxa fixa por pessoa), fatia de 11 colaboradores da equipe
A62: Junho/2026 | B62: DTEL | C62: Benefícios | D62: Gympass | E62: MICHELANGELO | F62: 11 | G62: 10.05 | H62: =F62*G62 -> 110.55 | I62: Real (taxa fixa por colaborador, confirmada em todas as empresas)
A63: Junho/2026 | B63: DTEL | C63: Benefícios | D63: Stargrid | E63: MICHELANGELO | F63: 11 | G63: 2.07 | H63: =F63*G63 -> 22.77 | I63: Real (taxa fixa por colaborador, confirmada em todas as empresas)
A64: Junho/2026 | B64: DTEL | C64: Fardamento | D64: Novo Fardamento | E64: MICHELANGELO | F64: 1 | G64: 215.62 | H64: 215.62 | I64: Estimado (fatia proporcional ao nº de colaboradores da equipe, sem taxa fixa por pessoa), fatia de 11 colaboradores da equipe
A65: Junho/2026 | B65: DTEL | C65: Fardamento | D65: Substituição extra de Fardamento | E65: MICHELANGELO | F65: 1 | G65: 324.56 | H65: 324.56 | I65: Estimado (fatia proporcional ao nº de colaboradores da equipe, sem taxa fixa por pessoa), fatia de 11 colaboradores da equipe
A66: Junho/2026 | B66: DTEL | C66: Estrutura/Infra | D66: Linhas moveis (FIQUE MÓVEL) | E66: MICHELANGELO | F66: 11 | G66: 30 | H66: =F66*G66 -> 330 | I66: Real (taxa fixa por colaborador, confirmada em todas as empresas)
A67: Junho/2026 | B67: DTEL | C67: Frota/Combustível | D67: Consumo de combustível | E67: MICHELANGELO | F67: 1 | G67: 0 | H67: =F67*G67 -> 0 | I67: Real (cruzado por nome, planilha de combustível) | Ajustado 24/08/2026: subtraído o combustível de Clovis Mendes da Silva (R$ 3878.58), que passou a ter linha própria de van/kombi, para não contar 2x.
A68: Junho/2026 | B68: Voicenet | C68: Pessoal | D68: Folha Trabalhista com impostos do mês | E68: MICHELANGELO | F68: 1 | G68: 2763.14 | H68: =F68*G68 -> 2763.14 | I68: Real (cruzado por nome, 1/2 encontrados)
A69: Junho/2026 | B69: Voicenet | C69: Pessoal | D69: Despesas com RH | E69: MICHELANGELO | F69: 2 | G69: 28.31 | H69: =F69*G69 -> 56.62 | I69: Real (taxa fixa por colaborador, confirmada em todas as empresas)
A70: Junho/2026 | B70: Voicenet | C70: Pessoal | D70: Despesas com DP | E70: MICHELANGELO | F70: 2 | G70: 47.79 | H70: =F70*G70 -> 95.58 | I70: Real (taxa fixa por colaborador, confirmada em todas as empresas)
A71: Junho/2026 | B71: Voicenet | C71: Segurança do Trabalho | D71: Despesas com SST | E71: MICHELANGELO | F71: 2 | G71: 64.54 | H71: =F71*G71 -> 129.08 | I71: Real (taxa fixa por colaborador, confirmada em todas as empresas)
A72: Junho/2026 | B72: Voicenet | C72: Benefícios | D72: Gympass | E72: MICHELANGELO | F72: 2 | G72: 10.05 | H72: =F72*G72 -> 20.1 | I72: Real (taxa fixa por colaborador, confirmada em todas as empresas)
A73: Junho/2026 | B73: Voicenet | C73: Benefícios | D73: Stargrid | E73: MICHELANGELO | F73: 2 | G73: 2.07 | H73: =F73*G73 -> 4.14 | I73: Real (taxa fixa por colaborador, confirmada em todas as empresas)
A74: Junho/2026 | B74: Voicenet | C74: Estrutura/Infra | D74: Linhas moveis (FIQUE MÓVEL) | E74: MICHELANGELO | F74: 2 | G74: 30 | H74: =F74*G74 -> 60 | I74: Real (taxa fixa por colaborador, confirmada em todas as empresas)
A75: Junho/2026 | B75: Voicenet | C75: Frota/Combustível | D75: Consumo de combustível | E75: MICHELANGELO | F75: 1 | G75: 696.8 | H75: =F75*G75 -> 696.8 | I75: Real (cruzado por nome, planilha de combustível)
A76: Junho/2026 | B76: DTEL | C76: Pessoal | D76: Folha Trabalhista com impostos do mês | E76: TARCIZIO MEIRELES | F76: 1 | G76: 57354.935 | H76: =F76*G76 -> 57354.935 | I76: Real (cruzado por nome, 18/18 encontrados) | Ajustado 24/08/2026: subtraído o custo de folha de Jose Zenildo da Silva (R$ 5227.07), que passou a ter linha própria de van/kombi, para não contar 2x.
A77: Junho/2026 | B77: DTEL | C77: Pessoal | D77: Vale Transporte | E77: TARCIZIO MEIRELES | F77: 1 | G77: 570.86 | H77: 570.86 | I77: Estimado (fatia proporcional ao nº de colaboradores da equipe, sem taxa fixa por pessoa), fatia de 18 colaboradores da equipe
A78: Junho/2026 | B78: DTEL | C78: Pessoal | D78: Despesas com RH | E78: TARCIZIO MEIRELES | F78: 18 | G78: 28.31 | H78: =F78*G78 -> 509.58 | I78: Real (taxa fixa por colaborador, confirmada em todas as empresas)
A79: Junho/2026 | B79: DTEL | C79: Pessoal | D79: Despesas com DP | E79: TARCIZIO MEIRELES | F79: 18 | G79: 47.79 | H79: =F79*G79 -> 860.22 | I79: Real (taxa fixa por colaborador, confirmada em todas as empresas)
A80: Junho/2026 | B80: DTEL | C80: Segurança do Trabalho | D80: Despesas com SST | E80: TARCIZIO MEIRELES | F80: 18 | G80: 64.54 | H80: =F80*G80 -> 1161.72 | I80: Real (taxa fixa por colaborador, confirmada em todas as empresas)
A81: Junho/2026 | B81: DTEL | C81: Segurança do Trabalho | D81: Despesas SST exames | E81: TARCIZIO MEIRELES | F81: 1 | G81: 65.57 | H81: 65.57 | I81: Estimado (fatia proporcional ao nº de colaboradores da equipe, sem taxa fixa por pessoa), fatia de 18 colaboradores da equipe
A82: Junho/2026 | B82: DTEL | C82: Benefícios | D82: Gympass | E82: TARCIZIO MEIRELES | F82: 18 | G82: 10.05 | H82: =F82*G82 -> 180.9 | I82: Real (taxa fixa por colaborador, confirmada em todas as empresas)
A83: Junho/2026 | B83: DTEL | C83: Benefícios | D83: Stargrid | E83: TARCIZIO MEIRELES | F83: 18 | G83: 2.07 | H83: =F83*G83 -> 37.26 | I83: Real (taxa fixa por colaborador, confirmada em todas as empresas)
A84: Junho/2026 | B84: DTEL | C84: Fardamento | D84: Novo Fardamento | E84: TARCIZIO MEIRELES | F84: 1 | G84: 352.84 | H84: 352.84 | I84: Estimado (fatia proporcional ao nº de colaboradores da equipe, sem taxa fixa por pessoa), fatia de 18 colaboradores da equipe
A85: Junho/2026 | B85: DTEL | C85: Fardamento | D85: Substituição extra de Fardamento | E85: TARCIZIO MEIRELES | F85: 1 | G85: 531.09 | H85: 531.09 | I85: Estimado (fatia proporcional ao nº de colaboradores da equipe, sem taxa fixa por pessoa), fatia de 18 colaboradores da equipe
A86: Junho/2026 | B86: DTEL | C86: Estrutura/Infra | D86: Linhas moveis (FIQUE MÓVEL) | E86: TARCIZIO MEIRELES | F86: 18 | G86: 30 | H86: =F86*G86 -> 540 | I86: Real (taxa fixa por colaborador, confirmada em todas as empresas)
A87: Junho/2026 | B87: DTEL | C87: Frota/Combustível | D87: Consumo de combustível | E87: TARCIZIO MEIRELES | F87: 1 | G87: 2345.27 | H87: =F87*G87 -> 2345.27 | I87: Real (cruzado por nome, planilha de combustível) | Ajustado 24/08/2026: subtraído o combustível de Jose Zenildo da Silva (R$ 2688.78), que passou a ter linha própria de van/kombi, para não contar 2x.
A88: Junho/2026 | B88: Solon Araújo | C88: Pessoal | D88: Folha Trabalhista com impostos do mês | E88: TARCIZIO MEIRELES | F88: 1 | G88: 2755.29 | H88: =F88*G88 -> 2755.29 | I88: Real (cruzado por nome, 1/2 encontrados)
A89: Junho/2026 | B89: Solon Araújo | C89: Pessoal | D89: Despesas com RH | E89: TARCIZIO MEIRELES | F89: 2 | G89: 28.31 | H89: =F89*G89 -> 56.62 | I89: Real (taxa fixa por colaborador, confirmada em todas as empresas)
A90: Junho/2026 | B90: Solon Araújo | C90: Pessoal | D90: Despesas com DP | E90: TARCIZIO MEIRELES | F90: 2 | G90: 47.79 | H90: =F90*G90 -> 95.58 | I90: Real (taxa fixa por colaborador, confirmada em todas as empresas)
A91: Junho/2026 | B91: Solon Araújo | C91: Segurança do Trabalho | D91: Despesas com SST | E91: TARCIZIO MEIRELES | F91: 2 | G91: 64.54 | H91: =F91*G91 -> 129.08 | I91: Real (taxa fixa por colaborador, confirmada em todas as empresas)
A92: Junho/2026 | B92: Solon Araújo | C92: Benefícios | D92: Gympass | E92: TARCIZIO MEIRELES | F92: 2 | G92: 10.05 | H92: =F92*G92 -> 20.1 | I92: Real (taxa fixa por colaborador, confirmada em todas as empresas)
A93: Junho/2026 | B93: Solon Araújo | C93: Benefícios | D93: Stargrid | E93: TARCIZIO MEIRELES | F93: 2 | G93: 2.07 | H93: =F93*G93 -> 4.14 | I93: Real (taxa fixa por colaborador, confirmada em todas as empresas)
A94: Junho/2026 | B94: Solon Araújo | C94: Estrutura/Infra | D94: Linhas moveis (FIQUE MÓVEL) | E94: TARCIZIO MEIRELES | F94: 2 | G94: 30 | H94: =F94*G94 -> 60 | I94: Real (taxa fixa por colaborador, confirmada em todas as empresas)
A95: Junho/2026 | B95: Solon Araújo | C95: Frota/Combustível | D95: Consumo de combustível | E95: TARCIZIO MEIRELES | F95: 1 | G95: 1447.18 | H95: =F95*G95 -> 1447.18 | I95: Real (cruzado por nome, planilha de combustível)
A96: Junho/2026 | B96: Souza e Silva | C96: Pessoal | D96: Folha Trabalhista com impostos do mês | E96: TARCIZIO MEIRELES | F96: 1 | G96: 11931.77 | H96: =F96*G96 -> 11931.77 | I96: Real (cruzado por nome, 5/5 encontrados)
A97: Junho/2026 | B97: Souza e Silva | C97: Pessoal | D97: Despesas com RH | E97: TARCIZIO MEIRELES | F97: 5 | G97: 28.31 | H97: =F97*G97 -> 141.55 | I97: Real (taxa fixa por colaborador, confirmada em todas as empresas)
... A131: Junho/2026 | B131: Soares e Lins | C131: Estrutura/Infra | D131: Linhas moveis (FIQUE MÓVEL) | E131: VITOR LINS | F131: 1 | G131: 30 | H131: =F131*G131 -> 30 | I131: Real (taxa fixa por colaborador, confirmada em todas as empresas)
A132: Maio/2026 | B132: DTEL | C132: Pessoal | D132: Folha Trabalhista com impostos do mês | E132: ELTHON MENEZES | F132: 1 | G132: 70601.08 | H132: 70601.08 | I132: Real (cruzado por nome, 30/42 encontrados) | Ajustado 24/08/2026: subtraído o custo de folha de Pedro Moreira do Amaral (R$ 3706.20), que passou a ter linha própria de van/kombi, para não contar 2x. | Ajustado 24/08/2026: subtraído o custo de folha de Felipe Lopes de Souza (R$ 4503.24), que passou a ter linha própria de van/kombi, para não contar 2x. | Ajustado 24/08/2026: subtraído o custo de folha de Alvaro Henrique de Sousa (R$ 5488.35), que passou a ter linha própria de van/kombi, para não contar 2x.
A133: Maio/2026 | B133: DTEL | C133: Pessoal | D133: Vale Transporte | E133: ELTHON MENEZES | F133: 1 | G133: 2724.43 | H133: 2724.43 | I133: Estimado (fatia proporcional ao nº de colaboradores da equipe, sem taxa fixa por pessoa), fatia de 39 colaboradores da equipe
A134: Maio/2026 | B134: DTEL | C134: Pessoal | D134: Despesas com RH | E134: ELTHON MENEZES | F134: 39 | G134: 28.31 | H134: 1104.09 | I134: Real (taxa fixa por colaborador, confirmada em todas as empresas)
A135: Maio/2026 | B135: DTEL | C135: Pessoal | D135: Despesas com DP | E135: ELTHON MENEZES | F135: 39 | G135: 47.79 | H135: 1863.81 | I135: Real (taxa fixa por colaborador, confirmada em todas as empresas)
...

Sheet REEMBOLSO GERAL
A1: REEMBOLSO GERAL — CUSTOS POR SETOR E EMPRESA (Base Geral 2026, aba Reembolso Geral)
A2: Extraído da Base Geral 2026.xlsx (aba Reembolso Geral). O Setor já vem cruzado com o nome padrão da Plataforma quando havia correspondência clara com um setor existente em CUSTOS MENSAIS (ex.: RH, Marketing, TIC, Segurança do Trabalho). Setores sem correspondente direto (ex.: Administrativo/taxa de administração, Licitação, Frota, Comercial ambíguo entre Corporativo/Varejo) permaneceram com o nome original — não foram forçados a encaixar em nenhum setor existente. Esta aba é só de referência — não altera nenhum valor de CUSTOS MENSAIS.
A4: Mês | B4: Setor | C4: Descrição do Custo | D4: Empresa | E4: Quantidade | F4: Valor Unitário | G4: Valor Total | H4: Observação (forma de cálculo)
A5: ABRIL/2026 | B5: Adm Atendimento | C5: Adm atendimento presencial | D5: H&A | E5: 13402 | F5: 0.1870984 | G5: 2507.4928 | H5: Cálculo por número de clientes ativos
A6: ABRIL/2026 | B6: Adm Qualidade | C6: Qualidade | D6: H&A | E6: 13402 | F6: 0.20871322 | G6: 2797.1746 | H6: Cálculo por número de clientes ativos
A7: ABRIL/2026 | B7: Atendimento | C7: Material de escritório | D7: DX2 | E7: 0 | F7: 0 | G7: 0 | H7: Capa de carnê
A8: ABRIL/2026 | B8: Atendimento | C8: Material de uso coletivo | D8: DX2 | E8: 16 | F8: 2.85 | G8: 45.6 | H8: Água mineral
A9: ABRIL/2026 | B9: Atendimento | C9: Material de escritório | D9: H&A | E9: 0 | F9: 0 | G9: 0 | H9: Porta panfleto
A10: ABRIL/2026 | B10: Atendimento | C10: Promotor autonomo Erika sonara | D10: H&A | E10: 0 | F10: 0 | G10: 0 | H10: Comissionamento de vendas realizadas na h&a paga pela Dtel fev.
A11: ABRIL/2026 | B11: Atendimento | C11: Material de escritório | D11: Soares e Lins | E11: 0 | F11: 0 | G11: 0 | H11: Porta panfleto
A12: ABRIL/2026 | B12: Atendimento | C12: Material de uso coletivo | D12: Soares e Lins | E12: 10 | F12: 2.85 | G12: 28.5 | H12: Água mineral
A13: ABRIL/2026 | B13: Atendimento | C13: Material de escritório | D13: Soares e Silva | E13: 0 | F13: 0 | G13: 0 | H13: Capa de carnê
A14: ABRIL/2026 | B14: Atendimento | C14: Material de uso coletivo | D14: Soares e Silva | E14: 0 | F14: 0 | G14: 0 | H14: Agua mineral
A15: ABRIL/2026 | B15: Atendimento | C15: Material de escritório | D15: Solon Araújo | E15: 0 | F15: 0 | G15: 0 | H15: Caixa de resma
A16: ABRIL/2026 | B16: Atendimento | C16: Material de uso coletivo | D16: Solon Araújo | E16: 20 | F16: 2.85 | G16: 57 | H16: Água mineral
... A553: JUNHO/2026 | B553: Comercial | C553: Vendas da equipe Soares e lins p/ Dtel | D553: Soares e Lins | E553: -1 | F553: 7.0292308 | G553: -7.0292308 | H553: Vendas comercial varejo.xlsx (maio/2026)
A554: JUNHO/2026 | B554: Comercial | C554: Vendas da equipe Soares e lins p/ solon | D554: Soares e Lins | E554: 0 | F554: 0 | G554: 0
A555: JUNHO/2026 | B555: Comercial | C555: Vendas da equipe voicenet P/ SOARES E LINS | D555: Soares e Lins | E555: 0 | F555: 0 | G555: 0 | H555: Vendas instaladas
A556: JUNHO/2026 | B556: Comercial | C556: Consultas e análises de crédito | D556: Soares e Silva | E556: 601 | F556: 1.86 | G556: 1117.86 | H556: Vendas cadastradas e consultadas pelo argos (Consultas e analise de credito - junho26.xlsx)
A557: JUNHO/2026 | B557: Comercial | C557: Despesa do consultor BARTOLOMEU | D557: Soares e Silva | E557: 3 | F557: 393.04 | G557: 1179.12 | H557: Despesa trabalhista e combustÍvel do consultor dividido pelo total de vendas
A558: JUNHO/2026 | B558: Comercial | C558: Despesa do consultor PAULO MELO | D558: Soares e Silva | E558: 1 | F558: 439.28 | G558: 439.28 | H558: Despesa trabalhista e combustÍvel dividida pela quantidade de vendas
A559: JUNHO/2026 | B559: Comercial | C559: Despesa do consultor PEDRO GREGO | D559: Soares e Silva | E559: 4 | F559: 407.27 | G559: 1629.08 | H559: Despesa trabalhista e combustÍvel dividida pela quantidade de vendas
A560: JUNHO/2026 | B560: Comercial | C560: Despesa do coordenador TIAGO, pela gestão da equipe | D560: Soares e Silva | E560: 1 | F560: 439.04 | G560: 439.04 | H560: Despesa com combustÍvel e utilização de veÍculo dx2
A561: JUNHO/2026 | B561: Comercial | C561: Despesa do coordenador TIAGO, pela gestão da equipe | D561: Soares e Silva | E561: 78 | F561: 33.16 | G561: 2586.48 | H561: Despesa trabalhista e pela quantidade de vendas
A562: JUNHO/2026 | B562: Comercial | C562: Vendas da equipe Dtel porta a porta p/ Soares e silva | D562: Soares e Silva | E562: 0 | F562: 0 | G562: 0
A563: JUNHO/2026 | B563: Comercial | C563: Vendas da equipe H&A para Soares e Silva | D563: Soares e Silva | E563: 1 | F563: 278.60087 | G563: 278.60087 | H563: Vendas comercial varejo.xlsx (maio/2026)
A564: JUNHO/2026 | B564: Comercial | C564: Vendas da equipe Soares e Silva p/ DTEL | D564: Soares e Silva | E564: 0 | F564: 0 | G564: 0
A565: JUNHO/2026 | B565: Comercial | C565: Vendas da equipe voicenet porta a porta p/ Soares e silva | D565: Soares e Silva | E565: 1 | F565: 26.326 | G565: 26.326 | H565: Vendas instaladas
A566: JUNHO/2026 | B566: Comercial | C566: Consultas e análises de crédito | D566: Solon Araújo | E566: 461 | F566: 1.86 | G566: 857.46 | H566: Vendas cadastradas e consultadas pelo argos (Consultas e analise de credito - junho26.xlsx)
A567: JUNHO/2026 | B567: Comercial | C567: Despesa do consultor BARTOLOMEU | D567: Solon Araújo | E567: 4 | F567: 393.04 | G567: 1572.16 | H567: Despesa trabalhista e combustível do consultor dividido pelo total de vendas
A568: JUNHO/2026 | B568: Comercial | C568: Despesa do consultor PAULO MELO | D568: Solon Araújo | E568: 4 | F568: 439.28 | G568: 1757.12 | H568: Despesa trabalhista e combustível dividida pela quantidade de vendas
A569: JUNHO/2026 | B569: Comercial | C569: Despesa do consultor PEDRO GREGO | D569: Solon Araújo | E569: 6 | F569: 407.27 | G569: 2443.62 | H569: Despesa trabalhista e combustível dividida pela quantidade de vendas
A570: JUNHO/2026 | B570: Comercial | C570: Despesa do coordenador TARCIZIO, pela gestão da equipe | D570: Solon Araújo | E570: 1 | F570: 738.92 | G570: 738.92 | H570: Despesa com combustivel e utilização carro dtel
A571: JUNHO/2026 | B571: Comercial | C571: Despesa do coordenador TARCIZIO, pela gestão da equipe | D571: Solon Araújo | E571: 25 | F571: 19.53 | G571: 488.25 | H571: Despesa trabalhista dividida pela quantidade de vendas
A572: JUNHO/2026 | B572: Comercial | C572: Vendas da equipe Dtel porta a porta | D572: Solon Araújo | E572: 21 | F572: 278.60087 | G572: 5850.6183 | H572: Vendas comercial varejo.xlsx (maio/2026)
A573: JUNHO/2026 | B573: Comercial | C573: Vendas da equipe Litoral p/ Dtel | D573: Solon Araújo | E573: 0 | F573: 0 | G573: 0 | H573: Vendas instaladas
A574: JUNHO/2026 | B574: Comercial | C574: Vendas da equipe Voicenet p/ Solon | D574: Solon Araújo | E574: 0 | F574: 0 | G574: 0 | H574: Vendas instaladas
A575: JUNHO/2026 | B575: Comercial | C575: Vendas da equipe da soares e lins para Solon | D575: Solon Araújo | E575: 0 | F575: 0 | G575: 0 | H575: Vendas instaladas
A576: JUNHO/2026 | B576: Comercial | C576: Consultas e análises de crédito | D576: Souza e Silva | E576: 112 | F576: 1.86 | G576: 208.32 | H576: Vendas cadastradas e consultadas pelo argos (Consultas e analise de credito - junho26.xlsx)
... A590: JUNHO/2026 | B590: Comercial | C590: Vendas da equipe Dtel porta a porta | D590: Voicenet | E590: 4 | F590: 278.60087 | G590: 1114.4035 | H590: Vendas comercial varejo.xlsx (maio/2026)
A591: JUNHO/2026 | B591: Comercial | C591: Vendas da equipe H&A p/ voice | D591: Voicenet | E591: 0 | F591: 0 | G591: 0
A592: JUNHO/2026 | B592: Comercial | C592: Vendas da equipe Voicenet para Dtel | D592: Voicenet | E592: -12 | F592: 26.326 | G592: -315.912 | H592: Vendas comercial varejo.xlsx (maio/2026)
A593: JUNHO/2026 | B593: Comercial | C593: Vendas da equipe da Voicenet para soares e silva | D593: Voicenet | E593: -1 | F593: 26.326 | G593: -26.326 | H593: Vendas instaladas
A594: JUNHO/2026 | B594: Comercial | C594: Vendas da equipe voicenet p/ Solon | D594: Voicenet | E594: 0 | F594: 0 | G594: 0
A595: JUNHO/2026 | B595: Configuração | C595: Serviços de configuração e suporte ao Técnico | D595: DX2 | E595: 6445 | F595: 0.25375464 | G595: 1635.4487 | H595: Cálculo por número de clientes ativos
A596: JUNHO/2026 | B596: Configuração | C596: Serviços de configuração e suporte ao Técnico | D596: H&A | E596: 13418 | F596: 0.25375464 | G596: 3404.8798 | H596: Cálculo por número de clientes ativos
A597: JUNHO/2026 | B597: Configuração | C597: Serviços de configuração e suporte ao Técnico | D597: Soares e Lins | E597: 3704 | F597: 0.25375464 | G597: 939.90719 | H597: Cálculo por número de clientes ativos
A598: JUNHO/2026 | B598: Configuração | C598: Serviços de configuração e suporte ao Técnico | D598: Soares e Silva | E598: 6434 | F598: 0.25375464 | G598: 1632.6574 | H598: Cálculo por número de clientes ativos
A599: JUNHO/2026 | B599: Configuração | C599: Serviços de configuração e suporte ao Técnico | D599: Solon Araújo | E599: 14441 | F599: 0.25375464 | G599: 3664.4708 | H599: Cálculo por número de clientes ativos
A600: JUNHO/2026 | B600: Configuração | C600: Serviços de configuração e suporte ao Técnico | D600: Souza e Silva | E600: 4749 | F600: 0.25375464 | G600: 1205.0808 | H600: Cálculo por número de clientes ativos
A601: JUNHO/2026 | B601: Configuração | C601: Serviços de configuração e suporte ao Técnico | D601: Voicenet | E601: 4795 | F601: 0.25375464 | G601: 1216.7535 | H601: Cálculo por número de clientes ativos
A602: JUNHO/2026 | B602: Desenvolvimento | C602: Setor de Desenvolvimento | D602: H&A | E602: 13418 | F602: 0.10589521 | G602: 1420.9019 | H602: Cálculo por número de clientes ativos
A603: JUNHO/2026 | B603: Engenharia | C603: Uso mútuo de Postes | D603: DX2 | E603: 1 | F603: 9145.68 | G603: 9145.68 | H603: Contrato das empresas que está em nome da Dtel
A604: JUNHO/2026 | B604: Engenharia | C604: Uso mútuo de Postes | D604: Soares e Lins | E604: 1 | F604: 3372.11 | G604: 3372.11 | H604: Contrato das empresas que está em nome da Dtel
A605: JUNHO/2026 | B605: Engenharia | C605: Uso mútuo de Postes | D605: Souza e Silva | E605: 1 | F605: 15695.77 | G605: 15695.77 | H605: Contrato das empresas que está em nome da Dtel
A606: JUNHO/2026 | B606: Engenharia | C606: Despesas da equipe de Engenharia | D606: Voicenet | E606: 0 | F606: 0 | G606: 0 | H606: Combustível, alimentação
... A798: JULHO/2026 | B798: Comercial | C798: Vendas da equipe Soares e lins p/ Dtel | D798: Soares e Lins | E798: 0 | F798: 0 | G798: 0 | H798: Vendas comercial varejo.xlsx (junho/2026)
A799: JULHO/2026 | B799: Comercial | C799: Vendas da equipe Soares e lins p/ solon | D799: Soares e Lins | E799: 0 | F799: 0 | G799: 0
A800: JULHO/2026 | B800: Comercial | C800: Vendas da equipe voicenet P/ SOARES E LINS | D800: Soares e Lins | E800: 0 | F800: 0 | G800: 0 | H800: Vendas instaladas
A801: JULHO/2026 | B801: Comercial | C801: Consultas e análises de crédito | D801: Soares e Silva | E801: 669 | F801: 1.86 | G801: 1244.34 | H801: Vendas cadastradas e consultadas pelo argos
A802: JULHO/2026 | B802: Comercial | C802: Despesa do coordenador TIAGO, pela gestão da equipe | D802: Soares e Silva | E802: 1 | F802: 173.46 | G802: 173.46 | H802: Despesa com combustÍvel e utilização de veÍculo dx2
A803: JULHO/2026 | B803: Comercial | C803: Despesa do coordenador TIAGO, pela gestão da equipe | D803: Soares e Silva | E803: 65 | F803: 21.95 | G803: 1426.75 | H803: Despesa trabalhista e pela quantidade de vendas
A804: JULHO/2026 | B804: Comercial | C804: Vendas da equipe Dtel porta a porta p/ Soares e silva | D804: Soares e Silva | E804: 1 | F804: 221.78574 | G804: 221.78574 | H804: Vendas comercial varejo.xlsx (junho/2026)
A805: JULHO/2026 | B805: Comercial | C805: Vendas da equipe H&A para Soares e Silva | D805: Soares e Silva | E805: 2 | F805: 221.78574 | G805: 443.57149 | H805: Vendas comercial varejo.xlsx (junho/2026)
A806: JULHO/2026 | B806: Comercial | C806: Vendas da equipe Soares e Silva p/ DTEL | D806: Soares e Silva | E806: 0 | F806: 0 | G806: 0
A807: JULHO/2026 | B807: Comercial | C807: Vendas da equipe voicenet porta a porta p/ Soares e silva | D807: Soares e Silva | E807: 0 | F807: 0 | G807: 0 | H807: Vendas comercial varejo.xlsx (junho/2026)
A808: JULHO/2026 | B808: Comercial | C808: Consultas e análises de crédito | D808: Solon Araújo | E808: 510 | F808: 1.86 | G808: 948.6 | H808: Vendas cadastradas e consultadas pelo argos
A809: JULHO/2026 | B809: Comercial | C809: Despesa do coordenador TARCIZIO, pela gestão da equipe | D809: Solon Araújo | E809: 1 | F809: 542 | G809: 542 | H809: Despesa com combustivel e utilização carro dtel
A810: JULHO/2026 | B810: Comercial | C810: Despesa do coordenador TARCIZIO, pela gestão da equipe | D810: Solon Araújo | E810: 0 | F810: 0 | G810: 0 | H810: Despesa trabalhista dividida pela quantidade de vendas
A811: JULHO/2026 | B811: Comercial | C811: Vendas da equipe Dtel porta a porta | D811: Solon Araújo | E811: 6 | F811: 221.78574 | G811: 1330.7145 | H811: Vendas comercial varejo.xlsx (junho/2026)
A812: JULHO/2026 | B812: Comercial | C812: Vendas da equipe Voicenet p/ Solon | D812: Solon Araújo | E812: 0 | F812: 0 | G812: 0 | H812: Vendas instaladas
A813: JULHO/2026 | B813: Comercial | C813: Vendas da equipe da soares e lins para Solon | D813: Solon Araújo | E813: 0 | F813: 0 | G813: 0 | H813: Vendas instaladas
A814: JULHO/2026 | B814: Comercial | C814: Vendas da equipe solon p/ Dtel | D814: Solon Araújo | E814: 0 | F814: 0 | G814: 0 | H814: Vendas instaladas
A815: JULHO/2026 | B815: Comercial | C815: Consultas e análises de crédito | D815: Souza e Silva | E815: 154 | F815: 1.86 | G815: 286.44 | H815: Vendas cadastradas e consultadas pelo argos
A816: JULHO/2026 | B816: Comercial | C816: Despesa do coordenador TARCIZIO, pela gestão da equipe | D816: Souza e Silva | E816: 1 | F816: 729 | G816: 729 | H816: Despesa com combustível e utilização carro dtel
A817: JULHO/2026 | B817: Comercial | C817: Despesa do coordenador TARCIZIO, pela gestão da equipe | D817: Souza e Silva | E817: 35 | F817: 18.52 | G817: 648.2 | H817: Despesa trabalhista dividida pela quantidade de vendas
A818: JULHO/2026 | B818: Comercial | C818: Vendas da equipe Dtel porta a porta | D818: Souza e Silva | E818: 0 | F818: 0 | G818: 0 | H818: Vendas instaladas
... A822: JULHO/2026 | B822: Comercial | C822: Vendas da equipe Dtel porta a porta | D822: Voicenet | E822: 5 | F822: 221.78574 | G822: 1108.9287 | H822: Vendas comercial varejo
A823: JULHO/2026 | B823: Comercial | C823: Vendas da equipe H&A p/ voice | D823: Voicenet | E823: 0 | F823: 0 | G823: 0
A824: JULHO/2026 | B824: Comercial | C824: Vendas da equipe Voicenet para Dtel | D824: Voicenet | E824: -8 | F824: 289.27 | G824: -2314.16 | H824: Vendas comercial varejo.xlsx (junho/2026)
A825: JULHO/2026 | B825: Comercial | C825: Vendas da equipe da Voicenet para soares e silva | D825: Voicenet | E825: 0 | F825: 0 | G825: 0 | H825: Vendas instaladas
A826: JULHO/2026 | B826: Comercial | C826: Vendas da equipe voicenet p/ Solon | D826: Voicenet | E826: 0 | F826: 0 | G826: 0
A827: JULHO/2026 | B827: Configuração | C827: Serviços de configuração e suporte ao Técnico | D827: DX2 | E827: 6588 | F827: 0.2 | G827: 1317.6 | H827: Cálculo por número de clientes ativos
A828: JULHO/2026 | B828: Configuração | C828: Serviços de configuração e suporte ao Técnico | D828: H&A | E828: 13530 | F828: 0.2 | G828: 2706 | H828: Cálculo por número de clientes ativos
A829: JULHO/2026 | B829: Configuração | C829: Serviços de configuração e suporte ao Técnico | D829: Soares e Lins | E829: 3765 | F829: 0.2 | G829: 753 | H829: Cálculo por número de clientes ativos
A830: JULHO/2026 | B830: Configuração | C830: Serviços de configuração e suporte ao Técnico | D830: Soares e Silva | E830: 6568 | F830: 0.2 | G830: 1313.6 | H830: Cálculo por número de clientes ativos
A831: JULHO/2026 | B831: Configuração | C831: Serviços de configuração e suporte ao Técnico | D831: Solon Araújo | E831: 14689 | F831: 0.2 | G831: 2937.8 | H831: Cálculo por número de clientes ativos
A832: JULHO/2026 | B832: Configuração | C832: Serviços de configuração e suporte ao Técnico | D832: Souza e Silva | E832: 4805 | F832: 0.2 | G832: 961 | H832: Cálculo por número de clientes ativos
A833: JULHO/2026 | B833: Configuração | C833: Serviços de configuração e suporte ao Técnico | D833: Voicenet | E833: 4806 | F833: 0.2 | G833: 961.2 | H833: Cálculo por número de clientes ativos
A834: JULHO/2026 | B834: Desenvolvimento | C834: Setor de Desenvolvimento | D834: H&A | E834: 13530 | F834: 0.10105722 | G834: 1367.3042 | H834: Cálculo por número de clientes ativos
A835: JULHO/2026 | B835: Engenharia | C835: Uso mútuo de Postes | D835: DX2 | E835: 1579 | F835: 7.19 | G835: 11353.01 | H835: Contrato das empresas que está em nome da Dtel
A836: JULHO/2026 | B836: Engenharia | C836: Uso mútuo de Postes | D836: Soares e Lins | E836: 469 | F836: 7.19 | G836: 3372.11 | H836: Contrato das empresas que está em nome da Dtel
A837: JULHO/2026 | B837: Engenharia | C837: Uso mútuo de Postes | D837: Soares e Silva | E837: 727 | F837: 7.2044429 | G837: 5237.63 | H837: Contrato das empresas que está em nome da Dtel
A838: JULHO/2026 | B838: Engenharia | C838: Uso mútuo de Postes | D838: Solon Araújo | E838: 2981 | F838: 7.19 | G838: 21433.39 | H838: Contrato das empresas que está em nome da Dtel
... A1216: JULHO/2026 | B1216: Administrativo | C1216: Custo do departamento Administrativo | D1216: DX2 | E1216: 34 | F1216: 21.812927 | G1216: 741.6395 | H1216: Cálculo por número de funcionários ativos
A1217: JULHO/2026 | B1217: Administrativo | C1217: Custo do departamento Administrativo | D1217: H&A | H1217: Cálculo por número de funcionários ativos (sem quantidade exata para H&A)
A1218: JULHO/2026 | B1218: Administrativo | C1218: Custo do departamento Administrativo | D1218: Solon Araújo | E1218: 47 | F1218: 21.812927 | G1218: 1025.2076 | H1218: Cálculo por número de funcionários ativos
A1219: JULHO/2026 | B1219: Administrativo | C1219: Custo do departamento Administrativo | D1219: Soares e Lins | E1219: 11 | F1219: 21.812927 | G1219: 239.94219 | H1219: Cálculo por número de funcionários ativos
A1220: JULHO/2026 | B1220: Administrativo | C1220: Custo do departamento Administrativo | D1220: Soares e Silva | E1220: 50 | F1220: 21.812927 | G1220: 1090.6463 | H1220: Cálculo por número de funcionários ativos
A1221: JULHO/2026 | B1221: Administrativo | C1221: Custo do departamento Administrativo | D1221: Souza e Silva | E1221: 18 | F1221: 21.812927 | G1221: 392.63268 | H1221: Cálculo por número de funcionários ativos
...
